Workbook
Name CriticalList: Dropdown_Lists!$C$2:$C$3
Name DirectionList: Dropdown_Lists!$B$2:$B$4
Name GateStatusList: Dropdown_Lists!$E$2:$E$6
Name MetricTypeList: Dropdown_Lists!$A$2:$A$3
Name Period: Dropdown_Lists!$H$2:$H$5
Name ReviewStatusList: Dropdown_Lists!$F$2:$F$4
Name TimelineStatusList: Dropdown_Lists!$G$2:$G$6
Name UnitList: Dropdown_Lists!$D$2:$D$8

Sheet Instructions
A1: Gate Definition & Timeline Pack for PIC
A3: Sumber | B3: Disusun dari file gate_go_no_go_cards (3).html yang diunggah user pada 2026-04-20.
A4: Tujuan workbook | B4: Untuk dibagikan ke PIC agar mereka melengkapi definisi, evidence, status gate, dan update timeline per project.
A5: Bobot gate | B5: Gate 1 = 25%, Gate 2 = 30%, Gate 3 = 25%, Gate 4 = 20%.
A6: Hard gate | B6: Gate 1 dan Gate 3 adalah hard gate. Jika gagal, project tidak layak lanjut meskipun gate lain baik.
A7: Cara pakai | B7: Isi progres aktual hanya di Timeline_Tasks (PIC Start Date dan PIC Actual % Input). Timeline_Periods dan Progress % project akan roll-up otomatis.
A10: Ringkasan Workbook
A11: Total project | B11: =COUNTA(Project_Summary!A2:A200) -> 6
A12: Total gate | B12: =COUNTA(Gate_Definitions!A2:A500) -> 499
A13: Total hard gate | B13: =COUNTIF(Gate_Definitions!D2:D500,"Yes") -> 6
A14: Total timeline task | B14: =COUNTA(Timeline_Tasks!A2:A1000) -> 999
A17: Dropdown reference
A18: Gate status (PIC) | B18: Pass,Conditional,Fail,Not Started
A19: Timeline progress input | B19: Gunakan PIC Actual % Input pada Timeline_Tasks. Tidak lagi memakai status task sebagai penggerak progres.
A20: Reviewer status | B20: Open,In Review,Closed
A22: Panduan Definisi Kolom
A23: Kolom / Istilah | B23: Arti / definisi | C23: Cara isi / contoh | D23: Berlaku di sheet
A24: Hard Gate | B24: Gate kritikal. Jika statusnya Fail, proyek secara prinsip tidak boleh lanjut walaupun gate lain baik. | C24: Di file ini: Gate 1 dan Gate 3 adalah hard gate. | D24: Gate_Definitions
A25: Metric Type | B25: Jenis metric untuk evaluasi. "range" berarti nilai numerik, "select" berarti pilihan status. | C25: range = 92%; select = Pass / Conditional / Fail. | D25: Gate_Metrics
A26: Direction | B26: Arah penilaian metric. "high" berarti makin besar makin baik, "low" berarti makin kecil makin baik. | C26: Precision biasanya high; latency biasanya low. | D26: Gate_Metrics
A27: Current Value | B27: Nilai aktual metric saat ini dari hasil pilot, pengujian, atau implementasi lapangan. | C27: Contoh: uptime 99.1, latency 165, ROI 183. | D27: Gate_Metrics
A28: Pass Threshold | B28: Ambang minimum agar metric dinilai Pass. | C28: Jika direction=high, nilai aktual harus sama atau lebih tinggi dari angka ini. Jika direction=low, nilai aktual harus sama atau lebih rendah dari angka ini. | D28: Gate_Metrics
A29: Conditional Threshold | B29: Ambang tengah untuk status Conditional bila belum mencapai Pass tetapi masih dapat diterima sementara dengan tindak lanjut. | C29: Biasanya dipakai sebagai status warning / perlu improvement. | D29: Gate_Metrics
A30: Min | B30: Batas bawah rentang input untuk metric numerik. | C30: Contoh: 0, 50, atau -100 sesuai karakter metric. | D30: Gate_Metrics
A31: Max | B31: Batas atas rentang input untuk metric numerik. | C31: Contoh: 100 untuk persen, 400 untuk latency, 300 untuk net saving. | D31: Gate_Metrics
A32: Step | B32: Interval kenaikan/perubahan nilai input untuk metric bertipe range. | C32: step 1 = berubah per 1; step 0.1 = berubah per 0,1; step 5 = berubah per 5. | D32: Gate_Metrics
A33: PIC Status | B33: Status penilaian atau update yang diisi PIC. | C33: Gunakan opsi yang sudah disiapkan seperti Pass / Conditional / Fail / Not Started. | D33: Gate_Definitions; Timeline sheets
A34: Reviewer Status | B34: Status review dari evaluator/reviewer setelah PIC mengisi update. | C34: Open / In Review / Closed. | D34: Gate_Definitions; Timeline_Periods
... A38: Evidence Link / Folder | B38: Link folder, dokumen, file bukti, atau referensi evidence pendukung status yang diisi PIC. | C38: Bisa berupa Google Drive folder, dokumen test, minutes, screenshot, atau evidence lain. | D38: Gate_Definitions; Gate_Metrics; Timeline_Tasks
A40: Panduan pengisian kolom kuning
A41: Sheet | B41: Kolom kuning yang diisi PIC | C41: Tujuan | D41: Catatan
A42: Gate_Definitions | B42: PIC Status; PIC Notes / Key Findings; Evidence Link / Folder; PIC Owner; Target Close Date; Reviewer Status | C42: Mengisi hasil evaluasi per gate pada level narasi / governance. | D42: Gunakan untuk menjelaskan status gate secara ringkas namun jelas.
A43: Gate_Metrics | B43: PIC Current Finding; PIC Evidence / Source; PIC Comment; Metric Status | C43: Mengisi kondisi aktual tiap metric dan bukti pendukungnya. | D43: Metric Status sebaiknya konsisten dengan nilai aktual vs threshold.
A44: Timeline_Periods | B44: PIC Update Summary; PIC Risks / Dependencies; PIC Owner; Target Date; Reviewer Status | C44: Mengisi narasi kemajuan per phase/periode. Progress % terhitung otomatis dari Timeline_Tasks. | D44: Jangan input progress manual di sini.
A45: Timeline_Tasks | B45: PIC Actual Owner; PIC Start Date; PIC Actual % Input; PIC Progress Note; Evidence Link; Target Date; Dependency / Blocker | C45: Satu-satunya input progres numerik. Nilai ini yang menggerakkan progress phase/period/project. | D45: Isi 0-100 atau 0%-100%; workbook akan normalisasi otomatis.
A47: Catatan: step hanya relevan untuk metric_type = range. Untuk metric_type = select, cukup gunakan pilihan status seperti Pass / Conditional / Fail.
A49: Update workbook | B49: Ditambahkan kolom Need Support (PIC) pada Project_Summary, dropdown untuk Metric Type / Direction / Critical / Unit pada Gate_Metrics, dan sheet khusus untuk setiap project.
A50: Cara pakai sheet per project | B50: Setiap project sekarang memiliki 1 sheet sendiri untuk dibagikan ke PIC. Sheet gabungan tetap dipertahankan sebagai database all project / consolidated view.
A51: Dropdown Metric Type | B51: Pilihan: range, select. Gunakan range untuk angka/continuous metric, dan select untuk pass/conditional/fail.
A52: Dropdown Direction | B52: Pilihan: high, low. high = makin tinggi makin baik; low = makin rendah makin baik. Boleh dikosongkan jika Metric Type = select.
A53: Dropdown Critical | B53: Pilihan: Yes, No. Yes berarti metric kritikal dan biasanya memengaruhi keputusan gate secara langsung.
A54: Dropdown Unit | B54: Pilihan: %, ms, min, pts, /hr, M IDR, mo. Boleh dikosongkan jika Metric Type = select.
A56: Update layout | B56: Pada tiap sheet project, tabel Gate Definitions, Gate Metrics, Timeline Periods, dan Timeline Tasks diposisikan ke kanan (side-by-side) agar PIC bisa menambah row tanpa menabrak section di bawahnya.
A57: Dropdown tambahan | B57: Dropdown tersedia untuk PIC Status, Reviewer Status, Timeline Status, Metric Type, Direction, Critical, dan Unit. Dropdown diterapkan sampai row 2000 pada database gabungan.
A58: Dependency timeline | B58: Progress tidak lagi dipetakan dari status. Roll-up timeline hanya berasal dari PIC Actual % Input pada Timeline_Tasks.
A59: Roll-up period & project | B59: Period Progress % dihitung sebagai rata-rata Task Progress % (normalized) untuk kombinasi Project + Roadmap Period + Phase. Progress % project dihitung sebagai rata-rata Period Progress % per project.
A60: Input utama baru | B60: Timeline_Tasks!I (PIC Actual % Input) menerima angka 0-100 atau format persen. Timeline_Tasks!N menormalkan nilai menjadi persen 0%-100% untuk formula roll-up.
A61: Status period | B61: Period Status sekarang otomatis: Done jika 100%, Progress jika >0%, Plan jika 0%.
A63: NEW LOGIC: Database sheets auto-generate from project sheets
A64: Isi data hanya pada sheet masing-masing project.
A65: Sheet Project_Summary, Gate_Definitions, Gate_Metrics, Timeline_Periods, dan Timeline_Tasks sekarang auto-update dari sheet project.
A66: Jika PIC menambah / mengubah data pada tab project, database gabungan akan ikut berubah otomatis.
A67: Jangan edit sheet database gabungan secara manual karena isinya berasal dari formula reference.

Sheet Project_Summary
A1: Project | B1: Subtitle / Context | C1: Pilot Area | D1: Support Needed | E1: Current Phase | F1: Progress % | G1: Current Period | H1: Next Milestone | I1: Need Support (PIC)
A2: ='Arcas HD'!$B$5 -> Arcas HD | B2: ='Arcas HD'!$B$6 -> Heavy automation use case with high dependency on network, ROC monitoring, and safe fallback control. | C2: ='Arcas HD'!$F$5 -> PAMA BMO2, MTN SMO | D2: ='Arcas HD'!$F$6 -> kebutuhan akomodasi mesh untuk teknisi yang akan menginap di pama dan mtn awal mei, assist terhadap kebutuhan server dan scurity untuk streaming, tahap awal apakah bisa di fasilitasi maintech. | E2: ='Arcas HD'!$B$7 -> Pilot proving & controlled expansion | F2: ='Arcas HD'!$F$7 -> 0.425 | G2: ='Arcas HD'!$B$8 -> Apr–Jun 2026 | H2: ='Arcas HD'!$F$8 -> 0 | I2: ='Arcas HD'!$B$9 -> PAMA dan MTN
A3: ='MGD PC'!$B$5 -> MGD PC | B3: ='MGD PC'!$B$6 -> Precision-guidance pilot where technical accuracy and field consistency are more critical than raw ROI alone. | C3: ='MGD PC'!$F$5 -> PAMA BMO2 | D3: ='MGD PC'!$F$6 -> Positioning quality, operator interface, supervised pilot protocol | E3: ='MGD PC'!$B$7 -> Accuracy stabilization | F3: ='MGD PC'!$F$7 -> 0.53333333 | G3: ='MGD PC'!$B$8 -> Apr–Jun 2026 | H3: ='MGD PC'!$F$8 -> Guidance accuracy closeout for broader field test | I3: ='MGD PC'!$B$9 -> 0
A4: ='Remote Pump'!$B$5 -> Remote Pump | B4: ='Remote Pump'!$B$6 -> Remote operation pilot emphasizing interlock integrity, fail-safe response, and exposure reduction in pump areas. | C4: ='Remote Pump'!$F$5 -> BC SMO - ACI, BC BMO1 - PMO | D4: ='Remote Pump'!$F$6 -> 5G / telemetry network, PLC integration, remote command governance | E4: ='Remote Pump'!$B$7 -> Functional validation & availability proving | F4: ='Remote Pump'!$F$7 | G4: ='Remote Pump'!$B$8 -> Apr–Jun 2026 | H4: ='Remote Pump'!$F$8 -> Interlock sign-off and rollout readiness | I4: ='Remote Pump'!$B$9 -> 0
A5: ='Hauling Fleet Management'!$B$5 -> Hauling Fleet Management | B5: ='Hauling Fleet Management'!$B$6 -> Optimization pilot where dispatch quality, queue reduction, and utilization improvement drive the business case. | C5: ='Hauling Fleet Management'!$F$5 -> MTL BMO1 | D5: ='Hauling Fleet Management'!$F$6 -> Fleet data pipeline, dispatch integration, performance dashboard | E5: ='Hauling Fleet Management'!$B$7 -> Optimization scaling | F5: ='Hauling Fleet Management'!$F$7 | G5: ='Hauling Fleet Management'!$B$8 -> Apr–Jun 2026 | H5: ='Hauling Fleet Management'!$F$8 -> Portfolio-scale dispatch recommendation | I5: ='Hauling Fleet Management'!$B$9 -> 0
A6: ='Mining Eyes Analytics'!$B$5 -> Mining Eyes Analytics | B6: ='Mining Eyes Analytics'!$B$6 -> AI surveillance and analytics pilot where assurance value can be as important as direct cash ROI. | C6: ='Mining Eyes Analytics'!$F$5 -> PAMA BMO2, PAMA GMO, MTN SMO | D6: ='Mining Eyes Analytics'!$F$6 -> 5G infrastructure, cloud, surveillance dashboard (HRZ) | E6: ='Mining Eyes Analytics'!$B$7 -> Coverage improvement & workflow hardening | F6: ='Mining Eyes Analytics'!$F$7 | G6: ='Mining Eyes Analytics'!$B$8 -> Apr–Jun 2026 | H6: ='Mining Eyes Analytics'!$F$8 -> False positive reduction and closure workflow maturity | I6: ='Mining Eyes Analytics'!$B$9 -> 0
A7: ='Remote Dozer'!$B$5 -> Remote Dozer | B7: ='Remote Dozer'!$B$6 -> Remote dozer pilot with strong linkage between technical readiness, safe remote operation, and direct economical value from fuel and efficiency improvement. | C7: ='Remote Dozer'!$F$5 -> Kalimantan OB Disposal | D7: ='Remote Dozer'!$F$6 -> 5G network, remote control station, video telemetry, autonomous zone & dashboard | E7: ='Remote Dozer'!$B$7 -> Integrated readiness and economic proving | F7: ='Remote Dozer'!$F$7 -> 0.75 | G7: ='Remote Dozer'!$B$8 -> Apr–Jun 2026 | H7: ='Remote Dozer'!$F$8 -> Technical + economic pack for scale-up decision | I7: ='Remote Dozer'!$B$9 -> 0

Sheet Gate_Definitions
A1: Project | B1: Gate | C1: Gate Title | D1: Hard Gate | E1: Gate Definition | F1: Project-specific Explanation | G1: What This Gate Confirms | H1: What PIC Needs to Fill | I1: Original Caption | J1: PIC Status | K1: PIC Notes / Key Findings | L1: Evidence Link / Folder | M1: PIC Owner | N1: Target Close Date | O1: Reviewer Status
A2: =IF('Arcas HD'!$A13="","",'Arcas HD'!A13) -> Arcas HD | B2: =IF('Arcas HD'!$A13="","",'Arcas HD'!B13) -> Gate 1 | C2: =IF('Arcas HD'!$A13="","",'Arcas HD'!C13) -> Technical Feasibility | D2: =IF('Arcas HD'!$A13="","",'Arcas HD'!D13) -> Yes | E2: =IF('Arcas HD'!$A13="","",'Arcas HD'!E13) -> Menilai kelayakan teknis dasar solusi sebelum pilot dilanjutkan atau diperluas. | F2: =IF('Arcas HD'!$A13="","",'Arcas HD'!F13) -> Untuk proyek Arcas HD, gate ini fokus pada network readiness, stability, and end-to-end integration. | G2: =IF('Arcas HD'!$A13="","",'Arcas HD'!G13) -> Kesiapan infrastruktur, integrasi sistem, kualitas data/sinyal, stabilitas teknis, uptime, latency, dan reliability. | H2: =IF('Arcas HD'!$A13="","",'Arcas HD'!H13) -> Lengkapi evidence hasil uji teknis, gap teknis terbuka, mitigasi, dan rekomendasi readiness. | I2: =IF('Arcas HD'!$A13="","",'Arcas HD'!I13) -> Network readiness, stability, and end-to-end integration. | J2: =IF('Arcas HD'!$A13="","",'Arcas HD'!#REF!) -> #REF! | K2: =IF('Arcas HD'!$A13="","",'Arcas HD'!K13) -> Kamera front/disposal berfungsi baik (siang/malam). Frekuensi LiDAR tidak stabil (debu & gangguan grounding). Uji coba menggunakan asumsi jarak 6.4m. Menunggu perbaikan power & grounding di WS. | L2: =IF('Arcas HD'!$A13="","",'Arcas HD'!L13) -> https://canva.link/59bd8vwqnm3t9r4 | M2: =IF('Arcas HD'!$A13="","",'Arcas HD'!M13) -> pak ridho | N2: =IF('Arcas HD'!$A13="","",'Arcas HD'!N13) -> juni week 1 | O2: =IF('Arcas HD'!$A13="","",'Arcas HD'!O13) -> in review
A3: =IF('Arcas HD'!$A14="","",'Arcas HD'!A14) -> Arcas HD | B3: =IF('Arcas HD'!$A14="","",'Arcas HD'!B14) -> Gate 2 | C3: =IF('Arcas HD'!$A14="","",'Arcas HD'!C14) -> Performance / Effectiveness | D3: =IF('Arcas HD'!$A14="","",'Arcas HD'!D14) -> Yes | E3: =IF('Arcas HD'!$A14="","",'Arcas HD'!E14) -> Membuktikan bahwa solusi memberi hasil operasional yang relevan dengan tujuan proyek. | F3: =IF('Arcas HD'!$A14="","",'Arcas HD'!F14) -> Untuk proyek Arcas HD, gate ini fokus pada accuracy, intervention quality, and stability across shifts. | G3: =IF('Arcas HD'!$A14="","",'Arcas HD'!G14) -> Akurasi, efektivitas, availability, pengurangan loss, peningkatan produktivitas, atau manfaat performa lain sesuai use case. | H3: =IF('Arcas HD'!$A14="","",'Arcas HD'!H14) -> Lengkapi baseline vs actual, hasil pilot, variasi performa, akar masalah, dan action plan. | I3: =IF('Arcas HD'!$A14="","",'Arcas HD'!I14) -> Accuracy, intervention quality, and stability across shifts. | J3: =IF('Arcas HD'!$A14="","",'Arcas HD'!#REF!) -> #REF! | K3: =IF('Arcas HD'!$A14="","",'Arcas HD'!K14) -> Model YOLO 11 terbukti jauh lebih baik dan responsif dari YOLO 8, meskipun terdapat FPS delay 1 detik dari respon real-time. Alarm berbunyi sesuai limiter target. | L3: =IF('Arcas HD'!$A14="","",'Arcas HD'!L14) -> https://canva.link/59bd8vwqnm3t9r4 | M3: =IF('Arcas HD'!$A14="","",'Arcas HD'!M14) -> pak ridho | N3: =IF('Arcas HD'!$A14="","",'Arcas HD'!N14) -> juni week 1 | O3: =IF('Arcas HD'!$A14="","",'Arcas HD'!O14) -> in review
A4: =IF('Arcas HD'!$A15="","",'Arcas HD'!A15) -> Arcas HD | B4: =IF('Arcas HD'!$A15="","",'Arcas HD'!B15) -> Gate 3 | C4: =IF('Arcas HD'!$A15="","",'Arcas HD'!C15) -> Safety Case & Procedure | D4: =IF('Arcas HD'!$A15="","",'Arcas HD'!D15) -> No | E4: =IF('Arcas HD'!$A15="","",'Arcas HD'!E15) -> Memastikan proyek aman dijalankan dan governance operasionalnya siap. | F4: =IF('Arcas HD'!$A15="","",'Arcas HD'!F15) -> Untuk proyek Arcas HD, gate ini fokus pada emergency stop, override, sop, handover, and drill readiness. | G4: =IF('Arcas HD'!$A15="","",'Arcas HD'!G15) -> SOP, override, fail-safe, escalation path, audit trail, handover, interlock, dan penutupan risiko kritikal. | H4: =IF('Arcas HD'!$A15="","",'Arcas HD'!H15) -> Lengkapi status SOP, hasil simulasi/drill, kontrol keselamatan, approval safety, dan gap residual. | I4: =IF('Arcas HD'!$A15="","",'Arcas HD'!I15) -> Emergency stop, override, SOP, handover, and drill readiness. | J4: =IF('Arcas HD'!$A15="","",'Arcas HD'!#REF!) -> #REF! | K4: =IF('Arcas HD'!$A15="","",'Arcas HD'!K15) -> Sistem peringatan valid direspon oleh operator HD. Tahap selanjutnya akan fokus pada pengujian pengereman otomatis (brake) setelah unit keluar dari WS. | L4: =IF('Arcas HD'!$A15="","",'Arcas HD'!L15) -> https://canva.link/59bd8vwqnm3t9r4 | M4: =IF('Arcas HD'!$A15="","",'Arcas HD'!M15) -> pak ridho | N4: =IF('Arcas HD'!$A15="","",'Arcas HD'!N15) -> juni week 1 | O4: =IF('Arcas HD'!$A15="","",'Arcas HD'!O15) -> open
A5: =IF('Arcas HD'!$A16="","",'Arcas HD'!A16) -> Arcas HD | B5: =IF('Arcas HD'!$A16="","",'Arcas HD'!B16) -> Gate 4 | C5: =IF('Arcas HD'!$A16="","",'Arcas HD'!C16) -> Business / Assurance | D5: =IF('Arcas HD'!$A16="","",'Arcas HD'!D16) -> No | E5: =IF('Arcas HD'!$A16="","",'Arcas HD'!E16) -> Menilai kelayakan scale-up dari sisi bisnis, assurance, atau keekonomian. | F5: =IF('Arcas HD'!$A16="","",'Arcas HD'!F16) -> Untuk proyek Arcas HD, gate ini fokus pada exposure reduction, downtime prevention, and scale rationale. | G5: =IF('Arcas HD'!$A16="","",'Arcas HD'!G16) -> Nilai bisnis, reduction of exposure/loss, assurance value, economic case, payback, ROI, atau justification deployment lebih luas. | H5: =IF('Arcas HD'!$A16="","",'Arcas HD'!H16) -> Lengkapi manfaat terukur, asumsi bisnis/ekonomi, alasan scale-up, risiko bisnis, dan rekomendasi akhir. | I5: =IF('Arcas HD'!$A16="","",'Arcas HD'!I16) -> Exposure reduction, downtime prevention, and scale rationale. | J5: =IF('Arcas HD'!$A16="","",'Arcas HD'!#REF!) -> #REF! | K5: =IF('Arcas HD'!$A16="","",'Arcas HD'!K16) -> Belum dapat dievaluasi. Menunggu full system (termasuk brake) selesai terintegrasi | L5: =IF('Arcas HD'!$A16="","",'Arcas HD'!L16) -> https://canva.link/59bd8vwqnm3t9r4 | M5: =IF('Arcas HD'!$A16="","",'Arcas HD'!M16) -> pak ridho | N5: =IF('Arcas HD'!$A16="","",'Arcas HD'!N16) -> juni week 4 | O5: =IF('Arcas HD'!$A16="","",'Arcas HD'!O16) -> open
A6: =IF('Arcas HD'!$A17="","",'Arcas HD'!A17) -> Arcas HD | B6: =IF('Arcas HD'!$A17="","",'Arcas HD'!B17) -> 0 | C6: =IF('Arcas HD'!$A17="","",'Arcas HD'!C17) -> 0 | D6: =IF('Arcas HD'!$A17="","",'Arcas HD'!D17) -> 0 | E6: =IF('Arcas HD'!$A17="","",'Arcas HD'!E17) -> 0 | F6: =IF('Arcas HD'!$A17="","",'Arcas HD'!F17) -> 0 | G6: =IF('Arcas HD'!$A17="","",'Arcas HD'!G17) -> 0 | H6: =IF('Arcas HD'!$A17="","",'Arcas HD'!H17) -> 0 | ... O6: =IF('Arcas HD'!$A17="","",'Arcas HD'!O17) -> 0
A7: =IF('Arcas HD'!$A18="","",'Arcas HD'!A18) -> Arcas HD | B7: =IF('Arcas HD'!$A18="","",'Arcas HD'!B18) -> 0 | C7: =IF('Arcas HD'!$A18="","",'Arcas HD'!C18) -> 0 | D7: =IF('Arcas HD'!$A18="","",'Arcas HD'!D18) -> 0 | E7: =IF('Arcas HD'!$A18="","",'Arcas HD'!E18) -> 0 | F7: =IF('Arcas HD'!$A18="","",'Arcas HD'!F18) -> 0 | G7: =IF('Arcas HD'!$A18="","",'Arcas HD'!G18) -> 0 | H7: =IF('Arcas HD'!$A18="","",'Arcas HD'!H18) -> 0 | ... O7: =IF('Arcas HD'!$A18="","",'Arcas HD'!O18) -> 0
A8: =IF('Arcas HD'!$A19="","",'Arcas HD'!A19) -> Arcas HD | B8: =IF('Arcas HD'!$A19="","",'Arcas HD'!B19) -> 0 | C8: =IF('Arcas HD'!$A19="","",'Arcas HD'!C19) -> 0 | D8: =IF('Arcas HD'!$A19="","",'Arcas HD'!D19) -> 0 | E8: =IF('Arcas HD'!$A19="","",'Arcas HD'!E19) -> 0 | F8: =IF('Arcas HD'!$A19="","",'Arcas HD'!F19) -> 0 | G8: =IF('Arcas HD'!$A19="","",'Arcas HD'!G19) -> 0 | H8: =IF('Arcas HD'!$A19="","",'Arcas HD'!H19) -> 0 | ... O8: =IF('Arcas HD'!$A19="","",'Arcas HD'!O19) -> 0
A9: =IF('Arcas HD'!$A20="","",'Arcas HD'!A20) -> Arcas HD | B9: =IF('Arcas HD'!$A20="","",'Arcas HD'!B20) -> 0 | C9: =IF('Arcas HD'!$A20="","",'Arcas HD'!C20) -> 0 | D9: =IF('Arcas HD'!$A20="","",'Arcas HD'!D20) -> 0 | E9: =IF('Arcas HD'!$A20="","",'Arcas HD'!E20) -> 0 | F9: =IF('Arcas HD'!$A20="","",'Arcas HD'!F20) -> 0 | G9: =IF('Arcas HD'!$A20="","",'Arcas HD'!G20) -> 0 | H9: =IF('Arcas HD'!$A20="","",'Arcas HD'!H20) -> 0 | ... O9: =IF('Arcas HD'!$A20="","",'Arcas HD'!O20) -> 0
A10: =IF('Arcas HD'!$A21="","",'Arcas HD'!A21) -> Arcas HD | B10: =IF('Arcas HD'!$A21="","",'Arcas HD'!B21) -> 0 | C10: =IF('Arcas HD'!$A21="","",'Arcas HD'!C21) -> 0 | D10: =IF('Arcas HD'!$A21="","",'Arcas HD'!D21) -> 0 | E10: =IF('Arcas HD'!$A21="","",'Arcas HD'!E21) -> 0 | F10: =IF('Arcas HD'!$A21="","",'Arcas HD'!F21) -> 0 | G10: =IF('Arcas HD'!$A21="","",'Arcas HD'!G21) -> 0 | H10: =IF('Arcas HD'!$A21="","",'Arcas HD'!H21) -> 0 | ... O10: =IF('Arcas HD'!$A21="","",'Arcas HD'!O21) -> 0
A11: =IF('Arcas HD'!$A22="","",'Arcas HD'!A22) -> Arcas HD | B11: =IF('Arcas HD'!$A22="","",'Arcas HD'!B22) -> 0 | C11: =IF('Arcas HD'!$A22="","",'Arcas HD'!C22) -> 0 | D11: =IF('Arcas HD'!$A22="","",'Arcas HD'!D22) -> 0 | E11: =IF('Arcas HD'!$A22="","",'Arcas HD'!E22) -> 0 | F11: =IF('Arcas HD'!$A22="","",'Arcas HD'!F22) -> 0 | G11: =IF('Arcas HD'!$A22="","",'Arcas HD'!G22) -> 0 | H11: =IF('Arcas HD'!$A22="","",'Arcas HD'!H22) -> 0 | ... O11: =IF('Arcas HD'!$A22="","",'Arcas HD'!O22) -> 0
A12: =IF('Arcas HD'!$A23="","",'Arcas HD'!A23) -> Arcas HD | B12: =IF('Arcas HD'!$A23="","",'Arcas HD'!B23) -> 0 | C12: =IF('Arcas HD'!$A23="","",'Arcas HD'!C23) -> 0 | D12: =IF('Arcas HD'!$A23="","",'Arcas HD'!D23) -> 0 | E12: =IF('Arcas HD'!$A23="","",'Arcas HD'!E23) -> 0 | F12: =IF('Arcas HD'!$A23="","",'Arcas HD'!F23) -> 0 | G12: =IF('Arcas HD'!$A23="","",'Arcas HD'!G23) -> 0 | H12: =IF('Arcas HD'!$A23="","",'Arcas HD'!H23) -> 0 | ... O12: =IF('Arcas HD'!$A23="","",'Arcas HD'!O23) -> 0
A13: =IF('Arcas HD'!$A24="","",'Arcas HD'!A24) -> Arcas HD | B13: =IF('Arcas HD'!$A24="","",'Arcas HD'!B24) -> 0 | C13: =IF('Arcas HD'!$A24="","",'Arcas HD'!C24) -> 0 | D13: =IF('Arcas HD'!$A24="","",'Arcas HD'!D24) -> 0 | E13: =IF('Arcas HD'!$A24="","",'Arcas HD'!E24) -> 0 | F13: =IF('Arcas HD'!$A24="","",'Arcas HD'!F24) -> 0 | G13: =IF('Arcas HD'!$A24="","",'Arcas HD'!G24) -> 0 | H13: =IF('Arcas HD'!$A24="","",'Arcas HD'!H24) -> 0 | ... O13: =IF('Arcas HD'!$A24="","",'Arcas HD'!O24) -> 0
A14: =IF('Arcas HD'!$A25="","",'Arcas HD'!A25) -> Arcas HD | B14: =IF('Arcas HD'!$A25="","",'Arcas HD'!B25) -> 0 | C14: =IF('Arcas HD'!$A25="","",'Arcas HD'!C25) -> 0 | D14: =IF('Arcas HD'!$A25="","",'Arcas HD'!D25) -> 0 | E14: =IF('Arcas HD'!$A25="","",'Arcas HD'!E25) -> 0 | F14: =IF('Arcas HD'!$A25="","",'Arcas HD'!F25) -> 0 | G14: =IF('Arcas HD'!$A25="","",'Arcas HD'!G25) -> 0 | H14: =IF('Arcas HD'!$A25="","",'Arcas HD'!H25) -> 0 | ... O14: =IF('Arcas HD'!$A25="","",'Arcas HD'!O25) -> 0
A15: =IF('Arcas HD'!$A26="","",'Arcas HD'!A26) -> Arcas HD | B15: =IF('Arcas HD'!$A26="","",'Arcas HD'!B26) -> 0 | C15: =IF('Arcas HD'!$A26="","",'Arcas HD'!C26) -> 0 | D15: =IF('Arcas HD'!$A26="","",'Arcas HD'!D26) -> 0 | E15: =IF('Arcas HD'!$A26="","",'Arcas HD'!E26) -> 0 | F15: =IF('Arcas HD'!$A26="","",'Arcas HD'!F26) -> 0 | G15: =IF('Arcas HD'!$A26="","",'Arcas HD'!G26) -> 0 | H15: =IF('Arcas HD'!$A26="","",'Arcas HD'!H26) -> 0 | ... O15: =IF('Arcas HD'!$A26="","",'Arcas HD'!O26) -> 0
A16: =IF('Arcas HD'!$A27="","",'Arcas HD'!A27) -> Arcas HD | B16: =IF('Arcas HD'!$A27="","",'Arcas HD'!B27) -> 0 | C16: =IF('Arcas HD'!$A27="","",'Arcas HD'!C27) -> 0 | D16: =IF('Arcas HD'!$A27="","",'Arcas HD'!D27) -> 0 | E16: =IF('Arcas HD'!$A27="","",'Arcas HD'!E27) -> 0 | F16: =IF('Arcas HD'!$A27="","",'Arcas HD'!F27) -> 0 | G16: =IF('Arcas HD'!$A27="","",'Arcas HD'!G27) -> 0 | H16: =IF('Arcas HD'!$A27="","",'Arcas HD'!H27) -> 0 | ... O16: =IF('Arcas HD'!$A27="","",'Arcas HD'!O27) -> 0
A17: =IF('Arcas HD'!$A28="","",'Arcas HD'!A28) -> Arcas HD | B17: =IF('Arcas HD'!$A28="","",'Arcas HD'!B28) -> 0 | C17: =IF('Arcas HD'!$A28="","",'Arcas HD'!C28) -> 0 | D17: =IF('Arcas HD'!$A28="","",'Arcas HD'!D28) -> 0 | E17: =IF('Arcas HD'!$A28="","",'Arcas HD'!E28) -> 0 | F17: =IF('Arcas HD'!$A28="","",'Arcas HD'!F28) -> 0 | G17: =IF('Arcas HD'!$A28="","",'Arcas HD'!G28) -> 0 | H17: =IF('Arcas HD'!$A28="","",'Arcas HD'!H28) -> 0 | ... O17: =IF('Arcas HD'!$A28="","",'Arcas HD'!O28) -> 0
... A239: =IF('Arcas HD'!$A250="","",'Arcas HD'!A250) -> Arcas HD | B239: =IF('Arcas HD'!$A250="","",'Arcas HD'!B250) -> 0 | C239: =IF('Arcas HD'!$A250="","",'Arcas HD'!C250) -> 0 | D239: =IF('Arcas HD'!$A250="","",'Arcas HD'!D250) -> 0 | E239: =IF('Arcas HD'!$A250="","",'Arcas HD'!E250) -> 0 | F239: =IF('Arcas HD'!$A250="","",'Arcas HD'!F250) -> 0 | G239: =IF('Arcas HD'!$A250="","",'Arcas HD'!G250) -> 0 | H239: =IF('Arcas HD'!$A250="","",'Arcas HD'!H250) -> 0 | ... O239: =IF('Arcas HD'!$A250="","",'Arcas HD'!O250) -> 0
A240: =IF('MGD PC'!$A13="","",'MGD PC'!A13) -> MGD PC | B240: =IF('MGD PC'!$A13="","",'MGD PC'!B13) -> Gate 1 | C240: =IF('MGD PC'!$A13="","",'MGD PC'!C13) -> Technical Feasibility | D240: =IF('MGD PC'!$A13="","",'MGD PC'!D13) -> Yes | E240: =IF('MGD PC'!$A13="","",'MGD PC'!E13) -> Menilai kelayakan teknis dasar solusi sebelum pilot dilanjutkan atau diperluas. | F240: =IF('MGD PC'!$A13="","",'MGD PC'!F13) -> Untuk proyek MGD PC, gate ini fokus pada sensor reliability, positioning accuracy, and data logging. | G240: =IF('MGD PC'!$A13="","",'MGD PC'!G13) -> Kesiapan infrastruktur, integrasi sistem, kualitas data/sinyal, stabilitas teknis, uptime, latency, dan reliability. | H240: =IF('MGD PC'!$A13="","",'MGD PC'!H13) -> Lengkapi evidence hasil uji teknis, gap teknis terbuka, mitigasi, dan rekomendasi readiness. | I240: =IF('MGD PC'!$A13="","",'MGD PC'!I13) -> Sensor reliability, positioning accuracy, and data logging. | J240: =IF('MGD PC'!$A13="","",'Arcas HD'!J13) -> Conditional | K240: =IF('MGD PC'!$A13="","",'MGD PC'!K13) -> 0 | L240: =IF('MGD PC'!$A13="","",'MGD PC'!L13) -> 0 | M240: =IF('MGD PC'!$A13="","",'MGD PC'!M13) -> 0 | N240: =IF('MGD PC'!$A13="","",'MGD PC'!N13) -> 0 | O240: =IF('MGD PC'!$A13="","",'MGD PC'!O13) -> 0
A241: =IF('MGD PC'!$A14="","",'MGD PC'!A14) -> MGD PC | B241: =IF('MGD PC'!$A14="","",'MGD PC'!B14) -> Gate 2 | C241: =IF('MGD PC'!$A14="","",'MGD PC'!C14) -> Performance / Effectiveness | D241: =IF('MGD PC'!$A14="","",'MGD PC'!D14) -> No | E241: =IF('MGD PC'!$A14="","",'MGD PC'!E14) -> Membuktikan bahwa solusi memberi hasil operasional yang relevan dengan tujuan proyek. | F241: =IF('MGD PC'!$A14="","",'MGD PC'!F14) -> Untuk proyek MGD PC, gate ini fokus pada guidance accuracy, error reduction, and operational acceptance. | G241: =IF('MGD PC'!$A14="","",'MGD PC'!G14) -> Akurasi, efektivitas, availability, pengurangan loss, peningkatan produktivitas, atau manfaat performa lain sesuai use case. | H241: =IF('MGD PC'!$A14="","",'MGD PC'!H14) -> Lengkapi baseline vs actual, hasil pilot, variasi performa, akar masalah, dan action plan. | I241: =IF('MGD PC'!$A14="","",'MGD PC'!I14) -> Guidance accuracy, error reduction, and operational acceptance. | J241: =IF('MGD PC'!$A14="","",'Arcas HD'!J14) -> Conditional | K241: =IF('MGD PC'!$A14="","",'MGD PC'!K14) -> 0 | L241: =IF('MGD PC'!$A14="","",'MGD PC'!L14) -> 0 | M241: =IF('MGD PC'!$A14="","",'MGD PC'!M14) -> 0 | N241: =IF('MGD PC'!$A14="","",'MGD PC'!N14) -> 0 | O241: =IF('MGD PC'!$A14="","",'MGD PC'!O14) -> 0
A242: =IF('MGD PC'!$A15="","",'MGD PC'!A15) -> MGD PC | B242: =IF('MGD PC'!$A15="","",'MGD PC'!B15) -> Gate 3 | C242: =IF('MGD PC'!$A15="","",'MGD PC'!C15) -> Safety Case & Procedure | D242: =IF('MGD PC'!$A15="","",'MGD PC'!D15) -> Yes | E242: =IF('MGD PC'!$A15="","",'MGD PC'!E15) -> Memastikan proyek aman dijalankan dan governance operasionalnya siap. | F242: =IF('MGD PC'!$A15="","",'MGD PC'!F15) -> Untuk proyek MGD PC, gate ini fokus pada manual fallback, override logic, and safe exception handling. | G242: =IF('MGD PC'!$A15="","",'MGD PC'!G15) -> SOP, override, fail-safe, escalation path, audit trail, handover, interlock, dan penutupan risiko kritikal. | H242: =IF('MGD PC'!$A15="","",'MGD PC'!H15) -> Lengkapi status SOP, hasil simulasi/drill, kontrol keselamatan, approval safety, dan gap residual. | I242: =IF('MGD PC'!$A15="","",'MGD PC'!I15) -> Manual fallback, override logic, and safe exception handling. | J242: =IF('MGD PC'!$A15="","",'Arcas HD'!J15) -> Not Started | K242: =IF('MGD PC'!$A15="","",'MGD PC'!K15) -> 0 | L242: =IF('MGD PC'!$A15="","",'MGD PC'!L15) -> 0 | M242: =IF('MGD PC'!$A15="","",'MGD PC'!M15) -> 0 | N242: =IF('MGD PC'!$A15="","",'MGD PC'!N15) -> 0 | O242: =IF('MGD PC'!$A15="","",'MGD PC'!O15) -> 0
A243: =IF('MGD PC'!$A16="","",'MGD PC'!A16) -> MGD PC | B243: =IF('MGD PC'!$A16="","",'MGD PC'!B16) -> Gate 4 | C243: =IF('MGD PC'!$A16="","",'MGD PC'!C16) -> Business / Assurance | D243: =IF('MGD PC'!$A16="","",'MGD PC'!D16) -> No | E243: =IF('MGD PC'!$A16="","",'MGD PC'!E16) -> Menilai kelayakan scale-up dari sisi bisnis, assurance, atau keekonomian. | F243: =IF('MGD PC'!$A16="","",'MGD PC'!F16) -> Untuk proyek MGD PC, gate ini fokus pada operational efficiency, waste reduction, and quality improvement. | G243: =IF('MGD PC'!$A16="","",'MGD PC'!G16) -> Nilai bisnis, reduction of exposure/loss, assurance value, economic case, payback, ROI, atau justification deployment lebih luas. | H243: =IF('MGD PC'!$A16="","",'MGD PC'!H16) -> Lengkapi manfaat terukur, asumsi bisnis/ekonomi, alasan scale-up, risiko bisnis, dan rekomendasi akhir. | I243: =IF('MGD PC'!$A16="","",'MGD PC'!I16) -> Operational efficiency, waste reduction, and quality improvement. | J243: =IF('MGD PC'!$A16="","",'Arcas HD'!J16) -> Conditional | K243: =IF('MGD PC'!$A16="","",'MGD PC'!K16) -> 0 | L243: =IF('MGD PC'!$A16="","",'MGD PC'!L16) -> 0 | M243: =IF('MGD PC'!$A16="","",'MGD PC'!M16) -> 0 | N243: =IF('MGD PC'!$A16="","",'MGD PC'!N16) -> 0 | O243: =IF('MGD PC'!$A16="","",'MGD PC'!O16) -> 0
A244: =IF('MGD PC'!$A17="","",'MGD PC'!A17) -> MGD PC | B244: =IF('MGD PC'!$A17="","",'MGD PC'!B17) -> 0 | C244: =IF('MGD PC'!$A17="","",'MGD PC'!C17) -> 0 | D244: =IF('MGD PC'!$A17="","",'MGD PC'!D17) -> 0 | E244: =IF('MGD PC'!$A17="","",'MGD PC'!E17) -> 0 | F244: =IF('MGD PC'!$A17="","",'MGD PC'!F17) -> 0 | G244: =IF('MGD PC'!$A17="","",'MGD PC'!G17) -> 0 | H244: =IF('MGD PC'!$A17="","",'MGD PC'!H17) -> 0 | ... O244: =IF('MGD PC'!$A17="","",'MGD PC'!O17) -> 0
A245: =IF('MGD PC'!$A18="","",'MGD PC'!A18) -> MGD PC | B245: =IF('MGD PC'!$A18="","",'MGD PC'!B18) -> 0 | C245: =IF('MGD PC'!$A18="","",'MGD PC'!C18) -> 0 | D245: =IF('MGD PC'!$A18="","",'MGD PC'!D18) -> 0 | E245: =IF('MGD PC'!$A18="","",'MGD PC'!E18) -> 0 | F245: =IF('MGD PC'!$A18="","",'MGD PC'!F18) -> 0 | G245: =IF('MGD PC'!$A18="","",'MGD PC'!G18) -> 0 | H245: =IF('MGD PC'!$A18="","",'MGD PC'!H18) -> 0 | ... O245: =IF('MGD PC'!$A18="","",'MGD PC'!O18) -> 0
A246: =IF('MGD PC'!$A19="","",'MGD PC'!A19) -> MGD PC | B246: =IF('MGD PC'!$A19="","",'MGD PC'!B19) -> 0 | C246: =IF('MGD PC'!$A19="","",'MGD PC'!C19) -> 0 | D246: =IF('MGD PC'!$A19="","",'MGD PC'!D19) -> 0 | E246: =IF('MGD PC'!$A19="","",'MGD PC'!E19) -> 0 | F246: =IF('MGD PC'!$A19="","",'MGD PC'!F19) -> 0 | G246: =IF('MGD PC'!$A19="","",'MGD PC'!G19) -> 0 | H246: =IF('MGD PC'!$A19="","",'MGD PC'!H19) -> 0 | ... O246: =IF('MGD PC'!$A19="","",'MGD PC'!O19) -> 0
A247: =IF('MGD PC'!$A20="","",'MGD PC'!A20) -> MGD PC | B247: =IF('MGD PC'!$A20="","",'MGD PC'!B20) -> 0 | C247: =IF('MGD PC'!$A20="","",'MGD PC'!C20) -> 0 | D247: =IF('MGD PC'!$A20="","",'MGD PC'!D20) -> 0 | E247: =IF('MGD PC'!$A20="","",'MGD PC'!E20) -> 0 | F247: =IF('MGD PC'!$A20="","",'MGD PC'!F20) -> 0 | G247: =IF('MGD PC'!$A20="","",'MGD PC'!G20) -> 0 | H247: =IF('MGD PC'!$A20="","",'MGD PC'!H20) -> 0 | ... O247: =IF('MGD PC'!$A20="","",'MGD PC'!O20) -> 0
A248: =IF('MGD PC'!$A21="","",'MGD PC'!A21) -> MGD PC | B248: =IF('MGD PC'!$A21="","",'MGD PC'!B21) -> 0 | C248: =IF('MGD PC'!$A21="","",'MGD PC'!C21) -> 0 | D248: =IF('MGD PC'!$A21="","",'MGD PC'!D21) -> 0 | E248: =IF('MGD PC'!$A21="","",'MGD PC'!E21) -> 0 | F248: =IF('MGD PC'!$A21="","",'MGD PC'!F21) -> 0 | G248: =IF('MGD PC'!$A21="","",'MGD PC'!G21) -> 0 | H248: =IF('MGD PC'!$A21="","",'MGD PC'!H21) -> 0 | ... O248: =IF('MGD PC'!$A21="","",'MGD PC'!O21) -> 0
A249: =IF('MGD PC'!$A22="","",'MGD PC'!A22) -> MGD PC | B249: =IF('MGD PC'!$A22="","",'MGD PC'!B22) -> 0 | C249: =IF('MGD PC'!$A22="","",'MGD PC'!C22) -> 0 | D249: =IF('MGD PC'!$A22="","",'MGD PC'!D22) -> 0 | E249: =IF('MGD PC'!$A22="","",'MGD PC'!E22) -> 0 | F249: =IF('MGD PC'!$A22="","",'MGD PC'!F22) -> 0 | G249: =IF('MGD PC'!$A22="","",'MGD PC'!G22) -> 0 | H249: =IF('MGD PC'!$A22="","",'MGD PC'!H22) -> 0 | ... O249: =IF('MGD PC'!$A22="","",'MGD PC'!O22) -> 0
A250: =IF('MGD PC'!$A23="","",'MGD PC'!A23) -> MGD PC | B250: =IF('MGD PC'!$A23="","",'MGD PC'!B23) -> 0 | C250: =IF('MGD PC'!$A23="","",'MGD PC'!C23) -> 0 | D250: =IF('MGD PC'!$A23="","",'MGD PC'!D23) -> 0 | E250: =IF('MGD PC'!$A23="","",'MGD PC'!E23) -> 0 | F250: =IF('MGD PC'!$A23="","",'MGD PC'!F23) -> 0 | G250: =IF('MGD PC'!$A23="","",'MGD PC'!G23) -> 0 | H250: =IF('MGD PC'!$A23="","",'MGD PC'!H23) -> 0 | ... O250: =IF('MGD PC'!$A23="","",'MGD PC'!O23) -> 0
A251: =IF('MGD PC'!$A24="","",'MGD PC'!A24) -> MGD PC | B251: =IF('MGD PC'!$A24="","",'MGD PC'!B24) -> 0 | C251: =IF('MGD PC'!$A24="","",'MGD PC'!C24) -> 0 | D251: =IF('MGD PC'!$A24="","",'MGD PC'!D24) -> 0 | E251: =IF('MGD PC'!$A24="","",'MGD PC'!E24) -> 0 | F251: =IF('MGD PC'!$A24="","",'MGD PC'!F24) -> 0 | G251: =IF('MGD PC'!$A24="","",'MGD PC'!G24) -> 0 | H251: =IF('MGD PC'!$A24="","",'MGD PC'!H24) -> 0 | ... O251: =IF('MGD PC'!$A24="","",'MGD PC'!O24) -> 0
A252: =IF('MGD PC'!$A25="","",'MGD PC'!A25) -> MGD PC | B252: =IF('MGD PC'!$A25="","",'MGD PC'!B25) -> 0 | C252: =IF('MGD PC'!$A25="","",'MGD PC'!C25) -> 0 | D252: =IF('MGD PC'!$A25="","",'MGD PC'!D25) -> 0 | E252: =IF('MGD PC'!$A25="","",'MGD PC'!E25) -> 0 | F252: =IF('MGD PC'!$A25="","",'MGD PC'!F25) -> 0 | G252: =IF('MGD PC'!$A25="","",'MGD PC'!G25) -> 0 | H252: =IF('MGD PC'!$A25="","",'MGD PC'!H25) -> 0 | ... O252: =IF('MGD PC'!$A25="","",'MGD PC'!O25) -> 0
A253: =IF('MGD PC'!$A26="","",'MGD PC'!A26) -> MGD PC | B253: =IF('MGD PC'!$A26="","",'MGD PC'!B26) -> 0 | C253: =IF('MGD PC'!$A26="","",'MGD PC'!C26) -> 0 | D253: =IF('MGD PC'!$A26="","",'MGD PC'!D26) -> 0 | E253: =IF('MGD PC'!$A26="","",'MGD PC'!E26) -> 0 | F253: =IF('MGD PC'!$A26="","",'MGD PC'!F26) -> 0 | G253: =IF('MGD PC'!$A26="","",'MGD PC'!G26) -> 0 | H253: =IF('MGD PC'!$A26="","",'MGD PC'!H26) -> 0 | ... O253: =IF('MGD PC'!$A26="","",'MGD PC'!O26) -> 0
A254: =IF('MGD PC'!$A27="","",'MGD PC'!A27) -> MGD PC | B254: =IF('MGD PC'!$A27="","",'MGD PC'!B27) -> 0 | C254: =IF('MGD PC'!$A27="","",'MGD PC'!C27) -> 0 | D254: =IF('MGD PC'!$A27="","",'MGD PC'!D27) -> 0 | E254: =IF('MGD PC'!$A27="","",'MGD PC'!E27) -> 0 | F254: =IF('MGD PC'!$A27="","",'MGD PC'!F27) -> 0 | G254: =IF('MGD PC'!$A27="","",'MGD PC'!G27) -> 0 | H254: =IF('MGD PC'!$A27="","",'MGD PC'!H27) -> 0 | ... O254: =IF('MGD PC'!$A27="","",'MGD PC'!O27) -> 0
A255: =IF('MGD PC'!$A28="","",'MGD PC'!A28) -> MGD PC | B255: =IF('MGD PC'!$A28="","",'MGD PC'!B28) -> 0 | C255: =IF('MGD PC'!$A28="","",'MGD PC'!C28) -> 0 | D255: =IF('MGD PC'!$A28="","",'MGD PC'!D28) -> 0 | E255: =IF('MGD PC'!$A28="","",'MGD PC'!E28) -> 0 | F255: =IF('MGD PC'!$A28="","",'MGD PC'!F28) -> 0 | G255: =IF('MGD PC'!$A28="","",'MGD PC'!G28) -> 0 | H255: =IF('MGD PC'!$A28="","",'MGD PC'!H28) -> 0 | ... O255: =IF('MGD PC'!$A28="","",'MGD PC'!O28) -> 0
... A477: =IF('MGD PC'!$A250="","",'MGD PC'!A250) -> MGD PC | B477: =IF('MGD PC'!$A250="","",'MGD PC'!B250) -> 0 | C477: =IF('MGD PC'!$A250="","",'MGD PC'!C250) -> 0 | D477: =IF('MGD PC'!$A250="","",'MGD PC'!D250) -> 0 | E477: =IF('MGD PC'!$A250="","",'MGD PC'!E250) -> 0 | F477: =IF('MGD PC'!$A250="","",'MGD PC'!F250) -> 0 | G477: =IF('MGD PC'!$A250="","",'MGD PC'!G250) -> 0 | H477: =IF('MGD PC'!$A250="","",'MGD PC'!H250) -> 0 | ... O477: =IF('MGD PC'!$A250="","",'MGD PC'!O250) -> 0
A478: =IF('Remote Pump'!$A13="","",'Remote Pump'!A13) -> Remote Pump | B478: =IF('Remote Pump'!$A13="","",'Remote Pump'!B13) -> Gate 1 | C478: =IF('Remote Pump'!$A13="","",'Remote Pump'!C13) -> Technical Feasibility | D478: =IF('Remote Pump'!$A13="","",'Remote Pump'!D13) -> Yes | E478: =IF('Remote Pump'!$A13="","",'Remote Pump'!E13) -> Menilai kelayakan teknis dasar solusi sebelum pilot dilanjutkan atau diperluas. | F478: =IF('Remote Pump'!$A13="","",'Remote Pump'!F13) -> Untuk proyek Remote Pump, gate ini fokus pada command success, telemetry completeness, and communication stability. | G478: =IF('Remote Pump'!$A13="","",'Remote Pump'!G13) -> Kesiapan infrastruktur, integrasi sistem, kualitas data/sinyal, stabilitas teknis, uptime, latency, dan reliability. | H478: =IF('Remote Pump'!$A13="","",'Remote Pump'!H13) -> Lengkapi evidence hasil uji teknis, gap teknis terbuka, mitigasi, dan rekomendasi readiness. | ... O478: =IF('Remote Pump'!$A13="","",'Remote Pump'!O13) -> 0
A479: =IF('Remote Pump'!$A14="","",'Remote Pump'!A14) -> Remote Pump | B479: =IF('Remote Pump'!$A14="","",'Remote Pump'!B14) -> Gate 2 | C479: =IF('Remote Pump'!$A14="","",'Remote Pump'!C14) -> Performance / Effectiveness | D479: =IF('Remote Pump'!$A14="","",'Remote Pump'!D14) -> No | E479: =IF('Remote Pump'!$A14="","",'Remote Pump'!E14) -> Membuktikan bahwa solusi memberi hasil operasional yang relevan dengan tujuan proyek. | F479: =IF('Remote Pump'!$A14="","",'Remote Pump'!F14) -> Untuk proyek Remote Pump, gate ini fokus pada availability, remote-control reliability, and downtime impact. | G479: =IF('Remote Pump'!$A14="","",'Remote Pump'!G14) -> Akurasi, efektivitas, availability, pengurangan loss, peningkatan produktivitas, atau manfaat performa lain sesuai use case. | H479: =IF('Remote Pump'!$A14="","",'Remote Pump'!H14) -> Lengkapi baseline vs actual, hasil pilot, variasi performa, akar masalah, dan action plan. | ... O479: =IF('Remote Pump'!$A14="","",'Remote Pump'!O14) -> 0
A480: =IF('Remote Pump'!$A15="","",'Remote Pump'!A15) -> Remote Pump | B480: =IF('Remote Pump'!$A15="","",'Remote Pump'!B15) -> Gate 3 | C480: =IF('Remote Pump'!$A15="","",'Remote Pump'!C15) -> Safety Case & Procedure | D480: =IF('Remote Pump'!$A15="","",'Remote Pump'!D15) -> Yes | E480: =IF('Remote Pump'!$A15="","",'Remote Pump'!E15) -> Memastikan proyek aman dijalankan dan governance operasionalnya siap. | F480: =IF('Remote Pump'!$A15="","",'Remote Pump'!F15) -> Untuk proyek Remote Pump, gate ini fokus pada interlock, local override, fail-safe loss-of-signal logic. | G480: =IF('Remote Pump'!$A15="","",'Remote Pump'!G15) -> SOP, override, fail-safe, escalation path, audit trail, handover, interlock, dan penutupan risiko kritikal. | H480: =IF('Remote Pump'!$A15="","",'Remote Pump'!H15) -> Lengkapi status SOP, hasil simulasi/drill, kontrol keselamatan, approval safety, dan gap residual. | ... O480: =IF('Remote Pump'!$A15="","",'Remote Pump'!O15) -> 0
A481: =IF('Remote Pump'!$A16="","",'Remote Pump'!A16) -> Remote Pump | B481: =IF('Remote Pump'!$A16="","",'Remote Pump'!B16) -> Gate 4 | C481: =IF('Remote Pump'!$A16="","",'Remote Pump'!C16) -> Business / Assurance | D481: =IF('Remote Pump'!$A16="","",'Remote Pump'!D16) -> No | E481: =IF('Remote Pump'!$A16="","",'Remote Pump'!E16) -> Menilai kelayakan scale-up dari sisi bisnis, assurance, atau keekonomian. | F481: =IF('Remote Pump'!$A16="","",'Remote Pump'!F16) -> Untuk proyek Remote Pump, gate ini fokus pada travel exposure reduction, avoided delays, and operating value. | G481: =IF('Remote Pump'!$A16="","",'Remote Pump'!G16) -> Nilai bisnis, reduction of exposure/loss, assurance value, economic case, payback, ROI, atau justification deployment lebih luas. | H481: =IF('Remote Pump'!$A16="","",'Remote Pump'!H16) -> Lengkapi manfaat terukur, asumsi bisnis/ekonomi, alasan scale-up, risiko bisnis, dan rekomendasi akhir. | ... O481: =IF('Remote Pump'!$A16="","",'Remote Pump'!O16) -> 0
A482: =IF('Remote Pump'!$A17="","",'Remote Pump'!A17) -> Remote Pump | B482: =IF('Remote Pump'!$A17="","",'Remote Pump'!B17) -> 0 | C482: =IF('Remote Pump'!$A17="","",'Remote Pump'!C17) -> 0 | D482: =IF('Remote Pump'!$A17="","",'Remote Pump'!D17) -> 0 | E482: =IF('Remote Pump'!$A17="","",'Remote Pump'!E17) -> 0 | F482: =IF('Remote Pump'!$A17="","",'Remote Pump'!F17) -> 0 | G482: =IF('Remote Pump'!$A17="","",'Remote Pump'!G17) -> 0 | H482: =IF('Remote Pump'!$A17="","",'Remote Pump'!H17) -> 0 | ... O482: =IF('Remote Pump'!$A17="","",'Remote Pump'!O17) -> 0
A483: =IF('Remote Pump'!$A18="","",'Remote Pump'!A18) -> Remote Pump | B483: =IF('Remote Pump'!$A18="","",'Remote Pump'!B18) -> 0 | C483: =IF('Remote Pump'!$A18="","",'Remote Pump'!C18) -> 0 | D483: =IF('Remote Pump'!$A18="","",'Remote Pump'!D18) -> 0 | E483: =IF('Remote Pump'!$A18="","",'Remote Pump'!E18) -> 0 | F483: =IF('Remote Pump'!$A18="","",'Remote Pump'!F18) -> 0 | G483: =IF('Remote Pump'!$A18="","",'Remote Pump'!G18) -> 0 | H483: =IF('Remote Pump'!$A18="","",'Remote Pump'!H18) -> 0 | ... O483: =IF('Remote Pump'!$A18="","",'Remote Pump'!O18) -> 0
A484: =IF('Remote Pump'!$A19="","",'Remote Pump'!A19) -> Remote Pump | B484: =IF('Remote Pump'!$A19="","",'Remote Pump'!B19) -> 0 | C484: =IF('Remote Pump'!$A19="","",'Remote Pump'!C19) -> 0 | D484: =IF('Remote Pump'!$A19="","",'Remote Pump'!D19) -> 0 | E484: =IF('Remote Pump'!$A19="","",'Remote Pump'!E19) -> 0 | F484: =IF('Remote Pump'!$A19="","",'Remote Pump'!F19) -> 0 | G484: =IF('Remote Pump'!$A19="","",'Remote Pump'!G19) -> 0 | H484: =IF('Remote Pump'!$A19="","",'Remote Pump'!H19) -> 0 | ... O484: =IF('Remote Pump'!$A19="","",'Remote Pump'!O19) -> 0
A485: =IF('Remote Pump'!$A20="","",'Remote Pump'!A20) -> Remote Pump | B485: =IF('Remote Pump'!$A20="","",'Remote Pump'!B20) -> 0 | C485: =IF('Remote Pump'!$A20="","",'Remote Pump'!C20) -> 0 | D485: =IF('Remote Pump'!$A20="","",'Remote Pump'!D20) -> 0 | E485: =IF('Remote Pump'!$A20="","",'Remote Pump'!E20) -> 0 | F485: =IF('Remote Pump'!$A20="","",'Remote Pump'!F20) -> 0 | G485: =IF('Remote Pump'!$A20="","",'Remote Pump'!G20) -> 0 | H485: =IF('Remote Pump'!$A20="","",'Remote Pump'!H20) -> 0 | ... O485: =IF('Remote Pump'!$A20="","",'Remote Pump'!O20) -> 0
A486: =IF('Remote Pump'!$A21="","",'Remote Pump'!A21) -> Remote Pump | B486: =IF('Remote Pump'!$A21="","",'Remote Pump'!B21) -> 0 | C486: =IF('Remote Pump'!$A21="","",'Remote Pump'!C21) -> 0 | D486: =IF('Remote Pump'!$A21="","",'Remote Pump'!D21) -> 0 | E486: =IF('Remote Pump'!$A21="","",'Remote Pump'!E21) -> 0 | F486: =IF('Remote Pump'!$A21="","",'Remote Pump'!F21) -> 0 | G486: =IF('Remote Pump'!$A21="","",'Remote Pump'!G21) -> 0 | H486: =IF('Remote Pump'!$A21="","",'Remote Pump'!H21) -> 0 | ... O486: =IF('Remote Pump'!$A21="","",'Remote Pump'!O21) -> 0
A487: =IF('Remote Pump'!$A22="","",'Remote Pump'!A22) -> Remote Pump | B487: =IF('Remote Pump'!$A22="","",'Remote Pump'!B22) -> 0 | C487: =IF('Remote Pump'!$A22="","",'Remote Pump'!C22) -> 0 | D487: =IF('Remote Pump'!$A22="","",'Remote Pump'!D22) -> 0 | E487: =IF('Remote Pump'!$A22="","",'Remote Pump'!E22) -> 0 | F487: =IF('Remote Pump'!$A22="","",'Remote Pump'!F22) -> 0 | G487: =IF('Remote Pump'!$A22="","",'Remote Pump'!G22) -> 0 | H487: =IF('Remote Pump'!$A22="","",'Remote Pump'!H22) -> 0 | ... O487: =IF('Remote Pump'!$A22="","",'Remote Pump'!O22) -> 0
A488: =IF('Remote Pump'!$A23="","",'Remote Pump'!A23) -> Remote Pump | B488: =IF('Remote Pump'!$A23="","",'Remote Pump'!B23) -> 0 | C488: =IF('Remote Pump'!$A23="","",'Remote Pump'!C23) -> 0 | D488: =IF('Remote Pump'!$A23="","",'Remote Pump'!D23) -> 0 | E488: =IF('Remote Pump'!$A23="","",'Remote Pump'!E23) -> 0 | F488: =IF('Remote Pump'!$A23="","",'Remote Pump'!F23) -> 0 | G488: =IF('Remote Pump'!$A23="","",'Remote Pump'!G23) -> 0 | H488: =IF('Remote Pump'!$A23="","",'Remote Pump'!H23) -> 0 | ... O488: =IF('Remote Pump'!$A23="","",'Remote Pump'!O23) -> 0
A489: =IF('Remote Pump'!$A24="","",'Remote Pump'!A24) -> Remote Pump | B489: =IF('Remote Pump'!$A24="","",'Remote Pump'!B24) -> 0 | C489: =IF('Remote Pump'!$A24="","",'Remote Pump'!C24) -> 0 | D489: =IF('Remote Pump'!$A24="","",'Remote Pump'!D24) -> 0 | E489: =IF('Remote Pump'!$A24="","",'Remote Pump'!E24) -> 0 | F489: =IF('Remote Pump'!$A24="","",'Remote Pump'!F24) -> 0 | G489: =IF('Remote Pump'!$A24="","",'Remote Pump'!G24) -> 0 | H489: =IF('Remote Pump'!$A24="","",'Remote Pump'!H24) -> 0 | ... O489: =IF('Remote Pump'!$A24="","",'Remote Pump'!O24) -> 0
... A715: =IF('Remote Pump'!$A250="","",'Remote Pump'!A250) -> Remote Pump | B715: =IF('Remote Pump'!$A250="","",'Remote Pump'!B250) -> 0 | C715: =IF('Remote Pump'!$A250="","",'Remote Pump'!C250) -> 0 | D715: =IF('Remote Pump'!$A250="","",'Remote Pump'!D250) -> 0 | E715: =IF('Remote Pump'!$A250="","",'Remote Pump'!E250) -> 0 | F715: =IF('Remote Pump'!$A250="","",'Remote Pump'!F250) -> 0 | G715: =IF('Remote Pump'!$A250="","",'Remote Pump'!G250) -> 0 | H715: =IF('Remote Pump'!$A250="","",'Remote Pump'!H250) -> 0 | ... O715: =IF('Remote Pump'!$A250="","",'Remote Pump'!O250) -> 0
A716: =IF('Hauling Fleet Management'!$A13="","",'Hauling Fleet Management'!A13) -> Hauling Fleet Management | B716: =IF('Hauling Fleet Management'!$A13="","",'Hauling Fleet Management'!B13) -> Gate 1 | C716: =IF('Hauling Fleet Management'!$A13="","",'Hauling Fleet Management'!C13) -> Technical Feasibility | D716: =IF('Hauling Fleet Management'!$A13="","",'Hauling Fleet Management'!D13) -> Yes | E716: =IF('Hauling Fleet Management'!$A13="","",'Hauling Fleet Management'!E13) -> Menilai kelayakan teknis dasar solusi sebelum pilot dilanjutkan atau diperluas. | F716: =IF('Hauling Fleet Management'!$A13="","",'Hauling Fleet Management'!F13) -> Untuk proyek Hauling Fleet Management, gate ini fokus pada data ingestion, gps continuity, dashboard uptime, and integration. | G716: =IF('Hauling Fleet Management'!$A13="","",'Hauling Fleet Management'!G13) -> Kesiapan infrastruktur, integrasi sistem, kualitas data/sinyal, stabilitas teknis, uptime, latency, dan reliability. | H716: =IF('Hauling Fleet Management'!$A13="","",'Hauling Fleet Management'!H13) -> Lengkapi evidence hasil uji teknis, gap teknis terbuka, mitigasi, dan rekomendasi readiness. | ... O716: =IF('Hauling Fleet Management'!$A13="","",'Hauling Fleet Management'!O13) -> 0
A717: =IF('Hauling Fleet Management'!$A14="","",'Hauling Fleet Management'!A14) -> Hauling Fleet Management | B717: =IF('Hauling Fleet Management'!$A14="","",'Hauling Fleet Management'!B14) -> Gate 2 | C717: =IF('Hauling Fleet Management'!$A14="","",'Hauling Fleet Management'!C14) -> Performance / Effectiveness | D717: =IF('Hauling Fleet Management'!$A14="","",'Hauling Fleet Management'!D14) -> No | E717: =IF('Hauling Fleet Management'!$A14="","",'Hauling Fleet Management'!E14) -> Membuktikan bahwa solusi memberi hasil operasional yang relevan dengan tujuan proyek. | F717: =IF('Hauling Fleet Management'!$A14="","",'Hauling Fleet Management'!F14) -> Untuk proyek Hauling Fleet Management, gate ini fokus pada queue time, idle time, and cycle optimization effectiveness. | G717: =IF('Hauling Fleet Management'!$A14="","",'Hauling Fleet Management'!G14) -> Akurasi, efektivitas, availability, pengurangan loss, peningkatan produktivitas, atau manfaat performa lain sesuai use case. | H717: =IF('Hauling Fleet Management'!$A14="","",'Hauling Fleet Management'!H14) -> Lengkapi baseline vs actual, hasil pilot, variasi performa, akar masalah, dan action plan. | ... O717: =IF('Hauling Fleet Management'!$A14="","",'Hauling Fleet Management'!O14) -> 0
A718: =IF('Hauling Fleet Management'!$A15="","",'Hauling Fleet Management'!A15) -> Hauling Fleet Management | B718: =IF('Hauling Fleet Management'!$A15="","",'Hauling Fleet Management'!B15) -> Gate 3 | C718: =IF('Hauling Fleet Management'!$A15="","",'Hauling Fleet Management'!C15) -> Safety Case & Procedure | D718: =IF('Hauling Fleet Management'!$A15="","",'Hauling Fleet Management'!D15) -> Yes | E718: =IF('Hauling Fleet Management'!$A15="","",'Hauling Fleet Management'!E15) -> Memastikan proyek aman dijalankan dan governance operasionalnya siap. | F718: =IF('Hauling Fleet Management'!$A15="","",'Hauling Fleet Management'!F15) -> Untuk proyek Hauling Fleet Management, gate ini fokus pada override, rule compliance, and alignment with road safety logic. | G718: =IF('Hauling Fleet Management'!$A15="","",'Hauling Fleet Management'!G15) -> SOP, override, fail-safe, escalation path, audit trail, handover, interlock, dan penutupan risiko kritikal. | H718: =IF('Hauling Fleet Management'!$A15="","",'Hauling Fleet Management'!H15) -> Lengkapi status SOP, hasil simulasi/drill, kontrol keselamatan, approval safety, dan gap residual. | ... O718: =IF('Hauling Fleet Management'!$A15="","",'Hauling Fleet Management'!O15) -> 0
A719: =IF('Hauling Fleet Management'!$A16="","",'Hauling Fleet Management'!A16) -> Hauling Fleet Management | B719: =IF('Hauling Fleet Management'!$A16="","",'Hauling Fleet Management'!B16) -> Gate 4 | C719: =IF('Hauling Fleet Management'!$A16="","",'Hauling Fleet Management'!C16) -> Business / Assurance | D719: =IF('Hauling Fleet Management'!$A16="","",'Hauling Fleet Management'!D16) -> No | E719: =IF('Hauling Fleet Management'!$A16="","",'Hauling Fleet Management'!E16) -> Menilai kelayakan scale-up dari sisi bisnis, assurance, atau keekonomian. | F719: =IF('Hauling Fleet Management'!$A16="","",'Hauling Fleet Management'!F16) -> Untuk proyek Hauling Fleet Management, gate ini fokus pada fuel efficiency, utilization, and dispatch-led value creation. | G719: =IF('Hauling Fleet Management'!$A16="","",'Hauling Fleet Management'!G16) -> Nilai bisnis, reduction of exposure/loss, assurance value, economic case, payback, ROI, atau justification deployment lebih luas. | H719: =IF('Hauling Fleet Management'!$A16="","",'Hauling Fleet Management'!H16) -> Lengkapi manfaat terukur, asumsi bisnis/ekonomi, alasan scale-up, risiko bisnis, dan rekomendasi akhir. | ... O719: =IF('Hauling Fleet Management'!$A16="","",'Hauling Fleet Management'!O16) -> 0
A720: =IF('Hauling Fleet Management'!$A17="","",'Hauling Fleet Management'!A17) -> Hauling Fleet Management | B720: =IF('Hauling Fleet Management'!$A17="","",'Hauling Fleet Management'!B17) -> 0 | C720: =IF('Hauling Fleet Management'!$A17="","",'Hauling Fleet Management'!C17) -> 0 | D720: =IF('Hauling Fleet Management'!$A17="","",'Hauling Fleet Management'!D17) -> 0 | E720: =IF('Hauling Fleet Management'!$A17="","",'Hauling Fleet Management'!E17) -> 0 | F720: =IF('Hauling Fleet Management'!$A17="","",'Hauling Fleet Management'!F17) -> 0 | G720: =IF('Hauling Fleet Management'!$A17="","",'Hauling Fleet Management'!G17) -> 0 | H720: =IF('Hauling Fleet Management'!$A17="","",'Hauling Fleet Management'!H17) -> 0 | ... O720: =IF('Hauling Fleet Management'!$A17="","",'Hauling Fleet Management'!O17) -> 0
A721: =IF('Hauling Fleet Management'!$A18="","",'Hauling Fleet Management'!A18) -> Hauling Fleet Management | B721: =IF('Hauling Fleet Management'!$A18="","",'Hauling Fleet Management'!B18) -> 0 | C721: =IF('Hauling Fleet Management'!$A18="","",'Hauling Fleet Management'!C18) -> 0 | D721: =IF('Hauling Fleet Management'!$A18="","",'Hauling Fleet Management'!D18) -> 0 | E721: =IF('Hauling Fleet Management'!$A18="","",'Hauling Fleet Management'!E18) -> 0 | F721: =IF('Hauling Fleet Management'!$A18="","",'Hauling Fleet Management'!F18) -> 0 | G721: =IF('Hauling Fleet Management'!$A18="","",'Hauling Fleet Management'!G18) -> 0 | H721: =IF('Hauling Fleet Management'!$A18="","",'Hauling Fleet Management'!H18) -> 0 | ... O721: =IF('Hauling Fleet Management'!$A18="","",'Hauling Fleet Management'!O18) -> 0
A722: =IF('Hauling Fleet Management'!$A19="","",'Hauling Fleet Management'!A19) -> Hauling Fleet Management | B722: =IF('Hauling Fleet Management'!$A19="","",'Hauling Fleet Management'!B19) -> 0 | C722: =IF('Hauling Fleet Management'!$A19="","",'Hauling Fleet Management'!C19) -> 0 | D722: =IF('Hauling Fleet Management'!$A19="","",'Hauling Fleet Management'!D19) -> 0 | E722: =IF('Hauling Fleet Management'!$A19="","",'Hauling Fleet Management'!E19) -> 0 | F722: =IF('Hauling Fleet Management'!$A19="","",'Hauling Fleet Management'!F19) -> 0 | G722: =IF('Hauling Fleet Management'!$A19="","",'Hauling Fleet Management'!G19) -> 0 | H722: =IF('Hauling Fleet Management'!$A19="","",'Hauling Fleet Management'!H19) -> 0 | ... O722: =IF('Hauling Fleet Management'!$A19="","",'Hauling Fleet Management'!O19) -> 0
A723: =IF('Hauling Fleet Management'!$A20="","",'Hauling Fleet Management'!A20) -> Hauling Fleet Management | B723: =IF('Hauling Fleet Management'!$A20="","",'Hauling Fleet Management'!B20) -> 0 | C723: =IF('Hauling Fleet Management'!$A20="","",'Hauling Fleet Management'!C20) -> 0 | D723: =IF('Hauling Fleet Management'!$A20="","",'Hauling Fleet Management'!D20) -> 0 | E723: =IF('Hauling Fleet Management'!$A20="","",'Hauling Fleet Management'!E20) -> 0 | F723: =IF('Hauling Fleet Management'!$A20="","",'Hauling Fleet Management'!F20) -> 0 | G723: =IF('Hauling Fleet Management'!$A20="","",'Hauling Fleet Management'!G20) -> 0 | H723: =IF('Hauling Fleet Management'!$A20="","",'Hauling Fleet Management'!H20) -> 0 | ... O723: =IF('Hauling Fleet Management'!$A20="","",'Hauling Fleet Management'!O20) -> 0
A724: =IF('Hauling Fleet Management'!$A21="","",'Hauling Fleet Management'!A21) -> Hauling Fleet Management | B724: =IF('Hauling Fleet Management'!$A21="","",'Hauling Fleet Management'!B21) -> 0 | C724: =IF('Hauling Fleet Management'!$A21="","",'Hauling Fleet Management'!C21) -> 0 | D724: =IF('Hauling Fleet Management'!$A21="","",'Hauling Fleet Management'!D21) -> 0 | E724: =IF('Hauling Fleet Management'!$A21="","",'Hauling Fleet Management'!E21) -> 0 | F724: =IF('Hauling Fleet Management'!$A21="","",'Hauling Fleet Management'!F21) -> 0 | G724: =IF('Hauling Fleet Management'!$A21="","",'Hauling Fleet Management'!G21) -> 0 | H724: =IF('Hauling Fleet Management'!$A21="","",'Hauling Fleet Management'!H21) -> 0 | ... O724: =IF('Hauling Fleet Management'!$A21="","",'Hauling Fleet Management'!O21) -> 0
A725: =IF('Hauling Fleet Management'!$A22="","",'Hauling Fleet Management'!A22) -> Hauling Fleet Management | B725: =IF('Hauling Fleet Management'!$A22="","",'Hauling Fleet Management'!B22) -> 0 | C725: =IF('Hauling Fleet Management'!$A22="","",'Hauling Fleet Management'!C22) -> 0 | D725: =IF('Hauling Fleet Management'!$A22="","",'Hauling Fleet Management'!D22) -> 0 | E725: =IF('Hauling Fleet Management'!$A22="","",'Hauling Fleet Management'!E22) -> 0 | F725: =IF('Hauling Fleet Management'!$A22="","",'Hauling Fleet Management'!F22) -> 0 | G725: =IF('Hauling Fleet Management'!$A22="","",'Hauling Fleet Management'!G22) -> 0 | H725: =IF('Hauling Fleet Management'!$A22="","",'Hauling Fleet Management'!H22) -> 0 | ... O725: =IF('Hauling Fleet Management'!$A22="","",'Hauling Fleet Management'!O22) -> 0
A726: =IF('Hauling Fleet Management'!$A23="","",'Hauling Fleet Management'!A23) -> Hauling Fleet Management | B726: =IF('Hauling Fleet Management'!$A23="","",'Hauling Fleet Management'!B23) -> 0 | C726: =IF('Hauling Fleet Management'!$A23="","",'Hauling Fleet Management'!C23) -> 0 | D726: =IF('Hauling Fleet Management'!$A23="","",'Hauling Fleet Management'!D23) -> 0 | E726: =IF('Hauling Fleet Management'!$A23="","",'Hauling Fleet Management'!E23) -> 0 | F726: =IF('Hauling Fleet Management'!$A23="","",'Hauling Fleet Management'!F23) -> 0 | G726: =IF('Hauling Fleet Management'!$A23="","",'Hauling Fleet Management'!G23) -> 0 | H726: =IF('Hauling Fleet Management'!$A23="","",'Hauling Fleet Management'!H23) -> 0 | ... O726: =IF('Hauling Fleet Management'!$A23="","",'Hauling Fleet Management'!O23) -> 0
A727: =IF('Hauling Fleet Management'!$A24="","",'Hauling Fleet Management'!A24) -> Hauling Fleet Management | B727: =IF('Hauling Fleet Management'!$A24="","",'Hauling Fleet Management'!B24) -> 0 | C727: =IF('Hauling Fleet Management'!$A24="","",'Hauling Fleet Management'!C24) -> 0 | D727: =IF('Hauling Fleet Management'!$A24="","",'Hauling Fleet Management'!D24) -> 0 | E727: =IF('Hauling Fleet Management'!$A24="","",'Hauling Fleet Management'!E24) -> 0 | F727: =IF('Hauling Fleet Management'!$A24="","",'Hauling Fleet Management'!F24) -> 0 | G727: =IF('Hauling Fleet Management'!$A24="","",'Hauling Fleet Management'!G24) -> 0 | H727: =IF('Hauling Fleet Management'!$A24="","",'Hauling Fleet Management'!H24) -> 0 | ... O727: =IF('Hauling Fleet Management'!$A24="","",'Hauling Fleet Management'!O24) -> 0
... A953: =IF('Hauling Fleet Management'!$A250="","",'Hauling Fleet Management'!A250) -> Hauling Fleet Management | B953: =IF('Hauling Fleet Management'!$A250="","",'Hauling Fleet Management'!B250) -> 0 | C953: =IF('Hauling Fleet Management'!$A250="","",'Hauling Fleet Management'!C250) -> 0 | D953: =IF('Hauling Fleet Management'!$A250="","",'Hauling Fleet Management'!D250) -> 0 | E953: =IF('Hauling Fleet Management'!$A250="","",'Hauling Fleet Management'!E250) -> 0 | F953: =IF('Hauling Fleet Management'!$A250="","",'Hauling Fleet Management'!F250) -> 0 | G953: =IF('Hauling Fleet Management'!$A250="","",'Hauling Fleet Management'!G250) -> 0 | H953: =IF('Hauling Fleet Management'!$A250="","",'Hauling Fleet Management'!H250) -> 0 | ... O953: =IF('Hauling Fleet Management'!$A250="","",'Hauling Fleet Management'!O250) -> 0
A954: =IF('Mining Eyes Analytics'!$A13="","",'Mining Eyes Analytics'!A13) -> Mining Eyes Analytics | B954: =IF('Mining Eyes Analytics'!$A13="","",'Mining Eyes Analytics'!B13) -> Gate 1 | C954: =IF('Mining Eyes Analytics'!$A13="","",'Mining Eyes Analytics'!C13) -> Technical Feasibility | D954: =IF('Mining Eyes Analytics'!$A13="","",'Mining Eyes Analytics'!D13) -> Yes | E954: =IF('Mining Eyes Analytics'!$A13="","",'Mining Eyes Analytics'!E13) -> Menilai kelayakan teknis dasar solusi sebelum pilot dilanjutkan atau diperluas. | F954: =IF('Mining Eyes Analytics'!$A13="","",'Mining Eyes Analytics'!F13) -> Untuk proyek Mining Eyes Analytics, gate ini fokus pada camera uptime, inference flow, bandwidth, and stream stability. | G954: =IF('Mining Eyes Analytics'!$A13="","",'Mining Eyes Analytics'!G13) -> Kesiapan infrastruktur, integrasi sistem, kualitas data/sinyal, stabilitas teknis, uptime, latency, dan reliability. | H954: =IF('Mining Eyes Analytics'!$A13="","",'Mining Eyes Analytics'!H13) -> Lengkapi evidence hasil uji teknis, gap teknis terbuka, mitigasi, dan rekomendasi readiness. | ... O954: =IF('Mining Eyes Analytics'!$A13="","",'Mining Eyes Analytics'!O13) -> 0
A955: =IF('Mining Eyes Analytics'!$A14="","",'Mining Eyes Analytics'!A14) -> Mining Eyes Analytics | B955: =IF('Mining Eyes Analytics'!$A14="","",'Mining Eyes Analytics'!B14) -> Gate 2 | C955: =IF('Mining Eyes Analytics'!$A14="","",'Mining Eyes Analytics'!C14) -> Performance / Effectiveness | D955: =IF('Mining Eyes Analytics'!$A14="","",'Mining Eyes Analytics'!D14) -> No | E955: =IF('Mining Eyes Analytics'!$A14="","",'Mining Eyes Analytics'!E14) -> Membuktikan bahwa solusi memberi hasil operasional yang relevan dengan tujuan proyek. | F955: =IF('Mining Eyes Analytics'!$A14="","",'Mining Eyes Analytics'!F14) -> Untuk proyek Mining Eyes Analytics, gate ini fokus pada precision, recall, alert usefulness, and missed-event reduction. | G955: =IF('Mining Eyes Analytics'!$A14="","",'Mining Eyes Analytics'!G14) -> Akurasi, efektivitas, availability, pengurangan loss, peningkatan produktivitas, atau manfaat performa lain sesuai use case. | H955: =IF('Mining Eyes Analytics'!$A14="","",'Mining Eyes Analytics'!H14) -> Lengkapi baseline vs actual, hasil pilot, variasi performa, akar masalah, dan action plan. | ... O955: =IF('Mining Eyes Analytics'!$A14="","",'Mining Eyes Analytics'!O14) -> 0
A956: =IF('Mining Eyes Analytics'!$A15="","",'Mining Eyes Analytics'!A15) -> Mining Eyes Analytics | B956: =IF('Mining Eyes Analytics'!$A15="","",'Mining Eyes Analytics'!B15) -> Gate 3 | C956: =IF('Mining Eyes Analytics'!$A15="","",'Mining Eyes Analytics'!C15) -> Safety Case & Procedure | D956: =IF('Mining Eyes Analytics'!$A15="","",'Mining Eyes Analytics'!D15) -> Yes | E956: =IF('Mining Eyes Analytics'!$A15="","",'Mining Eyes Analytics'!E15) -> Memastikan proyek aman dijalankan dan governance operasionalnya siap. | F956: =IF('Mining Eyes Analytics'!$A15="","",'Mining Eyes Analytics'!F15) -> Untuk proyek Mining Eyes Analytics, gate ini fokus pada alert escalation, role clarity, verification workflow, and evidence retention. | G956: =IF('Mining Eyes Analytics'!$A15="","",'Mining Eyes Analytics'!G15) -> SOP, override, fail-safe, escalation path, audit trail, handover, interlock, dan penutupan risiko kritikal. | H956: =IF('Mining Eyes Analytics'!$A15="","",'Mining Eyes Analytics'!H15) -> Lengkapi status SOP, hasil simulasi/drill, kontrol keselamatan, approval safety, dan gap residual. | ... O956: =IF('Mining Eyes Analytics'!$A15="","",'Mining Eyes Analytics'!O15) -> 0
A957: =IF('Mining Eyes Analytics'!$A16="","",'Mining Eyes Analytics'!A16) -> Mining Eyes Analytics | B957: =IF('Mining Eyes Analytics'!$A16="","",'Mining Eyes Analytics'!B16) -> Gate 4 | C957: =IF('Mining Eyes Analytics'!$A16="","",'Mining Eyes Analytics'!C16) -> Business / Assurance | D957: =IF('Mining Eyes Analytics'!$A16="","",'Mining Eyes Analytics'!D16) -> No | E957: =IF('Mining Eyes Analytics'!$A16="","",'Mining Eyes Analytics'!E16) -> Menilai kelayakan scale-up dari sisi bisnis, assurance, atau keekonomian. | F957: =IF('Mining Eyes Analytics'!$A16="","",'Mining Eyes Analytics'!F16) -> Untuk proyek Mining Eyes Analytics, gate ini fokus pada monitoring coverage, assurance value, and reduction of missed critical events. | G957: =IF('Mining Eyes Analytics'!$A16="","",'Mining Eyes Analytics'!G16) -> Nilai bisnis, reduction of exposure/loss, assurance value, economic case, payback, ROI, atau justification deployment lebih luas. | H957: =IF('Mining Eyes Analytics'!$A16="","",'Mining Eyes Analytics'!H16) -> Lengkapi manfaat terukur, asumsi bisnis/ekonomi, alasan scale-up, risiko bisnis, dan rekomendasi akhir. | ... O957: =IF('Mining Eyes Analytics'!$A16="","",'Mining Eyes Analytics'!O16) -> 0
A958: =IF('Mining Eyes Analytics'!$A17="","",'Mining Eyes Analytics'!A17) -> Mining Eyes Analytics | B958: =IF('Mining Eyes Analytics'!$A17="","",'Mining Eyes Analytics'!B17) -> 0 | C958: =IF('Mining Eyes Analytics'!$A17="","",'Mining Eyes Analytics'!C17) -> 0 | D958: =IF('Mining Eyes Analytics'!$A17="","",'Mining Eyes Analytics'!D17) -> 0 | E958: =IF('Mining Eyes Analytics'!$A17="","",'Mining Eyes Analytics'!E17) -> 0 | F958: =IF('Mining Eyes Analytics'!$A17="","",'Mining Eyes Analytics'!F17) -> 0 | G958: =IF('Mining Eyes Analytics'!$A17="","",'Mining Eyes Analytics'!G17) -> 0 | H958: =IF('Mining Eyes Analytics'!$A17="","",'Mining Eyes Analytics'!H17) -> 0 | ... O958: =IF('Mining Eyes Analytics'!$A17="","",'Mining Eyes Analytics'!O17) -> 0
A959: =IF('Mining Eyes Analytics'!$A18="","",'Mining Eyes Analytics'!A18) -> Mining Eyes Analytics | B959: =IF('Mining Eyes Analytics'!$A18="","",'Mining Eyes Analytics'!B18) -> 0 | C959: =IF('Mining Eyes Analytics'!$A18="","",'Mining Eyes Analytics'!C18) -> 0 | D959: =IF('Mining Eyes Analytics'!$A18="","",'Mining Eyes Analytics'!D18) -> 0 | E959: =IF('Mining Eyes Analytics'!$A18="","",'Mining Eyes Analytics'!E18) -> 0 | F959: =IF('Mining Eyes Analytics'!$A18="","",'Mining Eyes Analytics'!F18) -> 0 | G959: =IF('Mining Eyes Analytics'!$A18="","",'Mining Eyes Analytics'!G18) -> 0 | H959: =IF('Mining Eyes Analytics'!$A18="","",'Mining Eyes Analytics'!H18) -> 0 | ... O959: =IF('Mining Eyes Analytics'!$A18="","",'Mining Eyes Analytics'!O18) -> 0
A960: =IF('Mining Eyes Analytics'!$A19="","",'Mining Eyes Analytics'!A19) -> Mining Eyes Analytics | B960: =IF('Mining Eyes Analytics'!$A19="","",'Mining Eyes Analytics'!B19) -> 0 | C960: =IF('Mining Eyes Analytics'!$A19="","",'Mining Eyes Analytics'!C19) -> 0 | D960: =IF('Mining Eyes Analytics'!$A19="","",'Mining Eyes Analytics'!D19) -> 0 | E960: =IF('Mining Eyes Analytics'!$A19="","",'Mining Eyes Analytics'!E19) -> 0 | F960: =IF('Mining Eyes Analytics'!$A19="","",'Mining Eyes Analytics'!F19) -> 0 | G960: =IF('Mining Eyes Analytics'!$A19="","",'Mining Eyes Analytics'!G19) -> 0 | H960: =IF('Mining Eyes Analytics'!$A19="","",'Mining Eyes Analytics'!H19) -> 0 | ... O960: =IF('Mining Eyes Analytics'!$A19="","",'Mining Eyes Analytics'!O19) -> 0
A961: =IF('Mining Eyes Analytics'!$A20="","",'Mining Eyes Analytics'!A20) -> Mining Eyes Analytics | B961: =IF('Mining Eyes Analytics'!$A20="","",'Mining Eyes Analytics'!B20) -> 0 | C961: =IF('Mining Eyes Analytics'!$A20="","",'Mining Eyes Analytics'!C20) -> 0 | D961: =IF('Mining Eyes Analytics'!$A20="","",'Mining Eyes Analytics'!D20) -> 0 | E961: =IF('Mining Eyes Analytics'!$A20="","",'Mining Eyes Analytics'!E20) -> 0 | F961: =IF('Mining Eyes Analytics'!$A20="","",'Mining Eyes Analytics'!F20) -> 0 | G961: =IF('Mining Eyes Analytics'!$A20="","",'Mining Eyes Analytics'!G20) -> 0 | H961: =IF('Mining Eyes Analytics'!$A20="","",'Mining Eyes Analytics'!H20) -> 0 | ... O961: =IF('Mining Eyes Analytics'!$A20="","",'Mining Eyes Analytics'!O20) -> 0
A962: =IF('Mining Eyes Analytics'!$A21="","",'Mining Eyes Analytics'!A21) -> Mining Eyes Analytics | B962: =IF('Mining Eyes Analytics'!$A21="","",'Mining Eyes Analytics'!B21) -> 0 | C962: =IF('Mining Eyes Analytics'!$A21="","",'Mining Eyes Analytics'!C21) -> 0 | D962: =IF('Mining Eyes Analytics'!$A21="","",'Mining Eyes Analytics'!D21) -> 0 | E962: =IF('Mining Eyes Analytics'!$A21="","",'Mining Eyes Analytics'!E21) -> 0 | F962: =IF('Mining Eyes Analytics'!$A21="","",'Mining Eyes Analytics'!F21) -> 0 | G962: =IF('Mining Eyes Analytics'!$A21="","",'Mining Eyes Analytics'!G21) -> 0 | H962: =IF('Mining Eyes Analytics'!$A21="","",'Mining Eyes Analytics'!H21) -> 0 | ... O962: =IF('Mining Eyes Analytics'!$A21="","",'Mining Eyes Analytics'!O21) -> 0
A963: =IF('Mining Eyes Analytics'!$A22="","",'Mining Eyes Analytics'!A22) -> Mining Eyes Analytics | B963: =IF('Mining Eyes Analytics'!$A22="","",'Mining Eyes Analytics'!B22) -> 0 | C963: =IF('Mining Eyes Analytics'!$A22="","",'Mining Eyes Analytics'!C22) -> 0 | D963: =IF('Mining Eyes Analytics'!$A22="","",'Mining Eyes Analytics'!D22) -> 0 | E963: =IF('Mining Eyes Analytics'!$A22="","",'Mining Eyes Analytics'!E22) -> 0 | F963: =IF('Mining Eyes Analytics'!$A22="","",'Mining Eyes Analytics'!F22) -> 0 | G963: =IF('Mining Eyes Analytics'!$A22="","",'Mining Eyes Analytics'!G22) -> 0 | H963: =IF('Mining Eyes Analytics'!$A22="","",'Mining Eyes Analytics'!H22) -> 0 | ... O963: =IF('Mining Eyes Analytics'!$A22="","",'Mining Eyes Analytics'!O22) -> 0
A964: =IF('Mining Eyes Analytics'!$A23="","",'Mining Eyes Analytics'!A23) -> Mining Eyes Analytics | B964: =IF('Mining Eyes Analytics'!$A23="","",'Mining Eyes Analytics'!B23) -> 0 | C964: =IF('Mining Eyes Analytics'!$A23="","",'Mining Eyes Analytics'!C23) -> 0 | D964: =IF('Mining Eyes Analytics'!$A23="","",'Mining Eyes Analytics'!D23) -> 0 | E964: =IF('Mining Eyes Analytics'!$A23="","",'Mining Eyes Analytics'!E23) -> 0 | F964: =IF('Mining Eyes Analytics'!$A23="","",'Mining Eyes Analytics'!F23) -> 0 | G964: =IF('Mining Eyes Analytics'!$A23="","",'Mining Eyes Analytics'!G23) -> 0 | H964: =IF('Mining Eyes Analytics'!$A23="","",'Mining Eyes Analytics'!H23) -> 0 | ... O964: =IF('Mining Eyes Analytics'!$A23="","",'Mining Eyes Analytics'!O23) -> 0
A965: =IF('Mining Eyes Analytics'!$A24="","",'Mining Eyes Analytics'!A24) -> Mining Eyes Analytics | B965: =IF('Mining Eyes Analytics'!$A24="","",'Mining Eyes Analytics'!B24) -> 0 | C965: =IF('Mining Eyes Analytics'!$A24="","",'Mining Eyes Analytics'!C24) -> 0 | D965: =IF('Mining Eyes Analytics'!$A24="","",'Mining Eyes Analytics'!D24) -> 0 | E965: =IF('Mining Eyes Analytics'!$A24="","",'Mining Eyes Analytics'!E24) -> 0 | F965: =IF('Mining Eyes Analytics'!$A24="","",'Mining Eyes Analytics'!F24) -> 0 | G965: =IF('Mining Eyes Analytics'!$A24="","",'Mining Eyes Analytics'!G24) -> 0 | H965: =IF('Mining Eyes Analytics'!$A24="","",'Mining Eyes Analytics'!H24) -> 0 | ... O965: =IF('Mining Eyes Analytics'!$A24="","",'Mining Eyes Analytics'!O24) -> 0
... A1191: =IF('Mining Eyes Analytics'!$A250="","",'Mining Eyes Analytics'!A250) -> Mining Eyes Analytics | B1191: =IF('Mining Eyes Analytics'!$A250="","",'Mining Eyes Analytics'!B250) -> 0 | C1191: =IF('Mining Eyes Analytics'!$A250="","",'Mining Eyes Analytics'!C250) -> 0 | D1191: =IF('Mining Eyes Analytics'!$A250="","",'Mining Eyes Analytics'!D250) -> 0 | E1191: =IF('Mining Eyes Analytics'!$A250="","",'Mining Eyes Analytics'!E250) -> 0 | F1191: =IF('Mining Eyes Analytics'!$A250="","",'Mining Eyes Analytics'!F250) -> 0 | G1191: =IF('Mining Eyes Analytics'!$A250="","",'Mining Eyes Analytics'!G250) -> 0 | H1191: =IF('Mining Eyes Analytics'!$A250="","",'Mining Eyes Analytics'!H250) -> 0 | ... O1191: =IF('Mining Eyes Analytics'!$A250="","",'Mining Eyes Analytics'!O250) -> 0
A1192: =IF('Remote Dozer'!$A13="","",'Remote Dozer'!A13) -> Remote Dozer | B1192: =IF('Remote Dozer'!$A13="","",'Remote Dozer'!B13) -> Gate 1 | C1192: =IF('Remote Dozer'!$A13="","",'Remote Dozer'!C13) -> Technical Feasibility | D1192: =IF('Remote Dozer'!$A13="","",'Remote Dozer'!D13) -> Yes | E1192: =IF('Remote Dozer'!$A13="","",'Remote Dozer'!E13) -> Menilai kelayakan teknis dasar solusi sebelum pilot dilanjutkan atau diperluas. | F1192: =IF('Remote Dozer'!$A13="","",'Remote Dozer'!F13) -> Untuk proyek Remote Dozer, gate ini fokus pada network readiness, command latency, and telemetry stability for remote dozing. | G1192: =IF('Remote Dozer'!$A13="","",'Remote Dozer'!G13) -> Kesiapan infrastruktur, integrasi sistem, kualitas data/sinyal, stabilitas teknis, uptime, latency, dan reliability. | H1192: =IF('Remote Dozer'!$A13="","",'Remote Dozer'!H13) -> Lengkapi evidence hasil uji teknis, gap teknis terbuka, mitigasi, dan rekomendasi readiness. | ... O1192: =IF('Remote Dozer'!$A13="","",'Remote Dozer'!O13) -> 0
A1193: =IF('Remote Dozer'!$A14="","",'Remote Dozer'!A14) -> Remote Dozer | B1193: =IF('Remote Dozer'!$A14="","",'Remote Dozer'!B14) -> Gate 2 | C1193: =IF('Remote Dozer'!$A14="","",'Remote Dozer'!C14) -> Performance / Effectiveness | D1193: =IF('Remote Dozer'!$A14="","",'Remote Dozer'!D14) -> No | E1193: =IF('Remote Dozer'!$A14="","",'Remote Dozer'!E14) -> Membuktikan bahwa solusi memberi hasil operasional yang relevan dengan tujuan proyek. | F1193: =IF('Remote Dozer'!$A14="","",'Remote Dozer'!F14) -> Untuk proyek Remote Dozer, gate ini fokus pada distance reduction, remote availability, and fuel-saving effectiveness. | G1193: =IF('Remote Dozer'!$A14="","",'Remote Dozer'!G14) -> Akurasi, efektivitas, availability, pengurangan loss, peningkatan produktivitas, atau manfaat performa lain sesuai use case. | H1193: =IF('Remote Dozer'!$A14="","",'Remote Dozer'!H14) -> Lengkapi baseline vs actual, hasil pilot, variasi performa, akar masalah, dan action plan. | ... O1193: =IF('Remote Dozer'!$A14="","",'Remote Dozer'!O14) -> 0
A1194: =IF('Remote Dozer'!$A15="","",'Remote Dozer'!A15) -> Remote Dozer | B1194: =IF('Remote Dozer'!$A15="","",'Remote Dozer'!B15) -> Gate 3 | C1194: =IF('Remote Dozer'!$A15="","",'Remote Dozer'!C15) -> Safety Case & Procedure | D1194: =IF('Remote Dozer'!$A15="","",'Remote Dozer'!D15) -> Yes | E1194: =IF('Remote Dozer'!$A15="","",'Remote Dozer'!E15) -> Memastikan proyek aman dijalankan dan governance operasionalnya siap. | F1194: =IF('Remote Dozer'!$A15="","",'Remote Dozer'!F15) -> Untuk proyek Remote Dozer, gate ini fokus pada emergency stop, fail-safe logic, zone control, and remote handover readiness. | G1194: =IF('Remote Dozer'!$A15="","",'Remote Dozer'!G15) -> SOP, override, fail-safe, escalation path, audit trail, handover, interlock, dan penutupan risiko kritikal. | H1194: =IF('Remote Dozer'!$A15="","",'Remote Dozer'!H15) -> Lengkapi status SOP, hasil simulasi/drill, kontrol keselamatan, approval safety, dan gap residual. | ... O1194: =IF('Remote Dozer'!$A15="","",'Remote Dozer'!O15) -> 0
A1195: =IF('Remote Dozer'!$A16="","",'Remote Dozer'!A16) -> Remote Dozer | B1195: =IF('Remote Dozer'!$A16="","",'Remote Dozer'!B16) -> Gate 4 | C1195: =IF('Remote Dozer'!$A16="","",'Remote Dozer'!C16) -> Business / Economical Pass | D1195: =IF('Remote Dozer'!$A16="","",'Remote Dozer'!D16) -> No | E1195: =IF('Remote Dozer'!$A16="","",'Remote Dozer'!E16) -> Menilai kelayakan scale-up dari sisi bisnis, assurance, atau keekonomian. | F1195: =IF('Remote Dozer'!$A16="","",'Remote Dozer'!F16) -> Untuk proyek Remote Dozer, gate ini fokus pada net saving, payback, and long-term roi from remote dozer deployment. | G1195: =IF('Remote Dozer'!$A16="","",'Remote Dozer'!G16) -> Nilai bisnis, reduction of exposure/loss, assurance value, economic case, payback, ROI, atau justification deployment lebih luas. | H1195: =IF('Remote Dozer'!$A16="","",'Remote Dozer'!H16) -> Lengkapi manfaat terukur, asumsi bisnis/ekonomi, alasan scale-up, risiko bisnis, dan rekomendasi akhir. | ... O1195: =IF('Remote Dozer'!$A16="","",'Remote Dozer'!O16) -> 0
A1196: =IF('Remote Dozer'!$A17="","",'Remote Dozer'!A17) -> Remote Dozer | B1196: =IF('Remote Dozer'!$A17="","",'Remote Dozer'!B17) -> 0 | C1196: =IF('Remote Dozer'!$A17="","",'Remote Dozer'!C17) -> 0 | D1196: =IF('Remote Dozer'!$A17="","",'Remote Dozer'!D17) -> 0 | E1196: =IF('Remote Dozer'!$A17="","",'Remote Dozer'!E17) -> 0 | F1196: =IF('Remote Dozer'!$A17="","",'Remote Dozer'!F17) -> 0 | G1196: =IF('Remote Dozer'!$A17="","",'Remote Dozer'!G17) -> 0 | H1196: =IF('Remote Dozer'!$A17="","",'Remote Dozer'!H17) -> 0 | ... O1196: =IF('Remote Dozer'!$A17="","",'Remote Dozer'!O17) -> 0
A1197: =IF('Remote Dozer'!$A18="","",'Remote Dozer'!A18) -> Remote Dozer | B1197: =IF('Remote Dozer'!$A18="","",'Remote Dozer'!B18) -> 0 | C1197: =IF('Remote Dozer'!$A18="","",'Remote Dozer'!C18) -> 0 | D1197: =IF('Remote Dozer'!$A18="","",'Remote Dozer'!D18) -> 0 | E1197: =IF('Remote Dozer'!$A18="","",'Remote Dozer'!E18) -> 0 | F1197: =IF('Remote Dozer'!$A18="","",'Remote Dozer'!F18) -> 0 | G1197: =IF('Remote Dozer'!$A18="","",'Remote Dozer'!G18) -> 0 | H1197: =IF('Remote Dozer'!$A18="","",'Remote Dozer'!H18) -> 0 | ... O1197: =IF('Remote Dozer'!$A18="","",'Remote Dozer'!O18) -> 0
A1198: =IF('Remote Dozer'!$A19="","",'Remote Dozer'!A19) -> Remote Dozer | B1198: =IF('Remote Dozer'!$A19="","",'Remote Dozer'!B19) -> 0 | C1198: =IF('Remote Dozer'!$A19="","",'Remote Dozer'!C19) -> 0 | D1198: =IF('Remote Dozer'!$A19="","",'Remote Dozer'!D19) -> 0 | E1198: =IF('Remote Dozer'!$A19="","",'Remote Dozer'!E19) -> 0 | F1198: =IF('Remote Dozer'!$A19="","",'Remote Dozer'!F19) -> 0 | G1198: =IF('Remote Dozer'!$A19="","",'Remote Dozer'!G19) -> 0 | H1198: =IF('Remote Dozer'!$A19="","",'Remote Dozer'!H19) -> 0 | ... O1198: =IF('Remote Dozer'!$A19="","",'Remote Dozer'!O19) -> 0
A1199: =IF('Remote Dozer'!$A20="","",'Remote Dozer'!A20) -> Remote Dozer | B1199: =IF('Remote Dozer'!$A20="","",'Remote Dozer'!B20) -> 0 | C1199: =IF('Remote Dozer'!$A20="","",'Remote Dozer'!C20) -> 0 | D1199: =IF('Remote Dozer'!$A20="","",'Remote Dozer'!D20) -> 0 | E1199: =IF('Remote Dozer'!$A20="","",'Remote Dozer'!E20) -> 0 | F1199: =IF('Remote Dozer'!$A20="","",'Remote Dozer'!F20) -> 0 | G1199: =IF('Remote Dozer'!$A20="","",'Remote Dozer'!G20) -> 0 | H1199: =IF('Remote Dozer'!$A20="","",'Remote Dozer'!H20) -> 0 | ... O1199: =IF('Remote Dozer'!$A20="","",'Remote Dozer'!O20) -> 0
A1200: =IF('Remote Dozer'!$A21="","",'Remote Dozer'!A21) -> Remote Dozer | B1200: =IF('Remote Dozer'!$A21="","",'Remote Dozer'!B21) -> 0 | C1200: =IF('Remote Dozer'!$A21="","",'Remote Dozer'!C21) -> 0 | D1200: =IF('Remote Dozer'!$A21="","",'Remote Dozer'!D21) -> 0 | E1200: =IF('Remote Dozer'!$A21="","",'Remote Dozer'!E21) -> 0 | F1200: =IF('Remote Dozer'!$A21="","",'Remote Dozer'!F21) -> 0 | G1200: =IF('Remote Dozer'!$A21="","",'Remote Dozer'!G21) -> 0 | H1200: =IF('Remote Dozer'!$A21="","",'Remote Dozer'!H21) -> 0 | ... O1200: =IF('Remote Dozer'!$A21="","",'Remote Dozer'!O21) -> 0
A1201: =IF('Remote Dozer'!$A22="","",'Remote Dozer'!A22) -> Remote Dozer | B1201: =IF('Remote Dozer'!$A22="","",'Remote Dozer'!B22) -> 0 | C1201: =IF('Remote Dozer'!$A22="","",'Remote Dozer'!C22) -> 0 | D1201: =IF('Remote Dozer'!$A22="","",'Remote Dozer'!D22) -> 0 | E1201: =IF('Remote Dozer'!$A22="","",'Remote Dozer'!E22) -> 0 | F1201: =IF('Remote Dozer'!$A22="","",'Remote Dozer'!F22) -> 0 | G1201: =IF('Remote Dozer'!$A22="","",'Remote Dozer'!G22) -> 0 | H1201: =IF('Remote Dozer'!$A22="","",'Remote Dozer'!H22) -> 0 | ... O1201: =IF('Remote Dozer'!$A22="","",'Remote Dozer'!O22) -> 0
A1202: =IF('Remote Dozer'!$A23="","",'Remote Dozer'!A23) -> Remote Dozer | B1202: =IF('Remote Dozer'!$A23="","",'Remote Dozer'!B23) -> 0 | C1202: =IF('Remote Dozer'!$A23="","",'Remote Dozer'!C23) -> 0 | D1202: =IF('Remote Dozer'!$A23="","",'Remote Dozer'!D23) -> 0 | E1202: =IF('Remote Dozer'!$A23="","",'Remote Dozer'!E23) -> 0 | F1202: =IF('Remote Dozer'!$A23="","",'Remote Dozer'!F23) -> 0 | G1202: =IF('Remote Dozer'!$A23="","",'Remote Dozer'!G23) -> 0 | H1202: =IF('Remote Dozer'!$A23="","",'Remote Dozer'!H23) -> 0 | ... O1202: =IF('Remote Dozer'!$A23="","",'Remote Dozer'!O23) -> 0
A1203: =IF('Remote Dozer'!$A24="","",'Remote Dozer'!A24) -> Remote Dozer | B1203: =IF('Remote Dozer'!$A24="","",'Remote Dozer'!B24) -> 0 | C1203: =IF('Remote Dozer'!$A24="","",'Remote Dozer'!C24) -> 0 | D1203: =IF('Remote Dozer'!$A24="","",'Remote Dozer'!D24) -> 0 | E1203: =IF('Remote Dozer'!$A24="","",'Remote Dozer'!E24) -> 0 | F1203: =IF('Remote Dozer'!$A24="","",'Remote Dozer'!F24) -> 0 | G1203: =IF('Remote Dozer'!$A24="","",'Remote Dozer'!G24) -> 0 | H1203: =IF('Remote Dozer'!$A24="","",'Remote Dozer'!H24) -> 0 | ... O1203: =IF('Remote Dozer'!$A24="","",'Remote Dozer'!O24) -> 0
... A1429: =IF('Remote Dozer'!$A250="","",'Remote Dozer'!A250) -> Remote Dozer | B1429: =IF('Remote Dozer'!$A250="","",'Remote Dozer'!B250) -> 0 | C1429: =IF('Remote Dozer'!$A250="","",'Remote Dozer'!C250) -> 0 | D1429: =IF('Remote Dozer'!$A250="","",'Remote Dozer'!D250) -> 0 | E1429: =IF('Remote Dozer'!$A250="","",'Remote Dozer'!E250) -> 0 | F1429: =IF('Remote Dozer'!$A250="","",'Remote Dozer'!F250) -> 0 | G1429: =IF('Remote Dozer'!$A250="","",'Remote Dozer'!G250) -> 0 | H1429: =IF('Remote Dozer'!$A250="","",'Remote Dozer'!H250) -> 0 | ... O1429: =IF('Remote Dozer'!$A250="","",'Remote Dozer'!O250) -> 0

Sheet Gate_Metrics
A1: Project | B1: Gate | C1: Gate Title | D1: Metric Name | E1: Metric Description | F1: Metric Type | G1: Direction | H1: Critical | I1: Unit | J1: Current Value | K1: Pass Threshold | L1: Conditional Threshold | M1: Min | N1: Max | O1: Step | P1: PIC Current Finding | Q1: PIC Evidence / Source | R1: PIC Comment | S1: Metric Status
A2: =IF('Arcas HD'!$Q13="","",'Arcas HD'!Q13) -> Arcas HD | B2: =IF('Arcas HD'!$Q13="","",'Arcas HD'!R13) -> Gate 1 | C2: =IF('Arcas HD'!$Q13="","",'Arcas HD'!S13) -> Technical Feasibility | D2: =IF('Arcas HD'!$Q13="","",'Arcas HD'!T13) -> Instalasi power & converter 12V - Setup jaringan (router/modem) - Uji koneksi remote Uji koneksi tanpa streaming Uji remote basic control | E2: =IF('Arcas HD'!$Q13="","",'Arcas HD'!U13) -> Network uptime stabil Packet loss rendah Respons koneksi | F2: =IF('Arcas HD'!$Q13="","",'Arcas HD'!V13) -> system | G2: =IF('Arcas HD'!$Q13="","",'Arcas HD'!W13) -> high | H2: =IF('Arcas HD'!$Q13="","",'Arcas HD'!X13) -> No | ... S2: =IF('Arcas HD'!$Q13="","",'Arcas HD'!AI13) -> pass
A3: =IF('Arcas HD'!$Q14="","",'Arcas HD'!Q14) -> Arcas HD | B3: =IF('Arcas HD'!$Q14="","",'Arcas HD'!R14) -> Gate 1 | C3: =IF('Arcas HD'!$Q14="","",'Arcas HD'!S14) -> Technical Feasibility | D3: =IF('Arcas HD'!$Q14="","",'Arcas HD'!T14) -> Testing YOLO lokal (tanpa streaming) - Testing RTSP streaming Uji VLC / RTSP push | E3: =IF('Arcas HD'!$Q14="","",'Arcas HD'!U14) -> Round-trip response delay during operation dan Mampu mendeteksi tanggulan dan air dalam conf 0.8 rata rata | F3: =IF('Arcas HD'!$Q14="","",'Arcas HD'!V14) -> deteksi | G3: =IF('Arcas HD'!$Q14="","",'Arcas HD'!W14) -> low | H3: =IF('Arcas HD'!$Q14="","",'Arcas HD'!X14) -> Yes | ... S3: =IF('Arcas HD'!$Q14="","",'Arcas HD'!AI14) -> Conditional
A4: =IF('Arcas HD'!$Q16="","",'Arcas HD'!Q16) -> Arcas HD | B4: =IF('Arcas HD'!$Q16="","",'Arcas HD'!R16) -> Gate 1 | C4: =IF('Arcas HD'!$Q16="","",'Arcas HD'!S16) -> Technical Feasibility | D4: =IF('Arcas HD'!$Q16="","",'Arcas HD'!T16) -> Setup logging system - Monitoring koneksi end-to-end, Logging error & event | E4: =IF('Arcas HD'!$Q16="","",'Arcas HD'!U16) -> Status monitoring aktif 100% node terbaca Data tersimpan = Tidak ada loss log >5% | F4: =IF('Arcas HD'!$Q16="","",'Arcas HD'!V16) -> select | G4: =IF('Arcas HD'!$Q16="","",'Arcas HD'!W16) -> high | H4: =IF('Arcas HD'!$Q16="","",'Arcas HD'!X16) -> Yes | ... S4: =IF('Arcas HD'!$Q16="","",'Arcas HD'!AI16) -> Need Check
A5: =IF('Arcas HD'!$Q17="","",'Arcas HD'!Q17) -> Arcas HD | B5: =IF('Arcas HD'!$Q17="","",'Arcas HD'!R17) -> Gate 2 | C5: =IF('Arcas HD'!$Q17="","",'Arcas HD'!S17) -> Performance / Effectiveness | D5: =IF('Arcas HD'!$Q17="","",'Arcas HD'!T17) -> Precision | E5: =IF('Arcas HD'!$Q17="","",'Arcas HD'!U17) -> Akurasi deteksi ≥ 90% Noise detection < 10% | F5: =IF('Arcas HD'!$Q17="","",'Arcas HD'!V17) -> range | G5: =IF('Arcas HD'!$Q17="","",'Arcas HD'!W17) -> high | H5: =IF('Arcas HD'!$Q17="","",'Arcas HD'!X17) -> No | ... S5: =IF('Arcas HD'!$Q17="","",'Arcas HD'!AI17) -> Pass
A6: =IF('Arcas HD'!$Q18="","",'Arcas HD'!Q18) -> Arcas HD | B6: =IF('Arcas HD'!$Q18="","",'Arcas HD'!R18) -> Gate 2 | C6: =IF('Arcas HD'!$Q18="","",'Arcas HD'!S18) -> Performance / Effectiveness | D6: =IF('Arcas HD'!$Q18="","",'Arcas HD'!T18) -> Recall | E6: =IF('Arcas HD'!$Q18="","",'Arcas HD'!U18) -> Stabilitas sensor = Tidak ada spike noise Coverage deteksi ≥ 85% Range efektif ≥ 6 meter stabil | F6: =IF('Arcas HD'!$Q18="","",'Arcas HD'!V18) -> system | G6: =IF('Arcas HD'!$Q18="","",'Arcas HD'!W18) -> high | H6: =IF('Arcas HD'!$Q18="","",'Arcas HD'!X18) -> No | ... S6: =IF('Arcas HD'!$Q18="","",'Arcas HD'!AI18) -> Conditional
A7: =IF('Arcas HD'!$Q19="","",'Arcas HD'!Q19) -> Arcas HD | B7: =IF('Arcas HD'!$Q19="","",'Arcas HD'!R19) -> Gate 3 | C7: =IF('Arcas HD'!$Q19="","",'Arcas HD'!S19) -> Safety Case & Procedure | D7: =IF('Arcas HD'!$Q19="","",'Arcas HD'!T19) -> SOP readiness | E7: =IF('Arcas HD'!$Q19="","",'Arcas HD'!U19) -> Procedure and handover governance completion. | F7: =IF('Arcas HD'!$Q19="","",'Arcas HD'!V19) -> select | G7: =IF('Arcas HD'!$Q19="","",'Arcas HD'!W19) -> 0 | H7: =IF('Arcas HD'!$Q19="","",'Arcas HD'!X19) -> Yes | ... S7: =IF('Arcas HD'!$Q19="","",'Arcas HD'!AI19) -> Not Started
A8: =IF('Arcas HD'!$Q20="","",'Arcas HD'!Q20) -> Arcas HD | B8: =IF('Arcas HD'!$Q20="","",'Arcas HD'!R20) -> Gate 3 | C8: =IF('Arcas HD'!$Q20="","",'Arcas HD'!S20) -> Safety Case & Procedure | D8: =IF('Arcas HD'!$Q20="","",'Arcas HD'!T20) -> Field drill | E8: =IF('Arcas HD'!$Q20="","",'Arcas HD'!U20) -> Simulation and field drill outcome. | F8: =IF('Arcas HD'!$Q20="","",'Arcas HD'!V20) -> select | G8: =IF('Arcas HD'!$Q20="","",'Arcas HD'!W20) -> 0 | H8: =IF('Arcas HD'!$Q20="","",'Arcas HD'!X20) -> Yes | ... S8: =IF('Arcas HD'!$Q20="","",'Arcas HD'!AI20) -> Not Started
A9: =IF('Arcas HD'!$Q21="","",'Arcas HD'!Q21) -> Arcas HD | B9: =IF('Arcas HD'!$Q21="","",'Arcas HD'!R21) -> Gate 4 | C9: =IF('Arcas HD'!$Q21="","",'Arcas HD'!S21) -> Business / Assurance | D9: =IF('Arcas HD'!$Q21="","",'Arcas HD'!T21) -> Exposure reduction | E9: =IF('Arcas HD'!$Q21="","",'Arcas HD'!U21) -> Index of direct exposure removal from hazard zone. | F9: =IF('Arcas HD'!$Q21="","",'Arcas HD'!V21) -> range | G9: =IF('Arcas HD'!$Q21="","",'Arcas HD'!W21) -> high | H9: =IF('Arcas HD'!$Q21="","",'Arcas HD'!X21) -> No | ... S9: =IF('Arcas HD'!$Q21="","",'Arcas HD'!AI21) -> Not Started
A10: =IF('Arcas HD'!$Q22="","",'Arcas HD'!Q22) -> Arcas HD | B10: =IF('Arcas HD'!$Q22="","",'Arcas HD'!R22) -> Gate 4 | C10: =IF('Arcas HD'!$Q22="","",'Arcas HD'!S22) -> Business / Assurance | D10: =IF('Arcas HD'!$Q22="","",'Arcas HD'!T22) -> Business case quality | E10: =IF('Arcas HD'!$Q22="","",'Arcas HD'!U22) -> Overall economic and assurance justification. | F10: =IF('Arcas HD'!$Q22="","",'Arcas HD'!V22) -> select | G10: =IF('Arcas HD'!$Q22="","",'Arcas HD'!W22) -> 0 | H10: =IF('Arcas HD'!$Q22="","",'Arcas HD'!X22) -> No | ... S10: =IF('Arcas HD'!$Q22="","",'Arcas HD'!AI22) -> Not Started
A11: =IF('Arcas HD'!$Q23="","",'Arcas HD'!Q23) -> Arcas HD | B11: =IF('Arcas HD'!$Q23="","",'Arcas HD'!R23) -> 0 | C11: =IF('Arcas HD'!$Q23="","",'Arcas HD'!S23) -> 0 | D11: =IF('Arcas HD'!$Q23="","",'Arcas HD'!T23) -> 0 | E11: =IF('Arcas HD'!$Q23="","",'Arcas HD'!U23) -> 0 | F11: =IF('Arcas HD'!$Q23="","",'Arcas HD'!V23) -> 0 | G11: =IF('Arcas HD'!$Q23="","",'Arcas HD'!W23) -> 0 | H11: =IF('Arcas HD'!$Q23="","",'Arcas HD'!X23) -> 0 | ... S11: =IF('Arcas HD'!$Q23="","",'Arcas HD'!AI23) -> 0
A12: =IF('Arcas HD'!$Q24="","",'Arcas HD'!Q24) -> Arcas HD | B12: =IF('Arcas HD'!$Q24="","",'Arcas HD'!R24) -> 0 | C12: =IF('Arcas HD'!$Q24="","",'Arcas HD'!S24) -> 0 | D12: =IF('Arcas HD'!$Q24="","",'Arcas HD'!T24) -> 0 | E12: =IF('Arcas HD'!$Q24="","",'Arcas HD'!U24) -> 0 | F12: =IF('Arcas HD'!$Q24="","",'Arcas HD'!V24) -> 0 | G12: =IF('Arcas HD'!$Q24="","",'Arcas HD'!W24) -> 0 | H12: =IF('Arcas HD'!$Q24="","",'Arcas HD'!X24) -> 0 | ... S12: =IF('Arcas HD'!$Q24="","",'Arcas HD'!AI24) -> 0
A13: =IF('Arcas HD'!$Q25="","",'Arcas HD'!Q25) -> Arcas HD | B13: =IF('Arcas HD'!$Q25="","",'Arcas HD'!R25) -> 0 | C13: =IF('Arcas HD'!$Q25="","",'Arcas HD'!S25) -> 0 | D13: =IF('Arcas HD'!$Q25="","",'Arcas HD'!T25) -> 0 | E13: =IF('Arcas HD'!$Q25="","",'Arcas HD'!U25) -> 0 | F13: =IF('Arcas HD'!$Q25="","",'Arcas HD'!V25) -> 0 | G13: =IF('Arcas HD'!$Q25="","",'Arcas HD'!W25) -> 0 | H13: =IF('Arcas HD'!$Q25="","",'Arcas HD'!X25) -> 0 | ... S13: =IF('Arcas HD'!$Q25="","",'Arcas HD'!AI25) -> 0
A14: =IF('Arcas HD'!$Q26="","",'Arcas HD'!Q26) -> Arcas HD | B14: =IF('Arcas HD'!$Q26="","",'Arcas HD'!R26) -> 0 | C14: =IF('Arcas HD'!$Q26="","",'Arcas HD'!S26) -> 0 | D14: =IF('Arcas HD'!$Q26="","",'Arcas HD'!T26) -> 0 | E14: =IF('Arcas HD'!$Q26="","",'Arcas HD'!U26) -> 0 | F14: =IF('Arcas HD'!$Q26="","",'Arcas HD'!V26) -> 0 | G14: =IF('Arcas HD'!$Q26="","",'Arcas HD'!W26) -> 0 | H14: =IF('Arcas HD'!$Q26="","",'Arcas HD'!X26) -> 0 | ... S14: =IF('Arcas HD'!$Q26="","",'Arcas HD'!AI26) -> 0
A15: =IF('Arcas HD'!$Q27="","",'Arcas HD'!Q27) -> Arcas HD | B15: =IF('Arcas HD'!$Q27="","",'Arcas HD'!R27) -> 0 | C15: =IF('Arcas HD'!$Q27="","",'Arcas HD'!S27) -> 0 | D15: =IF('Arcas HD'!$Q27="","",'Arcas HD'!T27) -> 0 | E15: =IF('Arcas HD'!$Q27="","",'Arcas HD'!U27) -> 0 | F15: =IF('Arcas HD'!$Q27="","",'Arcas HD'!V27) -> 0 | G15: =IF('Arcas HD'!$Q27="","",'Arcas HD'!W27) -> 0 | H15: =IF('Arcas HD'!$Q27="","",'Arcas HD'!X27) -> 0 | ... S15: =IF('Arcas HD'!$Q27="","",'Arcas HD'!AI27) -> 0
... A239: =IF('Arcas HD'!$Q251="","",'Arcas HD'!Q251) -> Arcas HD | B239: =IF('Arcas HD'!$Q251="","",'Arcas HD'!R251) -> 0 | C239: =IF('Arcas HD'!$Q251="","",'Arcas HD'!S251) -> 0 | D239: =IF('Arcas HD'!$Q251="","",'Arcas HD'!T251) -> 0 | E239: =IF('Arcas HD'!$Q251="","",'Arcas HD'!U251) -> 0 | F239: =IF('Arcas HD'!$Q251="","",'Arcas HD'!V251) -> 0 | G239: =IF('Arcas HD'!$Q251="","",'Arcas HD'!W251) -> 0 | H239: =IF('Arcas HD'!$Q251="","",'Arcas HD'!X251) -> 0 | ... S239: =IF('Arcas HD'!$Q251="","",'Arcas HD'!AI251) -> 0
A240: =IF('MGD PC'!$Q13="","",'MGD PC'!Q13) -> MGD PC | B240: =IF('MGD PC'!$Q13="","",'MGD PC'!R13) -> Gate 1 | C240: =IF('MGD PC'!$Q13="","",'MGD PC'!S13) -> Technical Feasibility | D240: =IF('MGD PC'!$Q13="","",'MGD PC'!T13) -> Position stability | E240: =IF('MGD PC'!$Q13="","",'MGD PC'!U13) -> Stability of location/guidance reference. | F240: =IF('MGD PC'!$Q13="","",'MGD PC'!V13) -> range | G240: =IF('MGD PC'!$Q13="","",'MGD PC'!W13) -> high | H240: =IF('MGD PC'!$Q13="","",'MGD PC'!X13) -> No | ... S240: =IF('MGD PC'!$Q13="","",'MGD PC'!AI13) -> 0
A241: =IF('MGD PC'!$Q14="","",'MGD PC'!Q14) -> MGD PC | B241: =IF('MGD PC'!$Q14="","",'MGD PC'!R14) -> Gate 1 | C241: =IF('MGD PC'!$Q14="","",'MGD PC'!S14) -> Technical Feasibility | D241: =IF('MGD PC'!$Q14="","",'MGD PC'!T14) -> Data completeness | E241: =IF('MGD PC'!$Q14="","",'MGD PC'!U14) -> Availability of pilot evidence for analysis. | F241: =IF('MGD PC'!$Q14="","",'MGD PC'!V14) -> range | G241: =IF('MGD PC'!$Q14="","",'MGD PC'!W14) -> high | H241: =IF('MGD PC'!$Q14="","",'MGD PC'!X14) -> No | ... S241: =IF('MGD PC'!$Q14="","",'MGD PC'!AI14) -> 0
A242: =IF('MGD PC'!$Q15="","",'MGD PC'!Q15) -> MGD PC | B242: =IF('MGD PC'!$Q15="","",'MGD PC'!R15) -> Gate 1 | C242: =IF('MGD PC'!$Q15="","",'MGD PC'!S15) -> Technical Feasibility | D242: =IF('MGD PC'!$Q15="","",'MGD PC'!T15) -> System uptime | E242: =IF('MGD PC'!$Q15="","",'MGD PC'!U15) -> Application and field support uptime. | F242: =IF('MGD PC'!$Q15="","",'MGD PC'!V15) -> range | G242: =IF('MGD PC'!$Q15="","",'MGD PC'!W15) -> high | H242: =IF('MGD PC'!$Q15="","",'MGD PC'!X15) -> Yes | ... S242: =IF('MGD PC'!$Q15="","",'MGD PC'!AI15) -> 0
A243: =IF('MGD PC'!$Q16="","",'MGD PC'!Q16) -> MGD PC | B243: =IF('MGD PC'!$Q16="","",'MGD PC'!R16) -> Gate 2 | C243: =IF('MGD PC'!$Q16="","",'MGD PC'!S16) -> Performance / Effectiveness | D243: =IF('MGD PC'!$Q16="","",'MGD PC'!T16) -> Guidance accuracy | E243: =IF('MGD PC'!$Q16="","",'MGD PC'!U16) -> Accuracy of field guidance versus target. | F243: =IF('MGD PC'!$Q16="","",'MGD PC'!V16) -> range | G243: =IF('MGD PC'!$Q16="","",'MGD PC'!W16) -> high | H243: =IF('MGD PC'!$Q16="","",'MGD PC'!X16) -> No | ... S243: =IF('MGD PC'!$Q16="","",'MGD PC'!AI16) -> 0
A244: =IF('MGD PC'!$Q17="","",'MGD PC'!Q17) -> MGD PC | B244: =IF('MGD PC'!$Q17="","",'MGD PC'!R17) -> Gate 2 | C244: =IF('MGD PC'!$Q17="","",'MGD PC'!S17) -> Performance / Effectiveness | D244: =IF('MGD PC'!$Q17="","",'MGD PC'!T17) -> Rework reduction | E244: =IF('MGD PC'!$Q17="","",'MGD PC'!U17) -> Reduction in repeated work or adjustment. | F244: =IF('MGD PC'!$Q17="","",'MGD PC'!V17) -> range | G244: =IF('MGD PC'!$Q17="","",'MGD PC'!W17) -> high | H244: =IF('MGD PC'!$Q17="","",'MGD PC'!X17) -> No | ... S244: =IF('MGD PC'!$Q17="","",'MGD PC'!AI17) -> 0
A245: =IF('MGD PC'!$Q18="","",'MGD PC'!Q18) -> MGD PC | B245: =IF('MGD PC'!$Q18="","",'MGD PC'!R18) -> Gate 2 | C245: =IF('MGD PC'!$Q18="","",'MGD PC'!S18) -> Performance / Effectiveness | D245: =IF('MGD PC'!$Q18="","",'MGD PC'!T18) -> User acceptance | E245: =IF('MGD PC'!$Q18="","",'MGD PC'!U18) -> Supervisor/operator willingness to use the solution. | F245: =IF('MGD PC'!$Q18="","",'MGD PC'!V18) -> range | G245: =IF('MGD PC'!$Q18="","",'MGD PC'!W18) -> high | H245: =IF('MGD PC'!$Q18="","",'MGD PC'!X18) -> No | ... S245: =IF('MGD PC'!$Q18="","",'MGD PC'!AI18) -> 0
A246: =IF('MGD PC'!$Q19="","",'MGD PC'!Q19) -> MGD PC | B246: =IF('MGD PC'!$Q19="","",'MGD PC'!R19) -> Gate 3 | C246: =IF('MGD PC'!$Q19="","",'MGD PC'!S19) -> Safety Case & Procedure | D246: =IF('MGD PC'!$Q19="","",'MGD PC'!T19) -> Override readiness | E246: =IF('MGD PC'!$Q19="","",'MGD PC'!U19) -> Manual fallback and override usability. | F246: =IF('MGD PC'!$Q19="","",'MGD PC'!V19) -> select | G246: =IF('MGD PC'!$Q19="","",'MGD PC'!W19) -> 0 | H246: =IF('MGD PC'!$Q19="","",'MGD PC'!X19) -> Yes | ... S246: =IF('MGD PC'!$Q19="","",'MGD PC'!AI19) -> 0
A247: =IF('MGD PC'!$Q20="","",'MGD PC'!Q20) -> MGD PC | B247: =IF('MGD PC'!$Q20="","",'MGD PC'!R20) -> Gate 3 | C247: =IF('MGD PC'!$Q20="","",'MGD PC'!S20) -> Safety Case & Procedure | D247: =IF('MGD PC'!$Q20="","",'MGD PC'!T20) -> Pilot SOP | E247: =IF('MGD PC'!$Q20="","",'MGD PC'!U20) -> Approved procedure for assisted/manual operation. | F247: =IF('MGD PC'!$Q20="","",'MGD PC'!V20) -> select | G247: =IF('MGD PC'!$Q20="","",'MGD PC'!W20) -> 0 | H247: =IF('MGD PC'!$Q20="","",'MGD PC'!X20) -> Yes | ... S247: =IF('MGD PC'!$Q20="","",'MGD PC'!AI20) -> 0
A248: =IF('MGD PC'!$Q21="","",'MGD PC'!Q21) -> MGD PC | B248: =IF('MGD PC'!$Q21="","",'MGD PC'!R21) -> Gate 3 | C248: =IF('MGD PC'!$Q21="","",'MGD PC'!S21) -> Safety Case & Procedure | D248: =IF('MGD PC'!$Q21="","",'MGD PC'!T21) -> Critical risk closure | E248: =IF('MGD PC'!$Q21="","",'MGD PC'!U21) -> Closure of open major safety issues. | F248: =IF('MGD PC'!$Q21="","",'MGD PC'!V21) -> range | G248: =IF('MGD PC'!$Q21="","",'MGD PC'!W21) -> high | H248: =IF('MGD PC'!$Q21="","",'MGD PC'!X21) -> Yes | ... S248: =IF('MGD PC'!$Q21="","",'MGD PC'!AI21) -> 0
A249: =IF('MGD PC'!$Q22="","",'MGD PC'!Q22) -> MGD PC | B249: =IF('MGD PC'!$Q22="","",'MGD PC'!R22) -> Gate 4 | C249: =IF('MGD PC'!$Q22="","",'MGD PC'!S22) -> Business / Assurance | D249: =IF('MGD PC'!$Q22="","",'MGD PC'!T22) -> Cycle benefit | E249: =IF('MGD PC'!$Q22="","",'MGD PC'!U22) -> Cycle improvement from assisted guidance. | F249: =IF('MGD PC'!$Q22="","",'MGD PC'!V22) -> range | G249: =IF('MGD PC'!$Q22="","",'MGD PC'!W22) -> high | H249: =IF('MGD PC'!$Q22="","",'MGD PC'!X22) -> No | ... S249: =IF('MGD PC'!$Q22="","",'MGD PC'!AI22) -> 0
A250: =IF('MGD PC'!$Q23="","",'MGD PC'!Q23) -> MGD PC | B250: =IF('MGD PC'!$Q23="","",'MGD PC'!R23) -> Gate 4 | C250: =IF('MGD PC'!$Q23="","",'MGD PC'!S23) -> Business / Assurance | D250: =IF('MGD PC'!$Q23="","",'MGD PC'!T23) -> Waste / rework gain | E250: =IF('MGD PC'!$Q23="","",'MGD PC'!U23) -> Reduction in avoidable quality loss. | F250: =IF('MGD PC'!$Q23="","",'MGD PC'!V23) -> range | G250: =IF('MGD PC'!$Q23="","",'MGD PC'!W23) -> high | H250: =IF('MGD PC'!$Q23="","",'MGD PC'!X23) -> No | ... S250: =IF('MGD PC'!$Q23="","",'MGD PC'!AI23) -> 0
A251: =IF('MGD PC'!$Q24="","",'MGD PC'!Q24) -> MGD PC | B251: =IF('MGD PC'!$Q24="","",'MGD PC'!R24) -> Gate 4 | C251: =IF('MGD PC'!$Q24="","",'MGD PC'!S24) -> Business / Assurance | D251: =IF('MGD PC'!$Q24="","",'MGD PC'!T24) -> Scale rationale | E251: =IF('MGD PC'!$Q24="","",'MGD PC'!U24) -> Readiness to move beyond proof-of-concept stage. | F251: =IF('MGD PC'!$Q24="","",'MGD PC'!V24) -> select | G251: =IF('MGD PC'!$Q24="","",'MGD PC'!W24) -> 0 | H251: =IF('MGD PC'!$Q24="","",'MGD PC'!X24) -> No | ... S251: =IF('MGD PC'!$Q24="","",'MGD PC'!AI24) -> 0
... A477: =IF('MGD PC'!$Q250="","",'MGD PC'!Q250) -> MGD PC | B477: =IF('MGD PC'!$Q250="","",'MGD PC'!R250) -> 0 | C477: =IF('MGD PC'!$Q250="","",'MGD PC'!S250) -> 0 | D477: =IF('MGD PC'!$Q250="","",'MGD PC'!T250) -> 0 | E477: =IF('MGD PC'!$Q250="","",'MGD PC'!U250) -> 0 | F477: =IF('MGD PC'!$Q250="","",'MGD PC'!V250) -> 0 | G477: =IF('MGD PC'!$Q250="","",'MGD PC'!W250) -> 0 | H477: =IF('MGD PC'!$Q250="","",'MGD PC'!X250) -> 0 | ... S477: =IF('MGD PC'!$Q250="","",'MGD PC'!AI250) -> 0
A478: =IF('Remote Pump'!$Q13="","",'Remote Pump'!Q13) -> Remote Pump | B478: =IF('Remote Pump'!$Q13="","",'Remote Pump'!R13) -> Gate 1 | C478: =IF('Remote Pump'!$Q13="","",'Remote Pump'!S13) -> Technical Feasibility | D478: =IF('Remote Pump'!$Q13="","",'Remote Pump'!T13) -> Command success rate | E478: =IF('Remote Pump'!$Q13="","",'Remote Pump'!U13) -> Success of issued remote command. | F478: =IF('Remote Pump'!$Q13="","",'Remote Pump'!V13) -> range | G478: =IF('Remote Pump'!$Q13="","",'Remote Pump'!W13) -> high | H478: =IF('Remote Pump'!$Q13="","",'Remote Pump'!X13) -> Yes | ... S478: =IF('Remote Pump'!$Q13="","",'Remote Pump'!AI13) -> 0
A479: =IF('Remote Pump'!$Q14="","",'Remote Pump'!Q14) -> Remote Pump | B479: =IF('Remote Pump'!$Q14="","",'Remote Pump'!R14) -> Gate 1 | C479: =IF('Remote Pump'!$Q14="","",'Remote Pump'!S14) -> Technical Feasibility | D479: =IF('Remote Pump'!$Q14="","",'Remote Pump'!T14) -> Telemetry completeness | E479: =IF('Remote Pump'!$Q14="","",'Remote Pump'!U14) -> Availability of remote feedback and audit data. | F479: =IF('Remote Pump'!$Q14="","",'Remote Pump'!V14) -> range | G479: =IF('Remote Pump'!$Q14="","",'Remote Pump'!W14) -> high | H479: =IF('Remote Pump'!$Q14="","",'Remote Pump'!X14) -> No | ... S479: =IF('Remote Pump'!$Q14="","",'Remote Pump'!AI14) -> 0
A480: =IF('Remote Pump'!$Q15="","",'Remote Pump'!Q15) -> Remote Pump | B480: =IF('Remote Pump'!$Q15="","",'Remote Pump'!R15) -> Gate 1 | C480: =IF('Remote Pump'!$Q15="","",'Remote Pump'!S15) -> Technical Feasibility | D480: =IF('Remote Pump'!$Q15="","",'Remote Pump'!T15) -> Communication uptime | E480: =IF('Remote Pump'!$Q15="","",'Remote Pump'!U15) -> Reliability of communication channel. | F480: =IF('Remote Pump'!$Q15="","",'Remote Pump'!V15) -> range | G480: =IF('Remote Pump'!$Q15="","",'Remote Pump'!W15) -> high | H480: =IF('Remote Pump'!$Q15="","",'Remote Pump'!X15) -> Yes | ... S480: =IF('Remote Pump'!$Q15="","",'Remote Pump'!AI15) -> 0
A481: =IF('Remote Pump'!$Q16="","",'Remote Pump'!Q16) -> Remote Pump | B481: =IF('Remote Pump'!$Q16="","",'Remote Pump'!R16) -> Gate 2 | C481: =IF('Remote Pump'!$Q16="","",'Remote Pump'!S16) -> Performance / Effectiveness | D481: =IF('Remote Pump'!$Q16="","",'Remote Pump'!T16) -> Remote availability | E481: =IF('Remote Pump'!$Q16="","",'Remote Pump'!U16) -> Ability to operate remotely when needed. | F481: =IF('Remote Pump'!$Q16="","",'Remote Pump'!V16) -> range | G481: =IF('Remote Pump'!$Q16="","",'Remote Pump'!W16) -> high | H481: =IF('Remote Pump'!$Q16="","",'Remote Pump'!X16) -> No | ... S481: =IF('Remote Pump'!$Q16="","",'Remote Pump'!AI16) -> 0
A482: =IF('Remote Pump'!$Q17="","",'Remote Pump'!Q17) -> Remote Pump | B482: =IF('Remote Pump'!$Q17="","",'Remote Pump'!R17) -> Gate 2 | C482: =IF('Remote Pump'!$Q17="","",'Remote Pump'!S17) -> Performance / Effectiveness | D482: =IF('Remote Pump'!$Q17="","",'Remote Pump'!T17) -> Response latency | E482: =IF('Remote Pump'!$Q17="","",'Remote Pump'!U17) -> Control response time under operating condition. | F482: =IF('Remote Pump'!$Q17="","",'Remote Pump'!V17) -> range | G482: =IF('Remote Pump'!$Q17="","",'Remote Pump'!W17) -> low | H482: =IF('Remote Pump'!$Q17="","",'Remote Pump'!X17) -> No | ... S482: =IF('Remote Pump'!$Q17="","",'Remote Pump'!AI17) -> 0
A483: =IF('Remote Pump'!$Q18="","",'Remote Pump'!Q18) -> Remote Pump | B483: =IF('Remote Pump'!$Q18="","",'Remote Pump'!R18) -> Gate 2 | C483: =IF('Remote Pump'!$Q18="","",'Remote Pump'!S18) -> Performance / Effectiveness | D483: =IF('Remote Pump'!$Q18="","",'Remote Pump'!T18) -> Downtime reduction | E483: =IF('Remote Pump'!$Q18="","",'Remote Pump'!U18) -> Reduction in event-driven downtime. | F483: =IF('Remote Pump'!$Q18="","",'Remote Pump'!V18) -> range | G483: =IF('Remote Pump'!$Q18="","",'Remote Pump'!W18) -> high | H483: =IF('Remote Pump'!$Q18="","",'Remote Pump'!X18) -> No | ... S483: =IF('Remote Pump'!$Q18="","",'Remote Pump'!AI18) -> 0
A484: =IF('Remote Pump'!$Q19="","",'Remote Pump'!Q19) -> Remote Pump | B484: =IF('Remote Pump'!$Q19="","",'Remote Pump'!R19) -> Gate 3 | C484: =IF('Remote Pump'!$Q19="","",'Remote Pump'!S19) -> Safety Case & Procedure | D484: =IF('Remote Pump'!$Q19="","",'Remote Pump'!T19) -> Safety interlock | E484: =IF('Remote Pump'!$Q19="","",'Remote Pump'!U19) -> Integrity of remote command permissive chain. | F484: =IF('Remote Pump'!$Q19="","",'Remote Pump'!V19) -> select | G484: =IF('Remote Pump'!$Q19="","",'Remote Pump'!W19) -> 0 | H484: =IF('Remote Pump'!$Q19="","",'Remote Pump'!X19) -> Yes | ... S484: =IF('Remote Pump'!$Q19="","",'Remote Pump'!AI19) -> 0
A485: =IF('Remote Pump'!$Q20="","",'Remote Pump'!Q20) -> Remote Pump | B485: =IF('Remote Pump'!$Q20="","",'Remote Pump'!R20) -> Gate 3 | C485: =IF('Remote Pump'!$Q20="","",'Remote Pump'!S20) -> Safety Case & Procedure | D485: =IF('Remote Pump'!$Q20="","",'Remote Pump'!T20) -> Loss-of-signal fail-safe | E485: =IF('Remote Pump'!$Q20="","",'Remote Pump'!U20) -> Safe fallback when signal is lost. | F485: =IF('Remote Pump'!$Q20="","",'Remote Pump'!V20) -> select | G485: =IF('Remote Pump'!$Q20="","",'Remote Pump'!W20) -> 0 | H485: =IF('Remote Pump'!$Q20="","",'Remote Pump'!X20) -> Yes | ... S485: =IF('Remote Pump'!$Q20="","",'Remote Pump'!AI20) -> 0
A486: =IF('Remote Pump'!$Q21="","",'Remote Pump'!Q21) -> Remote Pump | B486: =IF('Remote Pump'!$Q21="","",'Remote Pump'!R21) -> Gate 3 | C486: =IF('Remote Pump'!$Q21="","",'Remote Pump'!S21) -> Safety Case & Procedure | D486: =IF('Remote Pump'!$Q21="","",'Remote Pump'!T21) -> Isolation procedure | E486: =IF('Remote Pump'!$Q21="","",'Remote Pump'!U21) -> LOTO and local takeover procedure readiness. | F486: =IF('Remote Pump'!$Q21="","",'Remote Pump'!V21) -> select | G486: =IF('Remote Pump'!$Q21="","",'Remote Pump'!W21) -> 0 | H486: =IF('Remote Pump'!$Q21="","",'Remote Pump'!X21) -> Yes | ... S486: =IF('Remote Pump'!$Q21="","",'Remote Pump'!AI21) -> 0
A487: =IF('Remote Pump'!$Q22="","",'Remote Pump'!Q22) -> Remote Pump | B487: =IF('Remote Pump'!$Q22="","",'Remote Pump'!R22) -> Gate 4 | C487: =IF('Remote Pump'!$Q22="","",'Remote Pump'!S22) -> Business / Assurance | D487: =IF('Remote Pump'!$Q22="","",'Remote Pump'!T22) -> Travel exposure reduction | E487: =IF('Remote Pump'!$Q22="","",'Remote Pump'!U22) -> Reduction in personnel movement to pump area. | F487: =IF('Remote Pump'!$Q22="","",'Remote Pump'!V22) -> range | G487: =IF('Remote Pump'!$Q22="","",'Remote Pump'!W22) -> high | H487: =IF('Remote Pump'!$Q22="","",'Remote Pump'!X22) -> No | ... S487: =IF('Remote Pump'!$Q22="","",'Remote Pump'!AI22) -> 0
A488: =IF('Remote Pump'!$Q23="","",'Remote Pump'!Q23) -> Remote Pump | B488: =IF('Remote Pump'!$Q23="","",'Remote Pump'!R23) -> Gate 4 | C488: =IF('Remote Pump'!$Q23="","",'Remote Pump'!S23) -> Business / Assurance | D488: =IF('Remote Pump'!$Q23="","",'Remote Pump'!T23) -> Delay prevention | E488: =IF('Remote Pump'!$Q23="","",'Remote Pump'!U23) -> Avoided delay from remote intervention. | F488: =IF('Remote Pump'!$Q23="","",'Remote Pump'!V23) -> range | G488: =IF('Remote Pump'!$Q23="","",'Remote Pump'!W23) -> high | H488: =IF('Remote Pump'!$Q23="","",'Remote Pump'!X23) -> No | ... S488: =IF('Remote Pump'!$Q23="","",'Remote Pump'!AI23) -> 0
A489: =IF('Remote Pump'!$Q24="","",'Remote Pump'!Q24) -> Remote Pump | B489: =IF('Remote Pump'!$Q24="","",'Remote Pump'!R24) -> Gate 4 | C489: =IF('Remote Pump'!$Q24="","",'Remote Pump'!S24) -> Business / Assurance | D489: =IF('Remote Pump'!$Q24="","",'Remote Pump'!T24) -> Economic case | E489: =IF('Remote Pump'!$Q24="","",'Remote Pump'!U24) -> Scale case from avoided loss and assurance benefit. | F489: =IF('Remote Pump'!$Q24="","",'Remote Pump'!V24) -> select | G489: =IF('Remote Pump'!$Q24="","",'Remote Pump'!W24) -> 0 | H489: =IF('Remote Pump'!$Q24="","",'Remote Pump'!X24) -> No | ... S489: =IF('Remote Pump'!$Q24="","",'Remote Pump'!AI24) -> 0
... A715: =IF('Remote Pump'!$Q250="","",'Remote Pump'!Q250) -> Remote Pump | B715: =IF('Remote Pump'!$Q250="","",'Remote Pump'!R250) -> 0 | C715: =IF('Remote Pump'!$Q250="","",'Remote Pump'!S250) -> 0 | D715: =IF('Remote Pump'!$Q250="","",'Remote Pump'!T250) -> 0 | E715: =IF('Remote Pump'!$Q250="","",'Remote Pump'!U250) -> 0 | F715: =IF('Remote Pump'!$Q250="","",'Remote Pump'!V250) -> 0 | G715: =IF('Remote Pump'!$Q250="","",'Remote Pump'!W250) -> 0 | H715: =IF('Remote Pump'!$Q250="","",'Remote Pump'!X250) -> 0 | ... S715: =IF('Remote Pump'!$Q250="","",'Remote Pump'!AI250) -> 0
A716: =IF('Hauling Fleet Management'!$Q13="","",'Hauling Fleet Management'!Q13) -> Hauling Fleet Management | B716: =IF('Hauling Fleet Management'!$Q13="","",'Hauling Fleet Management'!R13) -> Gate 1 | C716: =IF('Hauling Fleet Management'!$Q13="","",'Hauling Fleet Management'!S13) -> Technical Feasibility | D716: =IF('Hauling Fleet Management'!$Q13="","",'Hauling Fleet Management'!T13) -> Data ingestion | E716: =IF('Hauling Fleet Management'!$Q13="","",'Hauling Fleet Management'!U13) -> Consistency of live fleet data ingestion. | F716: =IF('Hauling Fleet Management'!$Q13="","",'Hauling Fleet Management'!V13) -> range | G716: =IF('Hauling Fleet Management'!$Q13="","",'Hauling Fleet Management'!W13) -> high | H716: =IF('Hauling Fleet Management'!$Q13="","",'Hauling Fleet Management'!X13) -> No | ... S716: =IF('Hauling Fleet Management'!$Q13="","",'Hauling Fleet Management'!AI13) -> 0
A717: =IF('Hauling Fleet Management'!$Q14="","",'Hauling Fleet Management'!Q14) -> Hauling Fleet Management | B717: =IF('Hauling Fleet Management'!$Q14="","",'Hauling Fleet Management'!R14) -> Gate 1 | C717: =IF('Hauling Fleet Management'!$Q14="","",'Hauling Fleet Management'!S14) -> Technical Feasibility | D717: =IF('Hauling Fleet Management'!$Q14="","",'Hauling Fleet Management'!T14) -> Dashboard uptime | E717: =IF('Hauling Fleet Management'!$Q14="","",'Hauling Fleet Management'!U14) -> Operational dashboard availability. | F717: =IF('Hauling Fleet Management'!$Q14="","",'Hauling Fleet Management'!V14) -> range | G717: =IF('Hauling Fleet Management'!$Q14="","",'Hauling Fleet Management'!W14) -> high | H717: =IF('Hauling Fleet Management'!$Q14="","",'Hauling Fleet Management'!X14) -> Yes | ... S717: =IF('Hauling Fleet Management'!$Q14="","",'Hauling Fleet Management'!AI14) -> 0
A718: =IF('Hauling Fleet Management'!$Q15="","",'Hauling Fleet Management'!Q15) -> Hauling Fleet Management | B718: =IF('Hauling Fleet Management'!$Q15="","",'Hauling Fleet Management'!R15) -> Gate 1 | C718: =IF('Hauling Fleet Management'!$Q15="","",'Hauling Fleet Management'!S15) -> Technical Feasibility | D718: =IF('Hauling Fleet Management'!$Q15="","",'Hauling Fleet Management'!T15) -> Refresh cycle | E718: =IF('Hauling Fleet Management'!$Q15="","",'Hauling Fleet Management'!U15) -> Minutes needed for usable data refresh. | F718: =IF('Hauling Fleet Management'!$Q15="","",'Hauling Fleet Management'!V15) -> range | G718: =IF('Hauling Fleet Management'!$Q15="","",'Hauling Fleet Management'!W15) -> low | H718: =IF('Hauling Fleet Management'!$Q15="","",'Hauling Fleet Management'!X15) -> No | ... S718: =IF('Hauling Fleet Management'!$Q15="","",'Hauling Fleet Management'!AI15) -> 0
A719: =IF('Hauling Fleet Management'!$Q16="","",'Hauling Fleet Management'!Q16) -> Hauling Fleet Management | B719: =IF('Hauling Fleet Management'!$Q16="","",'Hauling Fleet Management'!R16) -> Gate 2 | C719: =IF('Hauling Fleet Management'!$Q16="","",'Hauling Fleet Management'!S16) -> Performance / Effectiveness | D719: =IF('Hauling Fleet Management'!$Q16="","",'Hauling Fleet Management'!T16) -> Queue time reduction | E719: =IF('Hauling Fleet Management'!$Q16="","",'Hauling Fleet Management'!U16) -> Reduction in waiting queue for loading/unloading. | F719: =IF('Hauling Fleet Management'!$Q16="","",'Hauling Fleet Management'!V16) -> range | G719: =IF('Hauling Fleet Management'!$Q16="","",'Hauling Fleet Management'!W16) -> high | H719: =IF('Hauling Fleet Management'!$Q16="","",'Hauling Fleet Management'!X16) -> No | ... S719: =IF('Hauling Fleet Management'!$Q16="","",'Hauling Fleet Management'!AI16) -> 0
A720: =IF('Hauling Fleet Management'!$Q17="","",'Hauling Fleet Management'!Q17) -> Hauling Fleet Management | B720: =IF('Hauling Fleet Management'!$Q17="","",'Hauling Fleet Management'!R17) -> Gate 2 | C720: =IF('Hauling Fleet Management'!$Q17="","",'Hauling Fleet Management'!S17) -> Performance / Effectiveness | D720: =IF('Hauling Fleet Management'!$Q17="","",'Hauling Fleet Management'!T17) -> Idle reduction | E720: =IF('Hauling Fleet Management'!$Q17="","",'Hauling Fleet Management'!U17) -> Reduction in idle or non-productive unit time. | F720: =IF('Hauling Fleet Management'!$Q17="","",'Hauling Fleet Management'!V17) -> range | G720: =IF('Hauling Fleet Management'!$Q17="","",'Hauling Fleet Management'!W17) -> high | H720: =IF('Hauling Fleet Management'!$Q17="","",'Hauling Fleet Management'!X17) -> No | ... S720: =IF('Hauling Fleet Management'!$Q17="","",'Hauling Fleet Management'!AI17) -> 0
A721: =IF('Hauling Fleet Management'!$Q18="","",'Hauling Fleet Management'!Q18) -> Hauling Fleet Management | B721: =IF('Hauling Fleet Management'!$Q18="","",'Hauling Fleet Management'!R18) -> Gate 2 | C721: =IF('Hauling Fleet Management'!$Q18="","",'Hauling Fleet Management'!S18) -> Performance / Effectiveness | D721: =IF('Hauling Fleet Management'!$Q18="","",'Hauling Fleet Management'!T18) -> User adoption | E721: =IF('Hauling Fleet Management'!$Q18="","",'Hauling Fleet Management'!U18) -> Dispatcher and supervisor usage level. | F721: =IF('Hauling Fleet Management'!$Q18="","",'Hauling Fleet Management'!V18) -> range | G721: =IF('Hauling Fleet Management'!$Q18="","",'Hauling Fleet Management'!W18) -> high | H721: =IF('Hauling Fleet Management'!$Q18="","",'Hauling Fleet Management'!X18) -> No | ... S721: =IF('Hauling Fleet Management'!$Q18="","",'Hauling Fleet Management'!AI18) -> 0
A722: =IF('Hauling Fleet Management'!$Q19="","",'Hauling Fleet Management'!Q19) -> Hauling Fleet Management | B722: =IF('Hauling Fleet Management'!$Q19="","",'Hauling Fleet Management'!R19) -> Gate 3 | C722: =IF('Hauling Fleet Management'!$Q19="","",'Hauling Fleet Management'!S19) -> Safety Case & Procedure | D722: =IF('Hauling Fleet Management'!$Q19="","",'Hauling Fleet Management'!T19) -> Safety conflict check | E722: =IF('Hauling Fleet Management'!$Q19="","",'Hauling Fleet Management'!U19) -> No contradiction with road-rule protections. | F722: =IF('Hauling Fleet Management'!$Q19="","",'Hauling Fleet Management'!V19) -> select | G722: =IF('Hauling Fleet Management'!$Q19="","",'Hauling Fleet Management'!W19) -> 0 | H722: =IF('Hauling Fleet Management'!$Q19="","",'Hauling Fleet Management'!X19) -> Yes | ... S722: =IF('Hauling Fleet Management'!$Q19="","",'Hauling Fleet Management'!AI19) -> 0
A723: =IF('Hauling Fleet Management'!$Q20="","",'Hauling Fleet Management'!Q20) -> Hauling Fleet Management | B723: =IF('Hauling Fleet Management'!$Q20="","",'Hauling Fleet Management'!R20) -> Gate 3 | C723: =IF('Hauling Fleet Management'!$Q20="","",'Hauling Fleet Management'!S20) -> Safety Case & Procedure | D723: =IF('Hauling Fleet Management'!$Q20="","",'Hauling Fleet Management'!T20) -> Audit trail | E723: =IF('Hauling Fleet Management'!$Q20="","",'Hauling Fleet Management'!U20) -> Decision traceability and reviewability. | F723: =IF('Hauling Fleet Management'!$Q20="","",'Hauling Fleet Management'!V20) -> select | G723: =IF('Hauling Fleet Management'!$Q20="","",'Hauling Fleet Management'!W20) -> 0 | H723: =IF('Hauling Fleet Management'!$Q20="","",'Hauling Fleet Management'!X20) -> No | ... S723: =IF('Hauling Fleet Management'!$Q20="","",'Hauling Fleet Management'!AI20) -> 0
A724: =IF('Hauling Fleet Management'!$Q21="","",'Hauling Fleet Management'!Q21) -> Hauling Fleet Management | B724: =IF('Hauling Fleet Management'!$Q21="","",'Hauling Fleet Management'!R21) -> Gate 3 | C724: =IF('Hauling Fleet Management'!$Q21="","",'Hauling Fleet Management'!S21) -> Safety Case & Procedure | D724: =IF('Hauling Fleet Management'!$Q21="","",'Hauling Fleet Management'!T21) -> Escalation path | E724: =IF('Hauling Fleet Management'!$Q21="","",'Hauling Fleet Management'!U21) -> Manual override and escalation remain available. | F724: =IF('Hauling Fleet Management'!$Q21="","",'Hauling Fleet Management'!V21) -> select | G724: =IF('Hauling Fleet Management'!$Q21="","",'Hauling Fleet Management'!W21) -> 0 | H724: =IF('Hauling Fleet Management'!$Q21="","",'Hauling Fleet Management'!X21) -> Yes | ... S724: =IF('Hauling Fleet Management'!$Q21="","",'Hauling Fleet Management'!AI21) -> 0
A725: =IF('Hauling Fleet Management'!$Q22="","",'Hauling Fleet Management'!Q22) -> Hauling Fleet Management | B725: =IF('Hauling Fleet Management'!$Q22="","",'Hauling Fleet Management'!R22) -> Gate 4 | C725: =IF('Hauling Fleet Management'!$Q22="","",'Hauling Fleet Management'!S22) -> Business / Assurance | D725: =IF('Hauling Fleet Management'!$Q22="","",'Hauling Fleet Management'!T22) -> Fuel benefit | E725: =IF('Hauling Fleet Management'!$Q22="","",'Hauling Fleet Management'!U22) -> Improvement in fuel-related operating value. | F725: =IF('Hauling Fleet Management'!$Q22="","",'Hauling Fleet Management'!V22) -> range | G725: =IF('Hauling Fleet Management'!$Q22="","",'Hauling Fleet Management'!W22) -> high | H725: =IF('Hauling Fleet Management'!$Q22="","",'Hauling Fleet Management'!X22) -> No | ... S725: =IF('Hauling Fleet Management'!$Q22="","",'Hauling Fleet Management'!AI22) -> 0
A726: =IF('Hauling Fleet Management'!$Q23="","",'Hauling Fleet Management'!Q23) -> Hauling Fleet Management | B726: =IF('Hauling Fleet Management'!$Q23="","",'Hauling Fleet Management'!R23) -> Gate 4 | C726: =IF('Hauling Fleet Management'!$Q23="","",'Hauling Fleet Management'!S23) -> Business / Assurance | D726: =IF('Hauling Fleet Management'!$Q23="","",'Hauling Fleet Management'!T23) -> Utilization uplift | E726: =IF('Hauling Fleet Management'!$Q23="","",'Hauling Fleet Management'!U23) -> Increase in productive fleet use. | F726: =IF('Hauling Fleet Management'!$Q23="","",'Hauling Fleet Management'!V23) -> range | G726: =IF('Hauling Fleet Management'!$Q23="","",'Hauling Fleet Management'!W23) -> high | H726: =IF('Hauling Fleet Management'!$Q23="","",'Hauling Fleet Management'!X23) -> No | ... S726: =IF('Hauling Fleet Management'!$Q23="","",'Hauling Fleet Management'!AI23) -> 0
A727: =IF('Hauling Fleet Management'!$Q24="","",'Hauling Fleet Management'!Q24) -> Hauling Fleet Management | B727: =IF('Hauling Fleet Management'!$Q24="","",'Hauling Fleet Management'!R24) -> Gate 4 | C727: =IF('Hauling Fleet Management'!$Q24="","",'Hauling Fleet Management'!S24) -> Business / Assurance | D727: =IF('Hauling Fleet Management'!$Q24="","",'Hauling Fleet Management'!T24) -> Scale economics | E727: =IF('Hauling Fleet Management'!$Q24="","",'Hauling Fleet Management'!U24) -> Strength of economic case for wider deployment. | F727: =IF('Hauling Fleet Management'!$Q24="","",'Hauling Fleet Management'!V24) -> select | G727: =IF('Hauling Fleet Management'!$Q24="","",'Hauling Fleet Management'!W24) -> 0 | H727: =IF('Hauling Fleet Management'!$Q24="","",'Hauling Fleet Management'!X24) -> No | ... S727: =IF('Hauling Fleet Management'!$Q24="","",'Hauling Fleet Management'!AI24) -> 0
... A953: =IF('Hauling Fleet Management'!$Q250="","",'Hauling Fleet Management'!Q250) -> Hauling Fleet Management | B953: =IF('Hauling Fleet Management'!$Q250="","",'Hauling Fleet Management'!R250) -> 0 | C953: =IF('Hauling Fleet Management'!$Q250="","",'Hauling Fleet Management'!S250) -> 0 | D953: =IF('Hauling Fleet Management'!$Q250="","",'Hauling Fleet Management'!T250) -> 0 | E953: =IF('Hauling Fleet Management'!$Q250="","",'Hauling Fleet Management'!U250) -> 0 | F953: =IF('Hauling Fleet Management'!$Q250="","",'Hauling Fleet Management'!V250) -> 0 | G953: =IF('Hauling Fleet Management'!$Q250="","",'Hauling Fleet Management'!W250) -> 0 | H953: =IF('Hauling Fleet Management'!$Q250="","",'Hauling Fleet Management'!X250) -> 0 | ... S953: =IF('Hauling Fleet Management'!$Q250="","",'Hauling Fleet Management'!AI250) -> 0
A954: =IF('Mining Eyes Analytics'!$Q13="","",'Mining Eyes Analytics'!Q13) -> Mining Eyes Analytics | B954: =IF('Mining Eyes Analytics'!$Q13="","",'Mining Eyes Analytics'!R13) -> Gate 1 | C954: =IF('Mining Eyes Analytics'!$Q13="","",'Mining Eyes Analytics'!S13) -> Technical Feasibility | D954: =IF('Mining Eyes Analytics'!$Q13="","",'Mining Eyes Analytics'!T13) -> Camera uptime | E954: =IF('Mining Eyes Analytics'!$Q13="","",'Mining Eyes Analytics'!U13) -> Video source availability for analytics. | F954: =IF('Mining Eyes Analytics'!$Q13="","",'Mining Eyes Analytics'!V13) -> range | G954: =IF('Mining Eyes Analytics'!$Q13="","",'Mining Eyes Analytics'!W13) -> high | H954: =IF('Mining Eyes Analytics'!$Q13="","",'Mining Eyes Analytics'!X13) -> No | ... S954: =IF('Mining Eyes Analytics'!$Q13="","",'Mining Eyes Analytics'!AI13) -> 0
A955: =IF('Mining Eyes Analytics'!$Q14="","",'Mining Eyes Analytics'!Q14) -> Mining Eyes Analytics | B955: =IF('Mining Eyes Analytics'!$Q14="","",'Mining Eyes Analytics'!R14) -> Gate 1 | C955: =IF('Mining Eyes Analytics'!$Q14="","",'Mining Eyes Analytics'!S14) -> Technical Feasibility | D955: =IF('Mining Eyes Analytics'!$Q14="","",'Mining Eyes Analytics'!T14) -> Inference latency | E955: =IF('Mining Eyes Analytics'!$Q14="","",'Mining Eyes Analytics'!U14) -> Speed from event to generated alert. | F955: =IF('Mining Eyes Analytics'!$Q14="","",'Mining Eyes Analytics'!V14) -> range | G955: =IF('Mining Eyes Analytics'!$Q14="","",'Mining Eyes Analytics'!W14) -> low | H955: =IF('Mining Eyes Analytics'!$Q14="","",'Mining Eyes Analytics'!X14) -> No | ... S955: =IF('Mining Eyes Analytics'!$Q14="","",'Mining Eyes Analytics'!AI14) -> 0
A956: =IF('Mining Eyes Analytics'!$Q15="","",'Mining Eyes Analytics'!Q15) -> Mining Eyes Analytics | B956: =IF('Mining Eyes Analytics'!$Q15="","",'Mining Eyes Analytics'!R15) -> Gate 1 | C956: =IF('Mining Eyes Analytics'!$Q15="","",'Mining Eyes Analytics'!S15) -> Technical Feasibility | D956: =IF('Mining Eyes Analytics'!$Q15="","",'Mining Eyes Analytics'!T15) -> Coverage stability | E956: =IF('Mining Eyes Analytics'!$Q15="","",'Mining Eyes Analytics'!U15) -> Consistency of effective area coverage. | F956: =IF('Mining Eyes Analytics'!$Q15="","",'Mining Eyes Analytics'!V15) -> range | G956: =IF('Mining Eyes Analytics'!$Q15="","",'Mining Eyes Analytics'!W15) -> high | H956: =IF('Mining Eyes Analytics'!$Q15="","",'Mining Eyes Analytics'!X15) -> Yes | ... S956: =IF('Mining Eyes Analytics'!$Q15="","",'Mining Eyes Analytics'!AI15) -> 0
A957: =IF('Mining Eyes Analytics'!$Q16="","",'Mining Eyes Analytics'!Q16) -> Mining Eyes Analytics | B957: =IF('Mining Eyes Analytics'!$Q16="","",'Mining Eyes Analytics'!R16) -> Gate 2 | C957: =IF('Mining Eyes Analytics'!$Q16="","",'Mining Eyes Analytics'!S16) -> Performance / Effectiveness | D957: =IF('Mining Eyes Analytics'!$Q16="","",'Mining Eyes Analytics'!T16) -> Precision | E957: =IF('Mining Eyes Analytics'!$Q16="","",'Mining Eyes Analytics'!U16) -> Alert correctness rate. | F957: =IF('Mining Eyes Analytics'!$Q16="","",'Mining Eyes Analytics'!V16) -> range | G957: =IF('Mining Eyes Analytics'!$Q16="","",'Mining Eyes Analytics'!W16) -> high | H957: =IF('Mining Eyes Analytics'!$Q16="","",'Mining Eyes Analytics'!X16) -> No | ... S957: =IF('Mining Eyes Analytics'!$Q16="","",'Mining Eyes Analytics'!AI16) -> 0
A958: =IF('Mining Eyes Analytics'!$Q17="","",'Mining Eyes Analytics'!Q17) -> Mining Eyes Analytics | B958: =IF('Mining Eyes Analytics'!$Q17="","",'Mining Eyes Analytics'!R17) -> Gate 2 | C958: =IF('Mining Eyes Analytics'!$Q17="","",'Mining Eyes Analytics'!S17) -> Performance / Effectiveness | D958: =IF('Mining Eyes Analytics'!$Q17="","",'Mining Eyes Analytics'!T17) -> Recall | E958: =IF('Mining Eyes Analytics'!$Q17="","",'Mining Eyes Analytics'!U17) -> Ability to capture true events. | F958: =IF('Mining Eyes Analytics'!$Q17="","",'Mining Eyes Analytics'!V17) -> range | G958: =IF('Mining Eyes Analytics'!$Q17="","",'Mining Eyes Analytics'!W17) -> high | H958: =IF('Mining Eyes Analytics'!$Q17="","",'Mining Eyes Analytics'!X17) -> No | ... S958: =IF('Mining Eyes Analytics'!$Q17="","",'Mining Eyes Analytics'!AI17) -> 0
A959: =IF('Mining Eyes Analytics'!$Q18="","",'Mining Eyes Analytics'!Q18) -> Mining Eyes Analytics | B959: =IF('Mining Eyes Analytics'!$Q18="","",'Mining Eyes Analytics'!R18) -> Gate 2 | C959: =IF('Mining Eyes Analytics'!$Q18="","",'Mining Eyes Analytics'!S18) -> Performance / Effectiveness | D959: =IF('Mining Eyes Analytics'!$Q18="","",'Mining Eyes Analytics'!T18) -> False positive rate | E959: =IF('Mining Eyes Analytics'!$Q18="","",'Mining Eyes Analytics'!U18) -> Lower rate reduces alert fatigue. | F959: =IF('Mining Eyes Analytics'!$Q18="","",'Mining Eyes Analytics'!V18) -> range | G959: =IF('Mining Eyes Analytics'!$Q18="","",'Mining Eyes Analytics'!W18) -> low | H959: =IF('Mining Eyes Analytics'!$Q18="","",'Mining Eyes Analytics'!X18) -> No | ... S959: =IF('Mining Eyes Analytics'!$Q18="","",'Mining Eyes Analytics'!AI18) -> 0
A960: =IF('Mining Eyes Analytics'!$Q19="","",'Mining Eyes Analytics'!Q19) -> Mining Eyes Analytics | B960: =IF('Mining Eyes Analytics'!$Q19="","",'Mining Eyes Analytics'!R19) -> Gate 3 | C960: =IF('Mining Eyes Analytics'!$Q19="","",'Mining Eyes Analytics'!S19) -> Safety Case & Procedure | D960: =IF('Mining Eyes Analytics'!$Q19="","",'Mining Eyes Analytics'!T19) -> Escalation SOP | E960: =IF('Mining Eyes Analytics'!$Q19="","",'Mining Eyes Analytics'!U19) -> Owner and response flow for incoming alerts. | F960: =IF('Mining Eyes Analytics'!$Q19="","",'Mining Eyes Analytics'!V19) -> select | G960: =IF('Mining Eyes Analytics'!$Q19="","",'Mining Eyes Analytics'!W19) -> 0 | H960: =IF('Mining Eyes Analytics'!$Q19="","",'Mining Eyes Analytics'!X19) -> Yes | ... S960: =IF('Mining Eyes Analytics'!$Q19="","",'Mining Eyes Analytics'!AI19) -> 0
A961: =IF('Mining Eyes Analytics'!$Q20="","",'Mining Eyes Analytics'!Q20) -> Mining Eyes Analytics | B961: =IF('Mining Eyes Analytics'!$Q20="","",'Mining Eyes Analytics'!R20) -> Gate 3 | C961: =IF('Mining Eyes Analytics'!$Q20="","",'Mining Eyes Analytics'!S20) -> Safety Case & Procedure | D961: =IF('Mining Eyes Analytics'!$Q20="","",'Mining Eyes Analytics'!T20) -> Audit trail | E961: =IF('Mining Eyes Analytics'!$Q20="","",'Mining Eyes Analytics'!U20) -> Evidence trace and alert history reviewability. | F961: =IF('Mining Eyes Analytics'!$Q20="","",'Mining Eyes Analytics'!V20) -> select | G961: =IF('Mining Eyes Analytics'!$Q20="","",'Mining Eyes Analytics'!W20) -> 0 | H961: =IF('Mining Eyes Analytics'!$Q20="","",'Mining Eyes Analytics'!X20) -> Yes | ... S961: =IF('Mining Eyes Analytics'!$Q20="","",'Mining Eyes Analytics'!AI20) -> 0
A962: =IF('Mining Eyes Analytics'!$Q21="","",'Mining Eyes Analytics'!Q21) -> Mining Eyes Analytics | B962: =IF('Mining Eyes Analytics'!$Q21="","",'Mining Eyes Analytics'!R21) -> Gate 3 | C962: =IF('Mining Eyes Analytics'!$Q21="","",'Mining Eyes Analytics'!S21) -> Safety Case & Procedure | D962: =IF('Mining Eyes Analytics'!$Q21="","",'Mining Eyes Analytics'!T21) -> Closure workflow | E962: =IF('Mining Eyes Analytics'!$Q21="","",'Mining Eyes Analytics'!U21) -> Quality of action closure discipline. | F962: =IF('Mining Eyes Analytics'!$Q21="","",'Mining Eyes Analytics'!V21) -> range | G962: =IF('Mining Eyes Analytics'!$Q21="","",'Mining Eyes Analytics'!W21) -> high | H962: =IF('Mining Eyes Analytics'!$Q21="","",'Mining Eyes Analytics'!X21) -> No | ... S962: =IF('Mining Eyes Analytics'!$Q21="","",'Mining Eyes Analytics'!AI21) -> 0
A963: =IF('Mining Eyes Analytics'!$Q22="","",'Mining Eyes Analytics'!Q22) -> Mining Eyes Analytics | B963: =IF('Mining Eyes Analytics'!$Q22="","",'Mining Eyes Analytics'!R22) -> Gate 4 | C963: =IF('Mining Eyes Analytics'!$Q22="","",'Mining Eyes Analytics'!S22) -> Business / Assurance | D963: =IF('Mining Eyes Analytics'!$Q22="","",'Mining Eyes Analytics'!T22) -> Coverage uplift | E963: =IF('Mining Eyes Analytics'!$Q22="","",'Mining Eyes Analytics'!U22) -> Increase in monitored area or observation capability. | F963: =IF('Mining Eyes Analytics'!$Q22="","",'Mining Eyes Analytics'!V22) -> range | G963: =IF('Mining Eyes Analytics'!$Q22="","",'Mining Eyes Analytics'!W22) -> high | H963: =IF('Mining Eyes Analytics'!$Q22="","",'Mining Eyes Analytics'!X22) -> No | ... S963: =IF('Mining Eyes Analytics'!$Q22="","",'Mining Eyes Analytics'!AI22) -> 0
A964: =IF('Mining Eyes Analytics'!$Q23="","",'Mining Eyes Analytics'!Q23) -> Mining Eyes Analytics | B964: =IF('Mining Eyes Analytics'!$Q23="","",'Mining Eyes Analytics'!R23) -> Gate 4 | C964: =IF('Mining Eyes Analytics'!$Q23="","",'Mining Eyes Analytics'!S23) -> Business / Assurance | D964: =IF('Mining Eyes Analytics'!$Q23="","",'Mining Eyes Analytics'!T23) -> Manual review reduction | E964: =IF('Mining Eyes Analytics'!$Q23="","",'Mining Eyes Analytics'!U23) -> Potential reduction in CCTV review effort. | F964: =IF('Mining Eyes Analytics'!$Q23="","",'Mining Eyes Analytics'!V23) -> range | G964: =IF('Mining Eyes Analytics'!$Q23="","",'Mining Eyes Analytics'!W23) -> high | H964: =IF('Mining Eyes Analytics'!$Q23="","",'Mining Eyes Analytics'!X23) -> No | ... S964: =IF('Mining Eyes Analytics'!$Q23="","",'Mining Eyes Analytics'!AI23) -> 0
A965: =IF('Mining Eyes Analytics'!$Q24="","",'Mining Eyes Analytics'!Q24) -> Mining Eyes Analytics | B965: =IF('Mining Eyes Analytics'!$Q24="","",'Mining Eyes Analytics'!R24) -> Gate 4 | C965: =IF('Mining Eyes Analytics'!$Q24="","",'Mining Eyes Analytics'!S24) -> Business / Assurance | D965: =IF('Mining Eyes Analytics'!$Q24="","",'Mining Eyes Analytics'!T24) -> Assurance case | E965: =IF('Mining Eyes Analytics'!$Q24="","",'Mining Eyes Analytics'!U24) -> Strength of visibility and auditability justification. | F965: =IF('Mining Eyes Analytics'!$Q24="","",'Mining Eyes Analytics'!V24) -> select | G965: =IF('Mining Eyes Analytics'!$Q24="","",'Mining Eyes Analytics'!W24) -> 0 | H965: =IF('Mining Eyes Analytics'!$Q24="","",'Mining Eyes Analytics'!X24) -> No | ... S965: =IF('Mining Eyes Analytics'!$Q24="","",'Mining Eyes Analytics'!AI24) -> 0
... A1191: =IF('Mining Eyes Analytics'!$Q250="","",'Mining Eyes Analytics'!Q250) -> Mining Eyes Analytics | B1191: =IF('Mining Eyes Analytics'!$Q250="","",'Mining Eyes Analytics'!R250) -> 0 | C1191: =IF('Mining Eyes Analytics'!$Q250="","",'Mining Eyes Analytics'!S250) -> 0 | D1191: =IF('Mining Eyes Analytics'!$Q250="","",'Mining Eyes Analytics'!T250) -> 0 | E1191: =IF('Mining Eyes Analytics'!$Q250="","",'Mining Eyes Analytics'!U250) -> 0 | F1191: =IF('Mining Eyes Analytics'!$Q250="","",'Mining Eyes Analytics'!V250) -> 0 | G1191: =IF('Mining Eyes Analytics'!$Q250="","",'Mining Eyes Analytics'!W250) -> 0 | H1191: =IF('Mining Eyes Analytics'!$Q250="","",'Mining Eyes Analytics'!X250) -> 0 | ... S1191: =IF('Mining Eyes Analytics'!$Q250="","",'Mining Eyes Analytics'!AI250) -> 0
A1192: =IF('Remote Dozer'!$Q13="","",'Remote Dozer'!Q13) -> Remote Dozer | B1192: =IF('Remote Dozer'!$Q13="","",'Remote Dozer'!R13) -> Gate 1 | C1192: =IF('Remote Dozer'!$Q13="","",'Remote Dozer'!S13) -> Technical Feasibility | D1192: =IF('Remote Dozer'!$Q13="","",'Remote Dozer'!T13) -> Network uptime | E1192: =IF('Remote Dozer'!$Q13="","",'Remote Dozer'!U13) -> Availability of network used for remote dozer control. | F1192: =IF('Remote Dozer'!$Q13="","",'Remote Dozer'!V13) -> range | G1192: =IF('Remote Dozer'!$Q13="","",'Remote Dozer'!W13) -> high | H1192: =IF('Remote Dozer'!$Q13="","",'Remote Dozer'!X13) -> Yes | ... S1192: =IF('Remote Dozer'!$Q13="","",'Remote Dozer'!AI13) -> 0
A1193: =IF('Remote Dozer'!$Q14="","",'Remote Dozer'!Q14) -> Remote Dozer | B1193: =IF('Remote Dozer'!$Q14="","",'Remote Dozer'!R14) -> Gate 1 | C1193: =IF('Remote Dozer'!$Q14="","",'Remote Dozer'!S14) -> Technical Feasibility | D1193: =IF('Remote Dozer'!$Q14="","",'Remote Dozer'!T14) -> Control latency | E1193: =IF('Remote Dozer'!$Q14="","",'Remote Dozer'!U14) -> Round-trip command latency during remote operation. | F1193: =IF('Remote Dozer'!$Q14="","",'Remote Dozer'!V14) -> range | G1193: =IF('Remote Dozer'!$Q14="","",'Remote Dozer'!W14) -> low | H1193: =IF('Remote Dozer'!$Q14="","",'Remote Dozer'!X14) -> Yes | ... S1193: =IF('Remote Dozer'!$Q14="","",'Remote Dozer'!AI14) -> 0
A1194: =IF('Remote Dozer'!$Q15="","",'Remote Dozer'!Q15) -> Remote Dozer | B1194: =IF('Remote Dozer'!$Q15="","",'Remote Dozer'!R15) -> Gate 2 | C1194: =IF('Remote Dozer'!$Q15="","",'Remote Dozer'!S15) -> Performance / Effectiveness | D1194: =IF('Remote Dozer'!$Q15="","",'Remote Dozer'!T15) -> Dozing distance reduction | E1194: =IF('Remote Dozer'!$Q15="","",'Remote Dozer'!U15) -> Reduction in average push distance versus conventional operation. | F1194: =IF('Remote Dozer'!$Q15="","",'Remote Dozer'!V15) -> range | G1194: =IF('Remote Dozer'!$Q15="","",'Remote Dozer'!W15) -> high | H1194: =IF('Remote Dozer'!$Q15="","",'Remote Dozer'!X15) -> No | ... S1194: =IF('Remote Dozer'!$Q15="","",'Remote Dozer'!AI15) -> 0
A1195: =IF('Remote Dozer'!$Q16="","",'Remote Dozer'!Q16) -> Remote Dozer | B1195: =IF('Remote Dozer'!$Q16="","",'Remote Dozer'!R16) -> Gate 2 | C1195: =IF('Remote Dozer'!$Q16="","",'Remote Dozer'!S16) -> Performance / Effectiveness | D1195: =IF('Remote Dozer'!$Q16="","",'Remote Dozer'!T16) -> Remote operating availability | E1195: =IF('Remote Dozer'!$Q16="","",'Remote Dozer'!U16) -> Percentage of planned operating time executed in remote mode. | F1195: =IF('Remote Dozer'!$Q16="","",'Remote Dozer'!V16) -> range | G1195: =IF('Remote Dozer'!$Q16="","",'Remote Dozer'!W16) -> high | H1195: =IF('Remote Dozer'!$Q16="","",'Remote Dozer'!X16) -> No | ... S1195: =IF('Remote Dozer'!$Q16="","",'Remote Dozer'!AI16) -> 0
A1196: =IF('Remote Dozer'!$Q17="","",'Remote Dozer'!Q17) -> Remote Dozer | B1196: =IF('Remote Dozer'!$Q17="","",'Remote Dozer'!R17) -> Gate 3 | C1196: =IF('Remote Dozer'!$Q17="","",'Remote Dozer'!S17) -> Safety Case & Procedure | D1196: =IF('Remote Dozer'!$Q17="","",'Remote Dozer'!T17) -> Emergency stop readiness | E1196: =IF('Remote Dozer'!$Q17="","",'Remote Dozer'!U17) -> Remote and local emergency stop function. | F1196: =IF('Remote Dozer'!$Q17="","",'Remote Dozer'!V17) -> select | G1196: =IF('Remote Dozer'!$Q17="","",'Remote Dozer'!W17) -> 0 | H1196: =IF('Remote Dozer'!$Q17="","",'Remote Dozer'!X17) -> Yes | ... S1196: =IF('Remote Dozer'!$Q17="","",'Remote Dozer'!AI17) -> 0
A1197: =IF('Remote Dozer'!$Q18="","",'Remote Dozer'!Q18) -> Remote Dozer | B1197: =IF('Remote Dozer'!$Q18="","",'Remote Dozer'!R18) -> Gate 3 | C1197: =IF('Remote Dozer'!$Q18="","",'Remote Dozer'!S18) -> Safety Case & Procedure | D1197: =IF('Remote Dozer'!$Q18="","",'Remote Dozer'!T18) -> Loss-of-signal fail-safe | E1197: =IF('Remote Dozer'!$Q18="","",'Remote Dozer'!U18) -> Machine response when communication is interrupted. | F1197: =IF('Remote Dozer'!$Q18="","",'Remote Dozer'!V18) -> select | G1197: =IF('Remote Dozer'!$Q18="","",'Remote Dozer'!W18) -> 0 | H1197: =IF('Remote Dozer'!$Q18="","",'Remote Dozer'!X18) -> Yes | ... S1197: =IF('Remote Dozer'!$Q18="","",'Remote Dozer'!AI18) -> 0
A1198: =IF('Remote Dozer'!$Q19="","",'Remote Dozer'!Q19) -> Remote Dozer | B1198: =IF('Remote Dozer'!$Q19="","",'Remote Dozer'!R19) -> Gate 4 | C1198: =IF('Remote Dozer'!$Q19="","",'Remote Dozer'!S19) -> Business / Economical Pass | D1198: =IF('Remote Dozer'!$Q19="","",'Remote Dozer'!T19) -> Net saving / month | E1198: =IF('Remote Dozer'!$Q19="","",'Remote Dozer'!U19) -> Monthly net saving after fuel saving and maintenance impact. | F1198: =IF('Remote Dozer'!$Q19="","",'Remote Dozer'!V19) -> range | G1198: =IF('Remote Dozer'!$Q19="","",'Remote Dozer'!W19) -> high | H1198: =IF('Remote Dozer'!$Q19="","",'Remote Dozer'!X19) -> No | ... S1198: =IF('Remote Dozer'!$Q19="","",'Remote Dozer'!AI19) -> 0
A1199: =IF('Remote Dozer'!$Q20="","",'Remote Dozer'!Q20) -> Remote Dozer | B1199: =IF('Remote Dozer'!$Q20="","",'Remote Dozer'!R20) -> Gate 4 | C1199: =IF('Remote Dozer'!$Q20="","",'Remote Dozer'!S20) -> Business / Economical Pass | D1199: =IF('Remote Dozer'!$Q20="","",'Remote Dozer'!T20) -> Simple payback | E1199: =IF('Remote Dozer'!$Q20="","",'Remote Dozer'!U20) -> Capital recovery period. Lower is better. | F1199: =IF('Remote Dozer'!$Q20="","",'Remote Dozer'!V20) -> range | G1199: =IF('Remote Dozer'!$Q20="","",'Remote Dozer'!W20) -> low | H1199: =IF('Remote Dozer'!$Q20="","",'Remote Dozer'!X20) -> No | ... S1199: =IF('Remote Dozer'!$Q20="","",'Remote Dozer'!AI20) -> 0
A1200: =IF('Remote Dozer'!$Q21="","",'Remote Dozer'!Q21) -> Remote Dozer | B1200: =IF('Remote Dozer'!$Q21="","",'Remote Dozer'!R21) -> Gate 4 | C1200: =IF('Remote Dozer'!$Q21="","",'Remote Dozer'!S21) -> Business / Economical Pass | D1200: =IF('Remote Dozer'!$Q21="","",'Remote Dozer'!T21) -> 5-year ROI | E1200: =IF('Remote Dozer'!$Q21="","",'Remote Dozer'!U21) -> Return on investment over five years after CAPEX recovery. | F1200: =IF('Remote Dozer'!$Q21="","",'Remote Dozer'!V21) -> range | G1200: =IF('Remote Dozer'!$Q21="","",'Remote Dozer'!W21) -> high | H1200: =IF('Remote Dozer'!$Q21="","",'Remote Dozer'!X21) -> No | ... S1200: =IF('Remote Dozer'!$Q21="","",'Remote Dozer'!AI21) -> 0
A1201: =IF('Remote Dozer'!$Q22="","",'Remote Dozer'!Q22) -> Remote Dozer | B1201: =IF('Remote Dozer'!$Q22="","",'Remote Dozer'!R22) -> 0 | C1201: =IF('Remote Dozer'!$Q22="","",'Remote Dozer'!S22) -> 0 | D1201: =IF('Remote Dozer'!$Q22="","",'Remote Dozer'!T22) -> 0 | E1201: =IF('Remote Dozer'!$Q22="","",'Remote Dozer'!U22) -> 0 | F1201: =IF('Remote Dozer'!$Q22="","",'Remote Dozer'!V22) -> 0 | G1201: =IF('Remote Dozer'!$Q22="","",'Remote Dozer'!W22) -> 0 | H1201: =IF('Remote Dozer'!$Q22="","",'Remote Dozer'!X22) -> 0 | ... S1201: =IF('Remote Dozer'!$Q22="","",'Remote Dozer'!AI22) -> 0
A1202: =IF('Remote Dozer'!$Q23="","",'Remote Dozer'!Q23) -> Remote Dozer | B1202: =IF('Remote Dozer'!$Q23="","",'Remote Dozer'!R23) -> 0 | C1202: =IF('Remote Dozer'!$Q23="","",'Remote Dozer'!S23) -> 0 | D1202: =IF('Remote Dozer'!$Q23="","",'Remote Dozer'!T23) -> 0 | E1202: =IF('Remote Dozer'!$Q23="","",'Remote Dozer'!U23) -> 0 | F1202: =IF('Remote Dozer'!$Q23="","",'Remote Dozer'!V23) -> 0 | G1202: =IF('Remote Dozer'!$Q23="","",'Remote Dozer'!W23) -> 0 | H1202: =IF('Remote Dozer'!$Q23="","",'Remote Dozer'!X23) -> 0 | ... S1202: =IF('Remote Dozer'!$Q23="","",'Remote Dozer'!AI23) -> 0
A1203: =IF('Remote Dozer'!$Q24="","",'Remote Dozer'!Q24) -> Remote Dozer | B1203: =IF('Remote Dozer'!$Q24="","",'Remote Dozer'!R24) -> 0 | C1203: =IF('Remote Dozer'!$Q24="","",'Remote Dozer'!S24) -> 0 | D1203: =IF('Remote Dozer'!$Q24="","",'Remote Dozer'!T24) -> 0 | E1203: =IF('Remote Dozer'!$Q24="","",'Remote Dozer'!U24) -> 0 | F1203: =IF('Remote Dozer'!$Q24="","",'Remote Dozer'!V24) -> 0 | G1203: =IF('Remote Dozer'!$Q24="","",'Remote Dozer'!W24) -> 0 | H1203: =IF('Remote Dozer'!$Q24="","",'Remote Dozer'!X24) -> 0 | ... S1203: =IF('Remote Dozer'!$Q24="","",'Remote Dozer'!AI24) -> 0
... A1429: =IF('Remote Dozer'!$Q250="","",'Remote Dozer'!Q250) -> Remote Dozer | B1429: =IF('Remote Dozer'!$Q250="","",'Remote Dozer'!R250) -> 0 | C1429: =IF('Remote Dozer'!$Q250="","",'Remote Dozer'!S250) -> 0 | D1429: =IF('Remote Dozer'!$Q250="","",'Remote Dozer'!T250) -> 0 | E1429: =IF('Remote Dozer'!$Q250="","",'Remote Dozer'!U250) -> 0 | F1429: =IF('Remote Dozer'!$Q250="","",'Remote Dozer'!V250) -> 0 | G1429: =IF('Remote Dozer'!$Q250="","",'Remote Dozer'!W250) -> 0 | H1429: =IF('Remote Dozer'!$Q250="","",'Remote Dozer'!X250) -> 0 | ... S1429: =IF('Remote Dozer'!$Q250="","",'Remote Dozer'!AI250) -> 0

Sheet Timeline_Periods
A1: Project | B1: Current Period | C1: Roadmap Period | D1: Phase | E1: Period Status | F1: Period Explanation | G1: Planned Objective / Outcome | H1: PIC Update Summary | I1: PIC Risks / Dependencies | J1: PIC Owner | K1: Target Date | L1: Reviewer Status | M1: Period Progress %
A2: =IF('Arcas HD'!$AK13="","",'Arcas HD'!AK13) -> Arcas HD | B2: =IF('Arcas HD'!$AK13="","",'Arcas HD'!AL13) -> Apr - Jun 2026 | C2: =IF('Arcas HD'!$AK13="","",'Arcas HD'!AM13) -> Jan - Mar 2026 | D2: =IF('Arcas HD'!$AK13="","",'Arcas HD'!AN13) -> Infrastructure & technical proving | E2: =IF('Arcas HD'!$AK13="","",'Arcas HD'!AO13) -> Progress | F2: =IF('Arcas HD'!$AK13="","",'Arcas HD'!AP13) -> Fase Infrastructure & technical proving pada periode Jan–Mar 2026 untuk Arcas HD. | G2: =IF('Arcas HD'!$AK13="","",'Arcas HD'!AQ13) -> Validate network backbone and ROC connection stability; Complete initial end-to-end system integration test | H2: =IF('Arcas HD'!$AK13="","",'Arcas HD'!AR13) -> Infrastruktur RTK dan server VPS monitoring sudah siap beroperasi 24/7. Evaluasi visual kamera siang dan malam di area tambang berjalan lancar. | ... M2: =IF('Arcas HD'!$AK13="","",'Arcas HD'!AW13) -> 0.6
A3: =IF('Arcas HD'!$AK14="","",'Arcas HD'!AK14) -> Arcas HD | B3: =IF('Arcas HD'!$AK14="","",'Arcas HD'!AL14) -> Apr - Jun 2026 | C3: =IF('Arcas HD'!$AK14="","",'Arcas HD'!AM14) -> Apr - Jun 2026 | D3: =IF('Arcas HD'!$AK14="","",'Arcas HD'!AN14) -> Pilot operation & safety proving | E3: =IF('Arcas HD'!$AK14="","",'Arcas HD'!AO14) -> Progress | F3: =IF('Arcas HD'!$AK14="","",'Arcas HD'!AP14) -> Fase Pilot operation & safety proving pada periode Apr–Jun 2026 untuk Arcas HD. | G3: =IF('Arcas HD'!$AK14="","",'Arcas HD'!AQ14) -> Run supervised multi-shift pilot scenario; Prepare Gate 3 evidence pack for approval | H3: =IF('Arcas HD'!$AK14="","",'Arcas HD'!AR14) -> Perakitan box kontrol, pemasangan wiring, dan instalasi bracket sensor pada unit HD selesai dilakukan. | ... M3: =IF('Arcas HD'!$AK14="","",'Arcas HD'!AW14) -> 0.25
A4: =IF('Arcas HD'!$AK15="","",'Arcas HD'!AK15) -> Arcas HD | B4: =IF('Arcas HD'!$AK15="","",'Arcas HD'!AL15) -> Apr - Jun 2026 | C4: =IF('Arcas HD'!$AK15="","",'Arcas HD'!AM15) -> Jul- Sept 2026 | D4: =IF('Arcas HD'!$AK15="","",'Arcas HD'!AN15) -> 0 | E4: =IF('Arcas HD'!$AK15="","",'Arcas HD'!AO15) | F4: =IF('Arcas HD'!$AK15="","",'Arcas HD'!AP15) -> 0 | G4: =IF('Arcas HD'!$AK15="","",'Arcas HD'!AQ15) -> 0 | H4: =IF('Arcas HD'!$AK15="","",'Arcas HD'!AR15) -> 0 | ... M4: =IF('Arcas HD'!$AK15="","",'Arcas HD'!AW15)
A5: =IF('Arcas HD'!$AK16="","",'Arcas HD'!AK16) -> Arcas HD | B5: =IF('Arcas HD'!$AK16="","",'Arcas HD'!AL16) -> Apr - Jun 2026 | C5: =IF('Arcas HD'!$AK16="","",'Arcas HD'!AM16) -> Oct - Dec 2026 | D5: =IF('Arcas HD'!$AK16="","",'Arcas HD'!AN16) -> 0 | E5: =IF('Arcas HD'!$AK16="","",'Arcas HD'!AO16) | F5: =IF('Arcas HD'!$AK16="","",'Arcas HD'!AP16) -> 0 | G5: =IF('Arcas HD'!$AK16="","",'Arcas HD'!AQ16) -> 0 | H5: =IF('Arcas HD'!$AK16="","",'Arcas HD'!AR16) -> 0 | ... M5: =IF('Arcas HD'!$AK16="","",'Arcas HD'!AW16)
A6: =IF('Arcas HD'!$AK17="","",'Arcas HD'!AK17) -> Arcas HD | B6: =IF('Arcas HD'!$AK17="","",'Arcas HD'!AL17) -> 0 | C6: =IF('Arcas HD'!$AK17="","",'Arcas HD'!AM17) -> 0 | D6: =IF('Arcas HD'!$AK17="","",'Arcas HD'!AN17) -> 0 | E6: =IF('Arcas HD'!$AK17="","",'Arcas HD'!AO17) | F6: =IF('Arcas HD'!$AK17="","",'Arcas HD'!AP17) -> 0 | G6: =IF('Arcas HD'!$AK17="","",'Arcas HD'!AQ17) -> 0 | H6: =IF('Arcas HD'!$AK17="","",'Arcas HD'!AR17) -> 0 | ... M6: =IF('Arcas HD'!$AK17="","",'Arcas HD'!AW17)
A7: =IF('Arcas HD'!$AK18="","",'Arcas HD'!AK18) -> Arcas HD | B7: =IF('Arcas HD'!$AK18="","",'Arcas HD'!AL18) -> 0 | C7: =IF('Arcas HD'!$AK18="","",'Arcas HD'!AM18) -> 0 | D7: =IF('Arcas HD'!$AK18="","",'Arcas HD'!AN18) -> 0 | E7: =IF('Arcas HD'!$AK18="","",'Arcas HD'!AO18) | F7: =IF('Arcas HD'!$AK18="","",'Arcas HD'!AP18) -> 0 | G7: =IF('Arcas HD'!$AK18="","",'Arcas HD'!AQ18) -> 0 | H7: =IF('Arcas HD'!$AK18="","",'Arcas HD'!AR18) -> 0 | ... M7: =IF('Arcas HD'!$AK18="","",'Arcas HD'!AW18)
A8: =IF('Arcas HD'!$AK19="","",'Arcas HD'!AK19) -> Arcas HD | B8: =IF('Arcas HD'!$AK19="","",'Arcas HD'!AL19) -> 0 | C8: =IF('Arcas HD'!$AK19="","",'Arcas HD'!AM19) -> 0 | D8: =IF('Arcas HD'!$AK19="","",'Arcas HD'!AN19) -> 0 | E8: =IF('Arcas HD'!$AK19="","",'Arcas HD'!AO19) | F8: =IF('Arcas HD'!$AK19="","",'Arcas HD'!AP19) -> 0 | G8: =IF('Arcas HD'!$AK19="","",'Arcas HD'!AQ19) -> 0 | H8: =IF('Arcas HD'!$AK19="","",'Arcas HD'!AR19) -> 0 | ... M8: =IF('Arcas HD'!$AK19="","",'Arcas HD'!AW19)
A9: =IF('Arcas HD'!$AK20="","",'Arcas HD'!AK20) -> Arcas HD | B9: =IF('Arcas HD'!$AK20="","",'Arcas HD'!AL20) -> 0 | C9: =IF('Arcas HD'!$AK20="","",'Arcas HD'!AM20) -> 0 | D9: =IF('Arcas HD'!$AK20="","",'Arcas HD'!AN20) -> 0 | E9: =IF('Arcas HD'!$AK20="","",'Arcas HD'!AO20) | F9: =IF('Arcas HD'!$AK20="","",'Arcas HD'!AP20) -> 0 | G9: =IF('Arcas HD'!$AK20="","",'Arcas HD'!AQ20) -> 0 | H9: =IF('Arcas HD'!$AK20="","",'Arcas HD'!AR20) -> 0 | ... M9: =IF('Arcas HD'!$AK20="","",'Arcas HD'!AW20)
A10: =IF('Arcas HD'!$AK21="","",'Arcas HD'!AK21) -> Arcas HD | B10: =IF('Arcas HD'!$AK21="","",'Arcas HD'!AL21) -> 0 | C10: =IF('Arcas HD'!$AK21="","",'Arcas HD'!AM21) -> 0 | D10: =IF('Arcas HD'!$AK21="","",'Arcas HD'!AN21) -> 0 | E10: =IF('Arcas HD'!$AK21="","",'Arcas HD'!AO21) | F10: =IF('Arcas HD'!$AK21="","",'Arcas HD'!AP21) -> 0 | G10: =IF('Arcas HD'!$AK21="","",'Arcas HD'!AQ21) -> 0 | H10: =IF('Arcas HD'!$AK21="","",'Arcas HD'!AR21) -> 0 | ... M10: =IF('Arcas HD'!$AK21="","",'Arcas HD'!AW21)
A11: =IF('Arcas HD'!$AK22="","",'Arcas HD'!AK22) -> Arcas HD | B11: =IF('Arcas HD'!$AK22="","",'Arcas HD'!AL22) -> 0 | C11: =IF('Arcas HD'!$AK22="","",'Arcas HD'!AM22) -> 0 | D11: =IF('Arcas HD'!$AK22="","",'Arcas HD'!AN22) -> 0 | E11: =IF('Arcas HD'!$AK22="","",'Arcas HD'!AO22) | F11: =IF('Arcas HD'!$AK22="","",'Arcas HD'!AP22) -> 0 | G11: =IF('Arcas HD'!$AK22="","",'Arcas HD'!AQ22) -> 0 | H11: =IF('Arcas HD'!$AK22="","",'Arcas HD'!AR22) -> 0 | ... M11: =IF('Arcas HD'!$AK22="","",'Arcas HD'!AW22)
A12: =IF('Arcas HD'!$AK23="","",'Arcas HD'!AK23) -> Arcas HD | B12: =IF('Arcas HD'!$AK23="","",'Arcas HD'!AL23) -> 0 | C12: =IF('Arcas HD'!$AK23="","",'Arcas HD'!AM23) -> 0 | D12: =IF('Arcas HD'!$AK23="","",'Arcas HD'!AN23) -> 0 | E12: =IF('Arcas HD'!$AK23="","",'Arcas HD'!AO23) | F12: =IF('Arcas HD'!$AK23="","",'Arcas HD'!AP23) -> 0 | G12: =IF('Arcas HD'!$AK23="","",'Arcas HD'!AQ23) -> 0 | H12: =IF('Arcas HD'!$AK23="","",'Arcas HD'!AR23) -> 0 | ... M12: =IF('Arcas HD'!$AK23="","",'Arcas HD'!AW23)
A13: =IF('Arcas HD'!$AK24="","",'Arcas HD'!AK24) -> Arcas HD | B13: =IF('Arcas HD'!$AK24="","",'Arcas HD'!AL24) -> 0 | C13: =IF('Arcas HD'!$AK24="","",'Arcas HD'!AM24) -> 0 | D13: =IF('Arcas HD'!$AK24="","",'Arcas HD'!AN24) -> 0 | E13: =IF('Arcas HD'!$AK24="","",'Arcas HD'!AO24) | F13: =IF('Arcas HD'!$AK24="","",'Arcas HD'!AP24) -> 0 | G13: =IF('Arcas HD'!$AK24="","",'Arcas HD'!AQ24) -> 0 | H13: =IF('Arcas HD'!$AK24="","",'Arcas HD'!AR24) -> 0 | ... M13: =IF('Arcas HD'!$AK24="","",'Arcas HD'!AW24)
... A239: =IF('Arcas HD'!$AK250="","",'Arcas HD'!AK250) -> Arcas HD | B239: =IF('Arcas HD'!$AK250="","",'Arcas HD'!AL250) -> 0 | C239: =IF('Arcas HD'!$AK250="","",'Arcas HD'!AM250) -> 0 | D239: =IF('Arcas HD'!$AK250="","",'Arcas HD'!AN250) -> 0 | E239: =IF('Arcas HD'!$AK250="","",'Arcas HD'!AO250) | F239: =IF('Arcas HD'!$AK250="","",'Arcas HD'!AP250) -> 0 | G239: =IF('Arcas HD'!$AK250="","",'Arcas HD'!AQ250) -> 0 | H239: =IF('Arcas HD'!$AK250="","",'Arcas HD'!AR250) -> 0 | ... M239: =IF('Arcas HD'!$AK250="","",'Arcas HD'!AW250)
A240: =IF('MGD PC'!$AK13="","",'MGD PC'!AK13) -> MGD PC | B240: =IF('MGD PC'!$AK13="","",'MGD PC'!AL13) -> Apr - Jun 2026 | C240: =IF('MGD PC'!$AK13="","",'MGD PC'!AM13) -> Jan–Mar 2026 | D240: =IF('MGD PC'!$AK13="","",'MGD PC'!AN13) -> Configuration & setup | E240: =IF('MGD PC'!$AK13="","",'MGD PC'!AO13) -> Progress | F240: =IF('MGD PC'!$AK13="","",'MGD PC'!AP13) -> Fase Configuration & setup pada periode Jan–Feb 2026 untuk MGD PC. | G240: =IF('MGD PC'!$AK13="","",'MGD PC'!AQ13) -> Install positioning and guidance configuration; Validate data logging and field test protocol; Train pilot supervisors on assisted workflow | H240: =IF('MGD PC'!$AK13="","",'MGD PC'!AR13) -> 0 | ... M240: =IF('MGD PC'!$AK13="","",'MGD PC'!AW13) -> 0.73333333
A241: =IF('MGD PC'!$AK14="","",'MGD PC'!AK14) -> MGD PC | B241: =IF('MGD PC'!$AK14="","",'MGD PC'!AL14) -> Apr - Jun 2026 | C241: =IF('MGD PC'!$AK14="","",'MGD PC'!AM14) -> Jan–Mar 2026 | D241: =IF('MGD PC'!$AK14="","",'MGD PC'!AN14) -> Pilot proving | E241: =IF('MGD PC'!$AK14="","",'MGD PC'!AO14) -> Progress | F241: =IF('MGD PC'!$AK14="","",'MGD PC'!AP14) -> Fase Pilot proving pada periode Mar–Jun 2026 untuk MGD PC. | G241: =IF('MGD PC'!$AK14="","",'MGD PC'!AQ14) -> Improve guidance accuracy at variable work fronts; Monitor user adoption and coaching needs; Review rework reduction evidence by shift | H241: =IF('MGD PC'!$AK14="","",'MGD PC'!AR14) -> 0 | ... M241: =IF('MGD PC'!$AK14="","",'MGD PC'!AW14) -> 0.33333333
A242: =IF('MGD PC'!$AK15="","",'MGD PC'!AK15) -> MGD PC | B242: =IF('MGD PC'!$AK15="","",'MGD PC'!AL15) -> 0 | C242: =IF('MGD PC'!$AK15="","",'MGD PC'!AM15) -> 0 | D242: =IF('MGD PC'!$AK15="","",'MGD PC'!AN15) -> 0 | E242: =IF('MGD PC'!$AK15="","",'MGD PC'!AO15) | F242: =IF('MGD PC'!$AK15="","",'MGD PC'!AP15) -> 0 | G242: =IF('MGD PC'!$AK15="","",'MGD PC'!AQ15) -> 0 | H242: =IF('MGD PC'!$AK15="","",'MGD PC'!AR15) -> 0 | ... M242: =IF('MGD PC'!$AK15="","",'MGD PC'!AW15)
A243: =IF('MGD PC'!$AK16="","",'MGD PC'!AK16) -> MGD PC | B243: =IF('MGD PC'!$AK16="","",'MGD PC'!AL16) -> 0 | C243: =IF('MGD PC'!$AK16="","",'MGD PC'!AM16) -> 0 | D243: =IF('MGD PC'!$AK16="","",'MGD PC'!AN16) -> 0 | E243: =IF('MGD PC'!$AK16="","",'MGD PC'!AO16) | F243: =IF('MGD PC'!$AK16="","",'MGD PC'!AP16) -> 0 | G243: =IF('MGD PC'!$AK16="","",'MGD PC'!AQ16) -> 0 | H243: =IF('MGD PC'!$AK16="","",'MGD PC'!AR16) -> 0 | ... M243: =IF('MGD PC'!$AK16="","",'MGD PC'!AW16)
A244: =IF('MGD PC'!$AK17="","",'MGD PC'!AK17) -> MGD PC | B244: =IF('MGD PC'!$AK17="","",'MGD PC'!AL17) -> 0 | C244: =IF('MGD PC'!$AK17="","",'MGD PC'!AM17) -> 0 | D244: =IF('MGD PC'!$AK17="","",'MGD PC'!AN17) -> 0 | E244: =IF('MGD PC'!$AK17="","",'MGD PC'!AO17) | F244: =IF('MGD PC'!$AK17="","",'MGD PC'!AP17) -> 0 | G244: =IF('MGD PC'!$AK17="","",'MGD PC'!AQ17) -> 0 | H244: =IF('MGD PC'!$AK17="","",'MGD PC'!AR17) -> 0 | ... M244: =IF('MGD PC'!$AK17="","",'MGD PC'!AW17)
A245: =IF('MGD PC'!$AK18="","",'MGD PC'!AK18) -> MGD PC | B245: =IF('MGD PC'!$AK18="","",'MGD PC'!AL18) -> 0 | C245: =IF('MGD PC'!$AK18="","",'MGD PC'!AM18) -> 0 | D245: =IF('MGD PC'!$AK18="","",'MGD PC'!AN18) -> 0 | E245: =IF('MGD PC'!$AK18="","",'MGD PC'!AO18) | F245: =IF('MGD PC'!$AK18="","",'MGD PC'!AP18) -> 0 | G245: =IF('MGD PC'!$AK18="","",'MGD PC'!AQ18) -> 0 | H245: =IF('MGD PC'!$AK18="","",'MGD PC'!AR18) -> 0 | ... M245: =IF('MGD PC'!$AK18="","",'MGD PC'!AW18)
A246: =IF('MGD PC'!$AK19="","",'MGD PC'!AK19) -> MGD PC | B246: =IF('MGD PC'!$AK19="","",'MGD PC'!AL19) -> 0 | C246: =IF('MGD PC'!$AK19="","",'MGD PC'!AM19) -> 0 | D246: =IF('MGD PC'!$AK19="","",'MGD PC'!AN19) -> 0 | E246: =IF('MGD PC'!$AK19="","",'MGD PC'!AO19) | F246: =IF('MGD PC'!$AK19="","",'MGD PC'!AP19) -> 0 | G246: =IF('MGD PC'!$AK19="","",'MGD PC'!AQ19) -> 0 | H246: =IF('MGD PC'!$AK19="","",'MGD PC'!AR19) -> 0 | ... M246: =IF('MGD PC'!$AK19="","",'MGD PC'!AW19)
A247: =IF('MGD PC'!$AK20="","",'MGD PC'!AK20) -> MGD PC | B247: =IF('MGD PC'!$AK20="","",'MGD PC'!AL20) -> 0 | C247: =IF('MGD PC'!$AK20="","",'MGD PC'!AM20) -> 0 | D247: =IF('MGD PC'!$AK20="","",'MGD PC'!AN20) -> 0 | E247: =IF('MGD PC'!$AK20="","",'MGD PC'!AO20) | F247: =IF('MGD PC'!$AK20="","",'MGD PC'!AP20) -> 0 | G247: =IF('MGD PC'!$AK20="","",'MGD PC'!AQ20) -> 0 | H247: =IF('MGD PC'!$AK20="","",'MGD PC'!AR20) -> 0 | ... M247: =IF('MGD PC'!$AK20="","",'MGD PC'!AW20)
A248: =IF('MGD PC'!$AK21="","",'MGD PC'!AK21) -> MGD PC | B248: =IF('MGD PC'!$AK21="","",'MGD PC'!AL21) -> 0 | C248: =IF('MGD PC'!$AK21="","",'MGD PC'!AM21) -> 0 | D248: =IF('MGD PC'!$AK21="","",'MGD PC'!AN21) -> 0 | E248: =IF('MGD PC'!$AK21="","",'MGD PC'!AO21) | F248: =IF('MGD PC'!$AK21="","",'MGD PC'!AP21) -> 0 | G248: =IF('MGD PC'!$AK21="","",'MGD PC'!AQ21) -> 0 | H248: =IF('MGD PC'!$AK21="","",'MGD PC'!AR21) -> 0 | ... M248: =IF('MGD PC'!$AK21="","",'MGD PC'!AW21)
A249: =IF('MGD PC'!$AK22="","",'MGD PC'!AK22) -> MGD PC | B249: =IF('MGD PC'!$AK22="","",'MGD PC'!AL22) -> 0 | C249: =IF('MGD PC'!$AK22="","",'MGD PC'!AM22) -> 0 | D249: =IF('MGD PC'!$AK22="","",'MGD PC'!AN22) -> 0 | E249: =IF('MGD PC'!$AK22="","",'MGD PC'!AO22) | F249: =IF('MGD PC'!$AK22="","",'MGD PC'!AP22) -> 0 | G249: =IF('MGD PC'!$AK22="","",'MGD PC'!AQ22) -> 0 | H249: =IF('MGD PC'!$AK22="","",'MGD PC'!AR22) -> 0 | ... M249: =IF('MGD PC'!$AK22="","",'MGD PC'!AW22)
A250: =IF('MGD PC'!$AK23="","",'MGD PC'!AK23) -> MGD PC | B250: =IF('MGD PC'!$AK23="","",'MGD PC'!AL23) -> 0 | C250: =IF('MGD PC'!$AK23="","",'MGD PC'!AM23) -> 0 | D250: =IF('MGD PC'!$AK23="","",'MGD PC'!AN23) -> 0 | E250: =IF('MGD PC'!$AK23="","",'MGD PC'!AO23) | F250: =IF('MGD PC'!$AK23="","",'MGD PC'!AP23) -> 0 | G250: =IF('MGD PC'!$AK23="","",'MGD PC'!AQ23) -> 0 | H250: =IF('MGD PC'!$AK23="","",'MGD PC'!AR23) -> 0 | ... M250: =IF('MGD PC'!$AK23="","",'MGD PC'!AW23)
A251: =IF('MGD PC'!$AK24="","",'MGD PC'!AK24) -> MGD PC | B251: =IF('MGD PC'!$AK24="","",'MGD PC'!AL24) -> 0 | C251: =IF('MGD PC'!$AK24="","",'MGD PC'!AM24) -> 0 | D251: =IF('MGD PC'!$AK24="","",'MGD PC'!AN24) -> 0 | E251: =IF('MGD PC'!$AK24="","",'MGD PC'!AO24) | F251: =IF('MGD PC'!$AK24="","",'MGD PC'!AP24) -> 0 | G251: =IF('MGD PC'!$AK24="","",'MGD PC'!AQ24) -> 0 | H251: =IF('MGD PC'!$AK24="","",'MGD PC'!AR24) -> 0 | ... M251: =IF('MGD PC'!$AK24="","",'MGD PC'!AW24)
... A477: =IF('MGD PC'!$AK250="","",'MGD PC'!AK250) -> MGD PC | B477: =IF('MGD PC'!$AK250="","",'MGD PC'!AL250) -> 0 | C477: =IF('MGD PC'!$AK250="","",'MGD PC'!AM250) -> 0 | D477: =IF('MGD PC'!$AK250="","",'MGD PC'!AN250) -> 0 | E477: =IF('MGD PC'!$AK250="","",'MGD PC'!AO250) | F477: =IF('MGD PC'!$AK250="","",'MGD PC'!AP250) -> 0 | G477: =IF('MGD PC'!$AK250="","",'MGD PC'!AQ250) -> 0 | H477: =IF('MGD PC'!$AK250="","",'MGD PC'!AR250) -> 0 | ... M477: =IF('MGD PC'!$AK250="","",'MGD PC'!AW250)
A478: =IF('Remote Pump'!$AK13="","",'Remote Pump'!AK13) -> Remote Pump | B478: =IF('Remote Pump'!$AK13="","",'Remote Pump'!AL13) -> Apr - Jun 2026 | C478: =IF('Remote Pump'!$AK13="","",'Remote Pump'!AM13) -> Jan - Mar 2026 | D478: =IF('Remote Pump'!$AK13="","",'Remote Pump'!AN13) -> Remote control commissioning | E478: =IF('Remote Pump'!$AK13="","",'Remote Pump'!AO13) | F478: =IF('Remote Pump'!$AK13="","",'Remote Pump'!AP13) -> Fase Remote control commissioning pada periode Jan–Mar 2026 untuk Remote Pump. | G478: =IF('Remote Pump'!$AK13="","",'Remote Pump'!AQ13) -> Commission telemetry and command loop; Validate remote signal reliability; Prepare pump isolation and takeover workflow | H478: =IF('Remote Pump'!$AK13="","",'Remote Pump'!AR13) -> 0 | ... M478: =IF('Remote Pump'!$AK13="","",'Remote Pump'!AW13)
A479: =IF('Remote Pump'!$AK14="","",'Remote Pump'!AK14) -> Remote Pump | B479: =IF('Remote Pump'!$AK14="","",'Remote Pump'!AL14) -> Apr - Jun 2026 | C479: =IF('Remote Pump'!$AK14="","",'Remote Pump'!AM14) -> Jan - Mar 2026 | D479: =IF('Remote Pump'!$AK14="","",'Remote Pump'!AN14) -> Operational pilot and fail-safe proving | E479: =IF('Remote Pump'!$AK14="","",'Remote Pump'!AO14) | F479: =IF('Remote Pump'!$AK14="","",'Remote Pump'!AP14) -> Fase Operational pilot and fail-safe proving pada periode Apr–Jul 2026 untuk Remote Pump. | G479: =IF('Remote Pump'!$AK14="","",'Remote Pump'!AQ14) -> Complete fail-safe loss-of-signal scenarios; Track downtime reduction against baseline; Document local override discipline by area | H479: =IF('Remote Pump'!$AK14="","",'Remote Pump'!AR14) -> 0 | ... M479: =IF('Remote Pump'!$AK14="","",'Remote Pump'!AW14)
A480: =IF('Remote Pump'!$AK15="","",'Remote Pump'!AK15) -> Remote Pump | B480: =IF('Remote Pump'!$AK15="","",'Remote Pump'!AL15) -> 0 | C480: =IF('Remote Pump'!$AK15="","",'Remote Pump'!AM15) -> 0 | D480: =IF('Remote Pump'!$AK15="","",'Remote Pump'!AN15) -> 0 | E480: =IF('Remote Pump'!$AK15="","",'Remote Pump'!AO15) | F480: =IF('Remote Pump'!$AK15="","",'Remote Pump'!AP15) -> 0 | G480: =IF('Remote Pump'!$AK15="","",'Remote Pump'!AQ15) -> 0 | H480: =IF('Remote Pump'!$AK15="","",'Remote Pump'!AR15) -> 0 | ... M480: =IF('Remote Pump'!$AK15="","",'Remote Pump'!AW15)
A481: =IF('Remote Pump'!$AK16="","",'Remote Pump'!AK16) -> Remote Pump | B481: =IF('Remote Pump'!$AK16="","",'Remote Pump'!AL16) -> 0 | C481: =IF('Remote Pump'!$AK16="","",'Remote Pump'!AM16) -> 0 | D481: =IF('Remote Pump'!$AK16="","",'Remote Pump'!AN16) -> 0 | E481: =IF('Remote Pump'!$AK16="","",'Remote Pump'!AO16) | F481: =IF('Remote Pump'!$AK16="","",'Remote Pump'!AP16) -> 0 | G481: =IF('Remote Pump'!$AK16="","",'Remote Pump'!AQ16) -> 0 | H481: =IF('Remote Pump'!$AK16="","",'Remote Pump'!AR16) -> 0 | ... M481: =IF('Remote Pump'!$AK16="","",'Remote Pump'!AW16)
A482: =IF('Remote Pump'!$AK17="","",'Remote Pump'!AK17) -> Remote Pump | B482: =IF('Remote Pump'!$AK17="","",'Remote Pump'!AL17) -> 0 | C482: =IF('Remote Pump'!$AK17="","",'Remote Pump'!AM17) -> 0 | D482: =IF('Remote Pump'!$AK17="","",'Remote Pump'!AN17) -> 0 | E482: =IF('Remote Pump'!$AK17="","",'Remote Pump'!AO17) | F482: =IF('Remote Pump'!$AK17="","",'Remote Pump'!AP17) -> 0 | G482: =IF('Remote Pump'!$AK17="","",'Remote Pump'!AQ17) -> 0 | H482: =IF('Remote Pump'!$AK17="","",'Remote Pump'!AR17) -> 0 | ... M482: =IF('Remote Pump'!$AK17="","",'Remote Pump'!AW17)
A483: =IF('Remote Pump'!$AK18="","",'Remote Pump'!AK18) -> Remote Pump | B483: =IF('Remote Pump'!$AK18="","",'Remote Pump'!AL18) -> 0 | C483: =IF('Remote Pump'!$AK18="","",'Remote Pump'!AM18) -> 0 | D483: =IF('Remote Pump'!$AK18="","",'Remote Pump'!AN18) -> 0 | E483: =IF('Remote Pump'!$AK18="","",'Remote Pump'!AO18) | F483: =IF('Remote Pump'!$AK18="","",'Remote Pump'!AP18) -> 0 | G483: =IF('Remote Pump'!$AK18="","",'Remote Pump'!AQ18) -> 0 | H483: =IF('Remote Pump'!$AK18="","",'Remote Pump'!AR18) -> 0 | ... M483: =IF('Remote Pump'!$AK18="","",'Remote Pump'!AW18)
A484: =IF('Remote Pump'!$AK19="","",'Remote Pump'!AK19) -> Remote Pump | B484: =IF('Remote Pump'!$AK19="","",'Remote Pump'!AL19) -> 0 | C484: =IF('Remote Pump'!$AK19="","",'Remote Pump'!AM19) -> 0 | D484: =IF('Remote Pump'!$AK19="","",'Remote Pump'!AN19) -> 0 | E484: =IF('Remote Pump'!$AK19="","",'Remote Pump'!AO19) | F484: =IF('Remote Pump'!$AK19="","",'Remote Pump'!AP19) -> 0 | G484: =IF('Remote Pump'!$AK19="","",'Remote Pump'!AQ19) -> 0 | H484: =IF('Remote Pump'!$AK19="","",'Remote Pump'!AR19) -> 0 | ... M484: =IF('Remote Pump'!$AK19="","",'Remote Pump'!AW19)
A485: =IF('Remote Pump'!$AK20="","",'Remote Pump'!AK20) -> Remote Pump | B485: =IF('Remote Pump'!$AK20="","",'Remote Pump'!AL20) -> 0 | C485: =IF('Remote Pump'!$AK20="","",'Remote Pump'!AM20) -> 0 | D485: =IF('Remote Pump'!$AK20="","",'Remote Pump'!AN20) -> 0 | E485: =IF('Remote Pump'!$AK20="","",'Remote Pump'!AO20) | F485: =IF('Remote Pump'!$AK20="","",'Remote Pump'!AP20) -> 0 | G485: =IF('Remote Pump'!$AK20="","",'Remote Pump'!AQ20) -> 0 | H485: =IF('Remote Pump'!$AK20="","",'Remote Pump'!AR20) -> 0 | ... M485: =IF('Remote Pump'!$AK20="","",'Remote Pump'!AW20)
A486: =IF('Remote Pump'!$AK21="","",'Remote Pump'!AK21) -> Remote Pump | B486: =IF('Remote Pump'!$AK21="","",'Remote Pump'!AL21) -> 0 | C486: =IF('Remote Pump'!$AK21="","",'Remote Pump'!AM21) -> 0 | D486: =IF('Remote Pump'!$AK21="","",'Remote Pump'!AN21) -> 0 | E486: =IF('Remote Pump'!$AK21="","",'Remote Pump'!AO21) | F486: =IF('Remote Pump'!$AK21="","",'Remote Pump'!AP21) -> 0 | G486: =IF('Remote Pump'!$AK21="","",'Remote Pump'!AQ21) -> 0 | H486: =IF('Remote Pump'!$AK21="","",'Remote Pump'!AR21) -> 0 | ... M486: =IF('Remote Pump'!$AK21="","",'Remote Pump'!AW21)
A487: =IF('Remote Pump'!$AK22="","",'Remote Pump'!AK22) -> Remote Pump | B487: =IF('Remote Pump'!$AK22="","",'Remote Pump'!AL22) -> 0 | C487: =IF('Remote Pump'!$AK22="","",'Remote Pump'!AM22) -> 0 | D487: =IF('Remote Pump'!$AK22="","",'Remote Pump'!AN22) -> 0 | E487: =IF('Remote Pump'!$AK22="","",'Remote Pump'!AO22) | F487: =IF('Remote Pump'!$AK22="","",'Remote Pump'!AP22) -> 0 | G487: =IF('Remote Pump'!$AK22="","",'Remote Pump'!AQ22) -> 0 | H487: =IF('Remote Pump'!$AK22="","",'Remote Pump'!AR22) -> 0 | ... M487: =IF('Remote Pump'!$AK22="","",'Remote Pump'!AW22)
A488: =IF('Remote Pump'!$AK23="","",'Remote Pump'!AK23) -> Remote Pump | B488: =IF('Remote Pump'!$AK23="","",'Remote Pump'!AL23) -> 0 | C488: =IF('Remote Pump'!$AK23="","",'Remote Pump'!AM23) -> 0 | D488: =IF('Remote Pump'!$AK23="","",'Remote Pump'!AN23) -> 0 | E488: =IF('Remote Pump'!$AK23="","",'Remote Pump'!AO23) | F488: =IF('Remote Pump'!$AK23="","",'Remote Pump'!AP23) -> 0 | G488: =IF('Remote Pump'!$AK23="","",'Remote Pump'!AQ23) -> 0 | H488: =IF('Remote Pump'!$AK23="","",'Remote Pump'!AR23) -> 0 | ... M488: =IF('Remote Pump'!$AK23="","",'Remote Pump'!AW23)
A489: =IF('Remote Pump'!$AK24="","",'Remote Pump'!AK24) -> Remote Pump | B489: =IF('Remote Pump'!$AK24="","",'Remote Pump'!AL24) -> 0 | C489: =IF('Remote Pump'!$AK24="","",'Remote Pump'!AM24) -> 0 | D489: =IF('Remote Pump'!$AK24="","",'Remote Pump'!AN24) -> 0 | E489: =IF('Remote Pump'!$AK24="","",'Remote Pump'!AO24) | F489: =IF('Remote Pump'!$AK24="","",'Remote Pump'!AP24) -> 0 | G489: =IF('Remote Pump'!$AK24="","",'Remote Pump'!AQ24) -> 0 | H489: =IF('Remote Pump'!$AK24="","",'Remote Pump'!AR24) -> 0 | ... M489: =IF('Remote Pump'!$AK24="","",'Remote Pump'!AW24)
... A715: =IF('Remote Pump'!$AK250="","",'Remote Pump'!AK250) -> Remote Pump | B715: =IF('Remote Pump'!$AK250="","",'Remote Pump'!AL250) -> 0 | C715: =IF('Remote Pump'!$AK250="","",'Remote Pump'!AM250) -> 0 | D715: =IF('Remote Pump'!$AK250="","",'Remote Pump'!AN250) -> 0 | E715: =IF('Remote Pump'!$AK250="","",'Remote Pump'!AO250) | F715: =IF('Remote Pump'!$AK250="","",'Remote Pump'!AP250) -> 0 | G715: =IF('Remote Pump'!$AK250="","",'Remote Pump'!AQ250) -> 0 | H715: =IF('Remote Pump'!$AK250="","",'Remote Pump'!AR250) -> 0 | ... M715: =IF('Remote Pump'!$AK250="","",'Remote Pump'!AW250)
A716: =IF('Hauling Fleet Management'!$AK13="","",'Hauling Fleet Management'!AK13) -> Hauling Fleet Management | B716: =IF('Hauling Fleet Management'!$AK13="","",'Hauling Fleet Management'!AL13) -> Apr - Jun 2026 | C716: =IF('Hauling Fleet Management'!$AK13="","",'Hauling Fleet Management'!AM13) -> Jan–Mar 2026 | D716: =IF('Hauling Fleet Management'!$AK13="","",'Hauling Fleet Management'!AN13) -> Data and dashboard stabilization | E716: =IF('Hauling Fleet Management'!$AK13="","",'Hauling Fleet Management'!AO13) | F716: =IF('Hauling Fleet Management'!$AK13="","",'Hauling Fleet Management'!AP13) -> Fase Data and dashboard stabilization pada periode Jan–Mar 2026 untuk Hauling Fleet Management. | G716: =IF('Hauling Fleet Management'!$AK13="","",'Hauling Fleet Management'!AQ13) -> Stabilize fleet data ingestion pipeline; Launch dispatcher dashboard and KPI baseline; Validate refresh cycle for operational use | H716: =IF('Hauling Fleet Management'!$AK13="","",'Hauling Fleet Management'!AR13) -> 0 | ... M716: =IF('Hauling Fleet Management'!$AK13="","",'Hauling Fleet Management'!AW13)
A717: =IF('Hauling Fleet Management'!$AK14="","",'Hauling Fleet Management'!AK14) -> Hauling Fleet Management | B717: =IF('Hauling Fleet Management'!$AK14="","",'Hauling Fleet Management'!AL14) -> Apr - Jun 2026 | C717: =IF('Hauling Fleet Management'!$AK14="","",'Hauling Fleet Management'!AM14) -> Jan–Mar 2026 | D717: =IF('Hauling Fleet Management'!$AK14="","",'Hauling Fleet Management'!AN14) -> Optimization proving | E717: =IF('Hauling Fleet Management'!$AK14="","",'Hauling Fleet Management'!AO14) | F717: =IF('Hauling Fleet Management'!$AK14="","",'Hauling Fleet Management'!AP14) -> Fase Optimization proving pada periode Apr–Aug 2026 untuk Hauling Fleet Management. | G717: =IF('Hauling Fleet Management'!$AK14="","",'Hauling Fleet Management'!AQ14) -> Track queue and idle reduction by shift; Improve user adoption across supervisors; Lock fuel and utilization uplift evidence | H717: =IF('Hauling Fleet Management'!$AK14="","",'Hauling Fleet Management'!AR14) -> 0 | ... M717: =IF('Hauling Fleet Management'!$AK14="","",'Hauling Fleet Management'!AW14)
A718: =IF('Hauling Fleet Management'!$AK15="","",'Hauling Fleet Management'!AK15) -> Hauling Fleet Management | B718: =IF('Hauling Fleet Management'!$AK15="","",'Hauling Fleet Management'!AL15) -> 0 | C718: =IF('Hauling Fleet Management'!$AK15="","",'Hauling Fleet Management'!AM15) -> 0 | D718: =IF('Hauling Fleet Management'!$AK15="","",'Hauling Fleet Management'!AN15) -> 0 | E718: =IF('Hauling Fleet Management'!$AK15="","",'Hauling Fleet Management'!AO15) | F718: =IF('Hauling Fleet Management'!$AK15="","",'Hauling Fleet Management'!AP15) -> 0 | G718: =IF('Hauling Fleet Management'!$AK15="","",'Hauling Fleet Management'!AQ15) -> 0 | H718: =IF('Hauling Fleet Management'!$AK15="","",'Hauling Fleet Management'!AR15) -> 0 | ... M718: =IF('Hauling Fleet Management'!$AK15="","",'Hauling Fleet Management'!AW15)
A719: =IF('Hauling Fleet Management'!$AK16="","",'Hauling Fleet Management'!AK16) -> Hauling Fleet Management | B719: =IF('Hauling Fleet Management'!$AK16="","",'Hauling Fleet Management'!AL16) -> 0 | C719: =IF('Hauling Fleet Management'!$AK16="","",'Hauling Fleet Management'!AM16) -> 0 | D719: =IF('Hauling Fleet Management'!$AK16="","",'Hauling Fleet Management'!AN16) -> 0 | E719: =IF('Hauling Fleet Management'!$AK16="","",'Hauling Fleet Management'!AO16) | F719: =IF('Hauling Fleet Management'!$AK16="","",'Hauling Fleet Management'!AP16) -> 0 | G719: =IF('Hauling Fleet Management'!$AK16="","",'Hauling Fleet Management'!AQ16) -> 0 | H719: =IF('Hauling Fleet Management'!$AK16="","",'Hauling Fleet Management'!AR16) -> 0 | ... M719: =IF('Hauling Fleet Management'!$AK16="","",'Hauling Fleet Management'!AW16)
A720: =IF('Hauling Fleet Management'!$AK17="","",'Hauling Fleet Management'!AK17) -> Hauling Fleet Management | B720: =IF('Hauling Fleet Management'!$AK17="","",'Hauling Fleet Management'!AL17) -> 0 | C720: =IF('Hauling Fleet Management'!$AK17="","",'Hauling Fleet Management'!AM17) -> 0 | D720: =IF('Hauling Fleet Management'!$AK17="","",'Hauling Fleet Management'!AN17) -> 0 | E720: =IF('Hauling Fleet Management'!$AK17="","",'Hauling Fleet Management'!AO17) | F720: =IF('Hauling Fleet Management'!$AK17="","",'Hauling Fleet Management'!AP17) -> 0 | G720: =IF('Hauling Fleet Management'!$AK17="","",'Hauling Fleet Management'!AQ17) -> 0 | H720: =IF('Hauling Fleet Management'!$AK17="","",'Hauling Fleet Management'!AR17) -> 0 | ... M720: =IF('Hauling Fleet Management'!$AK17="","",'Hauling Fleet Management'!AW17)
A721: =IF('Hauling Fleet Management'!$AK18="","",'Hauling Fleet Management'!AK18) -> Hauling Fleet Management | B721: =IF('Hauling Fleet Management'!$AK18="","",'Hauling Fleet Management'!AL18) -> 0 | C721: =IF('Hauling Fleet Management'!$AK18="","",'Hauling Fleet Management'!AM18) -> 0 | D721: =IF('Hauling Fleet Management'!$AK18="","",'Hauling Fleet Management'!AN18) -> 0 | E721: =IF('Hauling Fleet Management'!$AK18="","",'Hauling Fleet Management'!AO18) | F721: =IF('Hauling Fleet Management'!$AK18="","",'Hauling Fleet Management'!AP18) -> 0 | G721: =IF('Hauling Fleet Management'!$AK18="","",'Hauling Fleet Management'!AQ18) -> 0 | H721: =IF('Hauling Fleet Management'!$AK18="","",'Hauling Fleet Management'!AR18) -> 0 | ... M721: =IF('Hauling Fleet Management'!$AK18="","",'Hauling Fleet Management'!AW18)
A722: =IF('Hauling Fleet Management'!$AK19="","",'Hauling Fleet Management'!AK19) -> Hauling Fleet Management | B722: =IF('Hauling Fleet Management'!$AK19="","",'Hauling Fleet Management'!AL19) -> 0 | C722: =IF('Hauling Fleet Management'!$AK19="","",'Hauling Fleet Management'!AM19) -> 0 | D722: =IF('Hauling Fleet Management'!$AK19="","",'Hauling Fleet Management'!AN19) -> 0 | E722: =IF('Hauling Fleet Management'!$AK19="","",'Hauling Fleet Management'!AO19) | F722: =IF('Hauling Fleet Management'!$AK19="","",'Hauling Fleet Management'!AP19) -> 0 | G722: =IF('Hauling Fleet Management'!$AK19="","",'Hauling Fleet Management'!AQ19) -> 0 | H722: =IF('Hauling Fleet Management'!$AK19="","",'Hauling Fleet Management'!AR19) -> 0 | ... M722: =IF('Hauling Fleet Management'!$AK19="","",'Hauling Fleet Management'!AW19)
A723: =IF('Hauling Fleet Management'!$AK20="","",'Hauling Fleet Management'!AK20) -> Hauling Fleet Management | B723: =IF('Hauling Fleet Management'!$AK20="","",'Hauling Fleet Management'!AL20) -> 0 | C723: =IF('Hauling Fleet Management'!$AK20="","",'Hauling Fleet Management'!AM20) -> 0 | D723: =IF('Hauling Fleet Management'!$AK20="","",'Hauling Fleet Management'!AN20) -> 0 | E723: =IF('Hauling Fleet Management'!$AK20="","",'Hauling Fleet Management'!AO20) | F723: =IF('Hauling Fleet Management'!$AK20="","",'Hauling Fleet Management'!AP20) -> 0 | G723: =IF('Hauling Fleet Management'!$AK20="","",'Hauling Fleet Management'!AQ20) -> 0 | H723: =IF('Hauling Fleet Management'!$AK20="","",'Hauling Fleet Management'!AR20) -> 0 | ... M723: =IF('Hauling Fleet Management'!$AK20="","",'Hauling Fleet Management'!AW20)
A724: =IF('Hauling Fleet Management'!$AK21="","",'Hauling Fleet Management'!AK21) -> Hauling Fleet Management | B724: =IF('Hauling Fleet Management'!$AK21="","",'Hauling Fleet Management'!AL21) -> 0 | C724: =IF('Hauling Fleet Management'!$AK21="","",'Hauling Fleet Management'!AM21) -> 0 | D724: =IF('Hauling Fleet Management'!$AK21="","",'Hauling Fleet Management'!AN21) -> 0 | E724: =IF('Hauling Fleet Management'!$AK21="","",'Hauling Fleet Management'!AO21) | F724: =IF('Hauling Fleet Management'!$AK21="","",'Hauling Fleet Management'!AP21) -> 0 | G724: =IF('Hauling Fleet Management'!$AK21="","",'Hauling Fleet Management'!AQ21) -> 0 | H724: =IF('Hauling Fleet Management'!$AK21="","",'Hauling Fleet Management'!AR21) -> 0 | ... M724: =IF('Hauling Fleet Management'!$AK21="","",'Hauling Fleet Management'!AW21)
A725: =IF('Hauling Fleet Management'!$AK22="","",'Hauling Fleet Management'!AK22) -> Hauling Fleet Management | B725: =IF('Hauling Fleet Management'!$AK22="","",'Hauling Fleet Management'!AL22) -> 0 | C725: =IF('Hauling Fleet Management'!$AK22="","",'Hauling Fleet Management'!AM22) -> 0 | D725: =IF('Hauling Fleet Management'!$AK22="","",'Hauling Fleet Management'!AN22) -> 0 | E725: =IF('Hauling Fleet Management'!$AK22="","",'Hauling Fleet Management'!AO22) | F725: =IF('Hauling Fleet Management'!$AK22="","",'Hauling Fleet Management'!AP22) -> 0 | G725: =IF('Hauling Fleet Management'!$AK22="","",'Hauling Fleet Management'!AQ22) -> 0 | H725: =IF('Hauling Fleet Management'!$AK22="","",'Hauling Fleet Management'!AR22) -> 0 | ... M725: =IF('Hauling Fleet Management'!$AK22="","",'Hauling Fleet Management'!AW22)
A726: =IF('Hauling Fleet Management'!$AK23="","",'Hauling Fleet Management'!AK23) -> Hauling Fleet Management | B726: =IF('Hauling Fleet Management'!$AK23="","",'Hauling Fleet Management'!AL23) -> 0 | C726: =IF('Hauling Fleet Management'!$AK23="","",'Hauling Fleet Management'!AM23) -> 0 | D726: =IF('Hauling Fleet Management'!$AK23="","",'Hauling Fleet Management'!AN23) -> 0 | E726: =IF('Hauling Fleet Management'!$AK23="","",'Hauling Fleet Management'!AO23) | F726: =IF('Hauling Fleet Management'!$AK23="","",'Hauling Fleet Management'!AP23) -> 0 | G726: =IF('Hauling Fleet Management'!$AK23="","",'Hauling Fleet Management'!AQ23) -> 0 | H726: =IF('Hauling Fleet Management'!$AK23="","",'Hauling Fleet Management'!AR23) -> 0 | ... M726: =IF('Hauling Fleet Management'!$AK23="","",'Hauling Fleet Management'!AW23)
A727: =IF('Hauling Fleet Management'!$AK24="","",'Hauling Fleet Management'!AK24) -> Hauling Fleet Management | B727: =IF('Hauling Fleet Management'!$AK24="","",'Hauling Fleet Management'!AL24) -> 0 | C727: =IF('Hauling Fleet Management'!$AK24="","",'Hauling Fleet Management'!AM24) -> 0 | D727: =IF('Hauling Fleet Management'!$AK24="","",'Hauling Fleet Management'!AN24) -> 0 | E727: =IF('Hauling Fleet Management'!$AK24="","",'Hauling Fleet Management'!AO24) | F727: =IF('Hauling Fleet Management'!$AK24="","",'Hauling Fleet Management'!AP24) -> 0 | G727: =IF('Hauling Fleet Management'!$AK24="","",'Hauling Fleet Management'!AQ24) -> 0 | H727: =IF('Hauling Fleet Management'!$AK24="","",'Hauling Fleet Management'!AR24) -> 0 | ... M727: =IF('Hauling Fleet Management'!$AK24="","",'Hauling Fleet Management'!AW24)
... A953: =IF('Hauling Fleet Management'!$AK250="","",'Hauling Fleet Management'!AK250) -> Hauling Fleet Management | B953: =IF('Hauling Fleet Management'!$AK250="","",'Hauling Fleet Management'!AL250) -> 0 | C953: =IF('Hauling Fleet Management'!$AK250="","",'Hauling Fleet Management'!AM250) -> 0 | D953: =IF('Hauling Fleet Management'!$AK250="","",'Hauling Fleet Management'!AN250) -> 0 | E953: =IF('Hauling Fleet Management'!$AK250="","",'Hauling Fleet Management'!AO250) | F953: =IF('Hauling Fleet Management'!$AK250="","",'Hauling Fleet Management'!AP250) -> 0 | G953: =IF('Hauling Fleet Management'!$AK250="","",'Hauling Fleet Management'!AQ250) -> 0 | H953: =IF('Hauling Fleet Management'!$AK250="","",'Hauling Fleet Management'!AR250) -> 0 | ... M953: =IF('Hauling Fleet Management'!$AK250="","",'Hauling Fleet Management'!AW250)
A954: =IF('Mining Eyes Analytics'!$AK13="","",'Mining Eyes Analytics'!AK13) -> Mining Eyes Analytics | B954: =IF('Mining Eyes Analytics'!$AK13="","",'Mining Eyes Analytics'!AL13) -> Apr - Jun 2026 | C954: =IF('Mining Eyes Analytics'!$AK13="","",'Mining Eyes Analytics'!AM13) -> Jan–Mar 2026 | D954: =IF('Mining Eyes Analytics'!$AK13="","",'Mining Eyes Analytics'!AN13) -> Camera and analytics setup | E954: =IF('Mining Eyes Analytics'!$AK13="","",'Mining Eyes Analytics'!AO13) | F954: =IF('Mining Eyes Analytics'!$AK13="","",'Mining Eyes Analytics'!AP13) -> Fase Camera and analytics setup pada periode Jan–Mar 2026 untuk Mining Eyes Analytics. | G954: =IF('Mining Eyes Analytics'!$AK13="","",'Mining Eyes Analytics'!AQ13) -> Deploy camera integration and basic inference flow; Stand up surveillance dashboard and alert feed; Define escalation owners and verification workflow | H954: =IF('Mining Eyes Analytics'!$AK13="","",'Mining Eyes Analytics'!AR13) -> 0 | ... M954: =IF('Mining Eyes Analytics'!$AK13="","",'Mining Eyes Analytics'!AW13)
A955: =IF('Mining Eyes Analytics'!$AK14="","",'Mining Eyes Analytics'!AK14) -> Mining Eyes Analytics | B955: =IF('Mining Eyes Analytics'!$AK14="","",'Mining Eyes Analytics'!AL14) -> Apr - Jun 2026 | C955: =IF('Mining Eyes Analytics'!$AK14="","",'Mining Eyes Analytics'!AM14) -> Jan–Mar 2026 | D955: =IF('Mining Eyes Analytics'!$AK14="","",'Mining Eyes Analytics'!AN14) -> Model and workflow improvement | E955: =IF('Mining Eyes Analytics'!$AK14="","",'Mining Eyes Analytics'!AO14) | F955: =IF('Mining Eyes Analytics'!$AK14="","",'Mining Eyes Analytics'!AP14) -> Fase Model and workflow improvement pada periode Apr–Jul 2026 untuk Mining Eyes Analytics. | G955: =IF('Mining Eyes Analytics'!$AK14="","",'Mining Eyes Analytics'!AQ14) -> Reduce false positives at priority use cases; Improve closure discipline and evidence linkage; Strengthen coverage in unstable network areas | H955: =IF('Mining Eyes Analytics'!$AK14="","",'Mining Eyes Analytics'!AR14) -> 0 | ... M955: =IF('Mining Eyes Analytics'!$AK14="","",'Mining Eyes Analytics'!AW14)
A956: =IF('Mining Eyes Analytics'!$AK15="","",'Mining Eyes Analytics'!AK15) -> Mining Eyes Analytics | B956: =IF('Mining Eyes Analytics'!$AK15="","",'Mining Eyes Analytics'!AL15) -> 0 | C956: =IF('Mining Eyes Analytics'!$AK15="","",'Mining Eyes Analytics'!AM15) -> 0 | D956: =IF('Mining Eyes Analytics'!$AK15="","",'Mining Eyes Analytics'!AN15) -> 0 | E956: =IF('Mining Eyes Analytics'!$AK15="","",'Mining Eyes Analytics'!AO15) | F956: =IF('Mining Eyes Analytics'!$AK15="","",'Mining Eyes Analytics'!AP15) -> 0 | G956: =IF('Mining Eyes Analytics'!$AK15="","",'Mining Eyes Analytics'!AQ15) -> 0 | H956: =IF('Mining Eyes Analytics'!$AK15="","",'Mining Eyes Analytics'!AR15) -> 0 | ... M956: =IF('Mining Eyes Analytics'!$AK15="","",'Mining Eyes Analytics'!AW15)
A957: =IF('Mining Eyes Analytics'!$AK16="","",'Mining Eyes Analytics'!AK16) -> Mining Eyes Analytics | B957: =IF('Mining Eyes Analytics'!$AK16="","",'Mining Eyes Analytics'!AL16) -> 0 | C957: =IF('Mining Eyes Analytics'!$AK16="","",'Mining Eyes Analytics'!AM16) -> 0 | D957: =IF('Mining Eyes Analytics'!$AK16="","",'Mining Eyes Analytics'!AN16) -> 0 | E957: =IF('Mining Eyes Analytics'!$AK16="","",'Mining Eyes Analytics'!AO16) | F957: =IF('Mining Eyes Analytics'!$AK16="","",'Mining Eyes Analytics'!AP16) -> 0 | G957: =IF('Mining Eyes Analytics'!$AK16="","",'Mining Eyes Analytics'!AQ16) -> 0 | H957: =IF('Mining Eyes Analytics'!$AK16="","",'Mining Eyes Analytics'!AR16) -> 0 | ... M957: =IF('Mining Eyes Analytics'!$AK16="","",'Mining Eyes Analytics'!AW16)
A958: =IF('Mining Eyes Analytics'!$AK17="","",'Mining Eyes Analytics'!AK17) -> Mining Eyes Analytics | B958: =IF('Mining Eyes Analytics'!$AK17="","",'Mining Eyes Analytics'!AL17) -> 0 | C958: =IF('Mining Eyes Analytics'!$AK17="","",'Mining Eyes Analytics'!AM17) -> 0 | D958: =IF('Mining Eyes Analytics'!$AK17="","",'Mining Eyes Analytics'!AN17) -> 0 | E958: =IF('Mining Eyes Analytics'!$AK17="","",'Mining Eyes Analytics'!AO17) | F958: =IF('Mining Eyes Analytics'!$AK17="","",'Mining Eyes Analytics'!AP17) -> 0 | G958: =IF('Mining Eyes Analytics'!$AK17="","",'Mining Eyes Analytics'!AQ17) -> 0 | H958: =IF('Mining Eyes Analytics'!$AK17="","",'Mining Eyes Analytics'!AR17) -> 0 | ... M958: =IF('Mining Eyes Analytics'!$AK17="","",'Mining Eyes Analytics'!AW17)
A959: =IF('Mining Eyes Analytics'!$AK18="","",'Mining Eyes Analytics'!AK18) -> Mining Eyes Analytics | B959: =IF('Mining Eyes Analytics'!$AK18="","",'Mining Eyes Analytics'!AL18) -> 0 | C959: =IF('Mining Eyes Analytics'!$AK18="","",'Mining Eyes Analytics'!AM18) -> 0 | D959: =IF('Mining Eyes Analytics'!$AK18="","",'Mining Eyes Analytics'!AN18) -> 0 | E959: =IF('Mining Eyes Analytics'!$AK18="","",'Mining Eyes Analytics'!AO18) | F959: =IF('Mining Eyes Analytics'!$AK18="","",'Mining Eyes Analytics'!AP18) -> 0 | G959: =IF('Mining Eyes Analytics'!$AK18="","",'Mining Eyes Analytics'!AQ18) -> 0 | H959: =IF('Mining Eyes Analytics'!$AK18="","",'Mining Eyes Analytics'!AR18) -> 0 | ... M959: =IF('Mining Eyes Analytics'!$AK18="","",'Mining Eyes Analytics'!AW18)
A960: =IF('Mining Eyes Analytics'!$AK19="","",'Mining Eyes Analytics'!AK19) -> Mining Eyes Analytics | B960: =IF('Mining Eyes Analytics'!$AK19="","",'Mining Eyes Analytics'!AL19) -> 0 | C960: =IF('Mining Eyes Analytics'!$AK19="","",'Mining Eyes Analytics'!AM19) -> 0 | D960: =IF('Mining Eyes Analytics'!$AK19="","",'Mining Eyes Analytics'!AN19) -> 0 | E960: =IF('Mining Eyes Analytics'!$AK19="","",'Mining Eyes Analytics'!AO19) | F960: =IF('Mining Eyes Analytics'!$AK19="","",'Mining Eyes Analytics'!AP19) -> 0 | G960: =IF('Mining Eyes Analytics'!$AK19="","",'Mining Eyes Analytics'!AQ19) -> 0 | H960: =IF('Mining Eyes Analytics'!$AK19="","",'Mining Eyes Analytics'!AR19) -> 0 | ... M960: =IF('Mining Eyes Analytics'!$AK19="","",'Mining Eyes Analytics'!AW19)
A961: =IF('Mining Eyes Analytics'!$AK20="","",'Mining Eyes Analytics'!AK20) -> Mining Eyes Analytics | B961: =IF('Mining Eyes Analytics'!$AK20="","",'Mining Eyes Analytics'!AL20) -> 0 | C961: =IF('Mining Eyes Analytics'!$AK20="","",'Mining Eyes Analytics'!AM20) -> 0 | D961: =IF('Mining Eyes Analytics'!$AK20="","",'Mining Eyes Analytics'!AN20) -> 0 | E961: =IF('Mining Eyes Analytics'!$AK20="","",'Mining Eyes Analytics'!AO20) | F961: =IF('Mining Eyes Analytics'!$AK20="","",'Mining Eyes Analytics'!AP20) -> 0 | G961: =IF('Mining Eyes Analytics'!$AK20="","",'Mining Eyes Analytics'!AQ20) -> 0 | H961: =IF('Mining Eyes Analytics'!$AK20="","",'Mining Eyes Analytics'!AR20) -> 0 | ... M961: =IF('Mining Eyes Analytics'!$AK20="","",'Mining Eyes Analytics'!AW20)
A962: =IF('Mining Eyes Analytics'!$AK21="","",'Mining Eyes Analytics'!AK21) -> Mining Eyes Analytics | B962: =IF('Mining Eyes Analytics'!$AK21="","",'Mining Eyes Analytics'!AL21) -> 0 | C962: =IF('Mining Eyes Analytics'!$AK21="","",'Mining Eyes Analytics'!AM21) -> 0 | D962: =IF('Mining Eyes Analytics'!$AK21="","",'Mining Eyes Analytics'!AN21) -> 0 | E962: =IF('Mining Eyes Analytics'!$AK21="","",'Mining Eyes Analytics'!AO21) | F962: =IF('Mining Eyes Analytics'!$AK21="","",'Mining Eyes Analytics'!AP21) -> 0 | G962: =IF('Mining Eyes Analytics'!$AK21="","",'Mining Eyes Analytics'!AQ21) -> 0 | H962: =IF('Mining Eyes Analytics'!$AK21="","",'Mining Eyes Analytics'!AR21) -> 0 | ... M962: =IF('Mining Eyes Analytics'!$AK21="","",'Mining Eyes Analytics'!AW21)
A963: =IF('Mining Eyes Analytics'!$AK22="","",'Mining Eyes Analytics'!AK22) -> Mining Eyes Analytics | B963: =IF('Mining Eyes Analytics'!$AK22="","",'Mining Eyes Analytics'!AL22) -> 0 | C963: =IF('Mining Eyes Analytics'!$AK22="","",'Mining Eyes Analytics'!AM22) -> 0 | D963: =IF('Mining Eyes Analytics'!$AK22="","",'Mining Eyes Analytics'!AN22) -> 0 | E963: =IF('Mining Eyes Analytics'!$AK22="","",'Mining Eyes Analytics'!AO22) | F963: =IF('Mining Eyes Analytics'!$AK22="","",'Mining Eyes Analytics'!AP22) -> 0 | G963: =IF('Mining Eyes Analytics'!$AK22="","",'Mining Eyes Analytics'!AQ22) -> 0 | H963: =IF('Mining Eyes Analytics'!$AK22="","",'Mining Eyes Analytics'!AR22) -> 0 | ... M963: =IF('Mining Eyes Analytics'!$AK22="","",'Mining Eyes Analytics'!AW22)
A964: =IF('Mining Eyes Analytics'!$AK23="","",'Mining Eyes Analytics'!AK23) -> Mining Eyes Analytics | B964: =IF('Mining Eyes Analytics'!$AK23="","",'Mining Eyes Analytics'!AL23) -> 0 | C964: =IF('Mining Eyes Analytics'!$AK23="","",'Mining Eyes Analytics'!AM23) -> 0 | D964: =IF('Mining Eyes Analytics'!$AK23="","",'Mining Eyes Analytics'!AN23) -> 0 | E964: =IF('Mining Eyes Analytics'!$AK23="","",'Mining Eyes Analytics'!AO23) | F964: =IF('Mining Eyes Analytics'!$AK23="","",'Mining Eyes Analytics'!AP23) -> 0 | G964: =IF('Mining Eyes Analytics'!$AK23="","",'Mining Eyes Analytics'!AQ23) -> 0 | H964: =IF('Mining Eyes Analytics'!$AK23="","",'Mining Eyes Analytics'!AR23) -> 0 | ... M964: =IF('Mining Eyes Analytics'!$AK23="","",'Mining Eyes Analytics'!AW23)
A965: =IF('Mining Eyes Analytics'!$AK24="","",'Mining Eyes Analytics'!AK24) -> Mining Eyes Analytics | B965: =IF('Mining Eyes Analytics'!$AK24="","",'Mining Eyes Analytics'!AL24) -> 0 | C965: =IF('Mining Eyes Analytics'!$AK24="","",'Mining Eyes Analytics'!AM24) -> 0 | D965: =IF('Mining Eyes Analytics'!$AK24="","",'Mining Eyes Analytics'!AN24) -> 0 | E965: =IF('Mining Eyes Analytics'!$AK24="","",'Mining Eyes Analytics'!AO24) | F965: =IF('Mining Eyes Analytics'!$AK24="","",'Mining Eyes Analytics'!AP24) -> 0 | G965: =IF('Mining Eyes Analytics'!$AK24="","",'Mining Eyes Analytics'!AQ24) -> 0 | H965: =IF('Mining Eyes Analytics'!$AK24="","",'Mining Eyes Analytics'!AR24) -> 0 | ... M965: =IF('Mining Eyes Analytics'!$AK24="","",'Mining Eyes Analytics'!AW24)
... A1191: =IF('Mining Eyes Analytics'!$AK250="","",'Mining Eyes Analytics'!AK250) -> Mining Eyes Analytics | B1191: =IF('Mining Eyes Analytics'!$AK250="","",'Mining Eyes Analytics'!AL250) -> 0 | C1191: =IF('Mining Eyes Analytics'!$AK250="","",'Mining Eyes Analytics'!AM250) -> 0 | D1191: =IF('Mining Eyes Analytics'!$AK250="","",'Mining Eyes Analytics'!AN250) -> 0 | E1191: =IF('Mining Eyes Analytics'!$AK250="","",'Mining Eyes Analytics'!AO250) | F1191: =IF('Mining Eyes Analytics'!$AK250="","",'Mining Eyes Analytics'!AP250) -> 0 | G1191: =IF('Mining Eyes Analytics'!$AK250="","",'Mining Eyes Analytics'!AQ250) -> 0 | H1191: =IF('Mining Eyes Analytics'!$AK250="","",'Mining Eyes Analytics'!AR250) -> 0 | ... M1191: =IF('Mining Eyes Analytics'!$AK250="","",'Mining Eyes Analytics'!AW250)
A1192: =IF('Remote Dozer'!$AK13="","",'Remote Dozer'!AK13) -> Remote Dozer | B1192: =IF('Remote Dozer'!$AK13="","",'Remote Dozer'!AL13) -> Apr - Jun 2026 | C1192: =IF('Remote Dozer'!$AK13="","",'Remote Dozer'!AM13) -> Jan - Mar 2026 | D1192: =IF('Remote Dozer'!$AK13="","",'Remote Dozer'!AN13) -> Remote system setup | E1192: =IF('Remote Dozer'!$AK13="","",'Remote Dozer'!AO13) -> Done | F1192: =IF('Remote Dozer'!$AK13="","",'Remote Dozer'!AP13) -> Fase Remote system setup pada periode Jan–Mar 2026 untuk Remote Dozer. | G1192: =IF('Remote Dozer'!$AK13="","",'Remote Dozer'!AQ13) -> Complete network and control station setup; Define remote zone boundary and procedure | H1192: =IF('Remote Dozer'!$AK13="","",'Remote Dozer'!AR13) -> 0 | ... M1192: =IF('Remote Dozer'!$AK13="","",'Remote Dozer'!AW13) -> 1
A1193: =IF('Remote Dozer'!$AK14="","",'Remote Dozer'!AK14) -> Remote Dozer | B1193: =IF('Remote Dozer'!$AK14="","",'Remote Dozer'!AL14) -> Apr - Jun 2026 | C1193: =IF('Remote Dozer'!$AK14="","",'Remote Dozer'!AM14) -> Apr - Jun 2026 | D1193: =IF('Remote Dozer'!$AK14="","",'Remote Dozer'!AN14) -> Pilot run and economic proof | E1193: =IF('Remote Dozer'!$AK14="","",'Remote Dozer'!AO14) -> Progress | F1193: =IF('Remote Dozer'!$AK14="","",'Remote Dozer'!AP14) -> Fase Pilot run and economic proof pada periode Apr–Aug 2026 untuk Remote Dozer. | G1193: =IF('Remote Dozer'!$AK14="","",'Remote Dozer'!AQ14) -> Track dozing distance reduction and remote availability; Refresh payback and ROI assumption model | H1193: =IF('Remote Dozer'!$AK14="","",'Remote Dozer'!AR14) -> 0 | ... M1193: =IF('Remote Dozer'!$AK14="","",'Remote Dozer'!AW14) -> 0.5
A1194: =IF('Remote Dozer'!$AK15="","",'Remote Dozer'!AK15) -> Remote Dozer | B1194: =IF('Remote Dozer'!$AK15="","",'Remote Dozer'!AL15) -> 0 | C1194: =IF('Remote Dozer'!$AK15="","",'Remote Dozer'!AM15) -> 0 | D1194: =IF('Remote Dozer'!$AK15="","",'Remote Dozer'!AN15) -> 0 | E1194: =IF('Remote Dozer'!$AK15="","",'Remote Dozer'!AO15) | F1194: =IF('Remote Dozer'!$AK15="","",'Remote Dozer'!AP15) -> 0 | G1194: =IF('Remote Dozer'!$AK15="","",'Remote Dozer'!AQ15) -> 0 | H1194: =IF('Remote Dozer'!$AK15="","",'Remote Dozer'!AR15) -> 0 | ... M1194: =IF('Remote Dozer'!$AK15="","",'Remote Dozer'!AW15)
A1195: =IF('Remote Dozer'!$AK16="","",'Remote Dozer'!AK16) -> Remote Dozer | B1195: =IF('Remote Dozer'!$AK16="","",'Remote Dozer'!AL16) -> 0 | C1195: =IF('Remote Dozer'!$AK16="","",'Remote Dozer'!AM16) -> 0 | D1195: =IF('Remote Dozer'!$AK16="","",'Remote Dozer'!AN16) -> 0 | E1195: =IF('Remote Dozer'!$AK16="","",'Remote Dozer'!AO16) | F1195: =IF('Remote Dozer'!$AK16="","",'Remote Dozer'!AP16) -> 0 | G1195: =IF('Remote Dozer'!$AK16="","",'Remote Dozer'!AQ16) -> 0 | H1195: =IF('Remote Dozer'!$AK16="","",'Remote Dozer'!AR16) -> 0 | ... M1195: =IF('Remote Dozer'!$AK16="","",'Remote Dozer'!AW16)
A1196: =IF('Remote Dozer'!$AK17="","",'Remote Dozer'!AK17) -> Remote Dozer | B1196: =IF('Remote Dozer'!$AK17="","",'Remote Dozer'!AL17) -> 0 | C1196: =IF('Remote Dozer'!$AK17="","",'Remote Dozer'!AM17) -> 0 | D1196: =IF('Remote Dozer'!$AK17="","",'Remote Dozer'!AN17) -> 0 | E1196: =IF('Remote Dozer'!$AK17="","",'Remote Dozer'!AO17) | F1196: =IF('Remote Dozer'!$AK17="","",'Remote Dozer'!AP17) -> 0 | G1196: =IF('Remote Dozer'!$AK17="","",'Remote Dozer'!AQ17) -> 0 | H1196: =IF('Remote Dozer'!$AK17="","",'Remote Dozer'!AR17) -> 0 | ... M1196: =IF('Remote Dozer'!$AK17="","",'Remote Dozer'!AW17)
A1197: =IF('Remote Dozer'!$AK18="","",'Remote Dozer'!AK18) -> Remote Dozer | B1197: =IF('Remote Dozer'!$AK18="","",'Remote Dozer'!AL18) -> 0 | C1197: =IF('Remote Dozer'!$AK18="","",'Remote Dozer'!AM18) -> 0 | D1197: =IF('Remote Dozer'!$AK18="","",'Remote Dozer'!AN18) -> 0 | E1197: =IF('Remote Dozer'!$AK18="","",'Remote Dozer'!AO18) | F1197: =IF('Remote Dozer'!$AK18="","",'Remote Dozer'!AP18) -> 0 | G1197: =IF('Remote Dozer'!$AK18="","",'Remote Dozer'!AQ18) -> 0 | H1197: =IF('Remote Dozer'!$AK18="","",'Remote Dozer'!AR18) -> 0 | ... M1197: =IF('Remote Dozer'!$AK18="","",'Remote Dozer'!AW18)
A1198: =IF('Remote Dozer'!$AK19="","",'Remote Dozer'!AK19) -> Remote Dozer | B1198: =IF('Remote Dozer'!$AK19="","",'Remote Dozer'!AL19) -> 0 | C1198: =IF('Remote Dozer'!$AK19="","",'Remote Dozer'!AM19) -> 0 | D1198: =IF('Remote Dozer'!$AK19="","",'Remote Dozer'!AN19) -> 0 | E1198: =IF('Remote Dozer'!$AK19="","",'Remote Dozer'!AO19) | F1198: =IF('Remote Dozer'!$AK19="","",'Remote Dozer'!AP19) -> 0 | G1198: =IF('Remote Dozer'!$AK19="","",'Remote Dozer'!AQ19) -> 0 | H1198: =IF('Remote Dozer'!$AK19="","",'Remote Dozer'!AR19) -> 0 | ... M1198: =IF('Remote Dozer'!$AK19="","",'Remote Dozer'!AW19)
A1199: =IF('Remote Dozer'!$AK20="","",'Remote Dozer'!AK20) -> Remote Dozer | B1199: =IF('Remote Dozer'!$AK20="","",'Remote Dozer'!AL20) -> 0 | C1199: =IF('Remote Dozer'!$AK20="","",'Remote Dozer'!AM20) -> 0 | D1199: =IF('Remote Dozer'!$AK20="","",'Remote Dozer'!AN20) -> 0 | E1199: =IF('Remote Dozer'!$AK20="","",'Remote Dozer'!AO20) | F1199: =IF('Remote Dozer'!$AK20="","",'Remote Dozer'!AP20) -> 0 | G1199: =IF('Remote Dozer'!$AK20="","",'Remote Dozer'!AQ20) -> 0 | H1199: =IF('Remote Dozer'!$AK20="","",'Remote Dozer'!AR20) -> 0 | ... M1199: =IF('Remote Dozer'!$AK20="","",'Remote Dozer'!AW20)
A1200: =IF('Remote Dozer'!$AK21="","",'Remote Dozer'!AK21) -> Remote Dozer | B1200: =IF('Remote Dozer'!$AK21="","",'Remote Dozer'!AL21) -> 0 | C1200: =IF('Remote Dozer'!$AK21="","",'Remote Dozer'!AM21) -> 0 | D1200: =IF('Remote Dozer'!$AK21="","",'Remote Dozer'!AN21) -> 0 | E1200: =IF('Remote Dozer'!$AK21="","",'Remote Dozer'!AO21) | F1200: =IF('Remote Dozer'!$AK21="","",'Remote Dozer'!AP21) -> 0 | G1200: =IF('Remote Dozer'!$AK21="","",'Remote Dozer'!AQ21) -> 0 | H1200: =IF('Remote Dozer'!$AK21="","",'Remote Dozer'!AR21) -> 0 | ... M1200: =IF('Remote Dozer'!$AK21="","",'Remote Dozer'!AW21)
A1201: =IF('Remote Dozer'!$AK22="","",'Remote Dozer'!AK22) -> Remote Dozer | B1201: =IF('Remote Dozer'!$AK22="","",'Remote Dozer'!AL22) -> 0 | C1201: =IF('Remote Dozer'!$AK22="","",'Remote Dozer'!AM22) -> 0 | D1201: =IF('Remote Dozer'!$AK22="","",'Remote Dozer'!AN22) -> 0 | E1201: =IF('Remote Dozer'!$AK22="","",'Remote Dozer'!AO22) | F1201: =IF('Remote Dozer'!$AK22="","",'Remote Dozer'!AP22) -> 0 | G1201: =IF('Remote Dozer'!$AK22="","",'Remote Dozer'!AQ22) -> 0 | H1201: =IF('Remote Dozer'!$AK22="","",'Remote Dozer'!AR22) -> 0 | ... M1201: =IF('Remote Dozer'!$AK22="","",'Remote Dozer'!AW22)
A1202: =IF('Remote Dozer'!$AK23="","",'Remote Dozer'!AK23) -> Remote Dozer | B1202: =IF('Remote Dozer'!$AK23="","",'Remote Dozer'!AL23) -> 0 | C1202: =IF('Remote Dozer'!$AK23="","",'Remote Dozer'!AM23) -> 0 | D1202: =IF('Remote Dozer'!$AK23="","",'Remote Dozer'!AN23) -> 0 | E1202: =IF('Remote Dozer'!$AK23="","",'Remote Dozer'!AO23) | F1202: =IF('Remote Dozer'!$AK23="","",'Remote Dozer'!AP23) -> 0 | G1202: =IF('Remote Dozer'!$AK23="","",'Remote Dozer'!AQ23) -> 0 | H1202: =IF('Remote Dozer'!$AK23="","",'Remote Dozer'!AR23) -> 0 | ... M1202: =IF('Remote Dozer'!$AK23="","",'Remote Dozer'!AW23)
A1203: =IF('Remote Dozer'!$AK24="","",'Remote Dozer'!AK24) -> Remote Dozer | B1203: =IF('Remote Dozer'!$AK24="","",'Remote Dozer'!AL24) -> 0 | C1203: =IF('Remote Dozer'!$AK24="","",'Remote Dozer'!AM24) -> 0 | D1203: =IF('Remote Dozer'!$AK24="","",'Remote Dozer'!AN24) -> 0 | E1203: =IF('Remote Dozer'!$AK24="","",'Remote Dozer'!AO24) | F1203: =IF('Remote Dozer'!$AK24="","",'Remote Dozer'!AP24) -> 0 | G1203: =IF('Remote Dozer'!$AK24="","",'Remote Dozer'!AQ24) -> 0 | H1203: =IF('Remote Dozer'!$AK24="","",'Remote Dozer'!AR24) -> 0 | ... M1203: =IF('Remote Dozer'!$AK24="","",'Remote Dozer'!AW24)
... A1429: =IF('Remote Dozer'!$AK250="","",'Remote Dozer'!AK250) -> Remote Dozer | B1429: =IF('Remote Dozer'!$AK250="","",'Remote Dozer'!AL250) -> 0 | C1429: =IF('Remote Dozer'!$AK250="","",'Remote Dozer'!AM250) -> 0 | D1429: =IF('Remote Dozer'!$AK250="","",'Remote Dozer'!AN250) -> 0 | E1429: =IF('Remote Dozer'!$AK250="","",'Remote Dozer'!AO250) | F1429: =IF('Remote Dozer'!$AK250="","",'Remote Dozer'!AP250) -> 0 | G1429: =IF('Remote Dozer'!$AK250="","",'Remote Dozer'!AQ250) -> 0 | H1429: =IF('Remote Dozer'!$AK250="","",'Remote Dozer'!AR250) -> 0 | ... M1429: =IF('Remote Dozer'!$AK250="","",'Remote Dozer'!AW250)

Sheet Timeline_Tasks
A1: Project | B1: Roadmap Period | C1: Phase | D1: Task | E1: Original Owner | F1: Original Status | G1: PIC Actual Owner | H1: PIC Start Date | I1: PIC Actual % Input | J1: PIC Progress Note | K1: Evidence Link | L1: Target Date | M1: Dependency / Blocker | N1: Task Progress % (Normalized)
A2: =IF('Arcas HD'!$AY13="","",'Arcas HD'!AY13) -> Arcas HD | B2: =IF('Arcas HD'!$AY13="","",'Arcas HD'!AZ13) -> Jan - Mar 2026 | C2: =IF('Arcas HD'!$AY13="","",'Arcas HD'!BA13) -> Infrastructure & technical proving | D2: =IF('Arcas HD'!$AY13="","",'Arcas HD'!BB13) -> Validate network backbone and ROC connection stability | E2: =IF('Arcas HD'!$AY13="","",'Arcas HD'!BC13) -> IT / Automation | F2: =IF('Arcas HD'!$AY13="","",'Arcas HD'!BD13) -> Done | G2: =IF('Arcas HD'!$AY13="","",'Arcas HD'!BE13) -> Poltek | H2: =IF('Arcas HD'!$AY13="","",'Arcas HD'!BF13) -> 46106 | ... N2: =IF('Arcas HD'!$AY13="","",'Arcas HD'!BL13) -> 60`%
A3: =IF('Arcas HD'!$AY14="","",'Arcas HD'!AY14) -> Arcas HD | B3: =IF('Arcas HD'!$AY14="","",'Arcas HD'!AZ14) -> Jan - Mar 2026 | C3: =IF('Arcas HD'!$AY14="","",'Arcas HD'!BA14) -> Infrastructure & technical proving | D3: =IF('Arcas HD'!$AY14="","",'Arcas HD'!BB14) -> Complete initial end-to-end system integration test | E3: =IF('Arcas HD'!$AY14="","",'Arcas HD'!BC14) -> Vendor + Ops | F3: =IF('Arcas HD'!$AY14="","",'Arcas HD'!BD14) -> Done | G3: =IF('Arcas HD'!$AY14="","",'Arcas HD'!BE14) -> Poltek | H3: =IF('Arcas HD'!$AY14="","",'Arcas HD'!BF14) -> 46132 | ... N3: =IF('Arcas HD'!$AY14="","",'Arcas HD'!BL14) -> 0.6
A4: =IF('Arcas HD'!$AY15="","",'Arcas HD'!AY15) -> Arcas HD | B4: =IF('Arcas HD'!$AY15="","",'Arcas HD'!AZ15) -> Apr - Jun 2026 | C4: =IF('Arcas HD'!$AY15="","",'Arcas HD'!BA15) -> Pilot operation & safety proving | D4: =IF('Arcas HD'!$AY15="","",'Arcas HD'!BB15) -> Run supervised multi-shift pilot scenario | E4: =IF('Arcas HD'!$AY15="","",'Arcas HD'!BC15) -> Ops | F4: =IF('Arcas HD'!$AY15="","",'Arcas HD'!BD15) -> Progress | G4: =IF('Arcas HD'!$AY15="","",'Arcas HD'!BE15) -> Poltek | H4: =IF('Arcas HD'!$AY15="","",'Arcas HD'!BF15) -> 0 | ... N4: =IF('Arcas HD'!$AY15="","",'Arcas HD'!BL15) -> 0.5
A5: =IF('Arcas HD'!$AY16="","",'Arcas HD'!AY16) -> Arcas HD | B5: =IF('Arcas HD'!$AY16="","",'Arcas HD'!AZ16) -> Apr - Jun 2026 | C5: =IF('Arcas HD'!$AY16="","",'Arcas HD'!BA16) -> Pilot operation & safety proving | D5: =IF('Arcas HD'!$AY16="","",'Arcas HD'!BB16) -> Prepare Gate 3 evidence pack for approval | E5: =IF('Arcas HD'!$AY16="","",'Arcas HD'!BC16) -> Project Team | F5: =IF('Arcas HD'!$AY16="","",'Arcas HD'!BD16) -> Plan | G5: =IF('Arcas HD'!$AY16="","",'Arcas HD'!BE16) -> Poltek | H5: =IF('Arcas HD'!$AY16="","",'Arcas HD'!BF16) -> 0 | ... N5: =IF('Arcas HD'!$AY16="","",'Arcas HD'!BL16) -> 0
A6: =IF('Arcas HD'!$AY17="","",'Arcas HD'!AY17) -> Arcas HD | B6: =IF('Arcas HD'!$AY17="","",'Arcas HD'!AZ17) -> 0 | C6: =IF('Arcas HD'!$AY17="","",'Arcas HD'!BA17) -> 0 | D6: =IF('Arcas HD'!$AY17="","",'Arcas HD'!BB17) -> 0 | E6: =IF('Arcas HD'!$AY17="","",'Arcas HD'!BC17) -> 0 | F6: =IF('Arcas HD'!$AY17="","",'Arcas HD'!BD17) -> 0 | G6: =IF('Arcas HD'!$AY17="","",'Arcas HD'!BE17) -> 0 | H6: =IF('Arcas HD'!$AY17="","",'Arcas HD'!BF17) -> 0 | ... N6: =IF('Arcas HD'!$AY17="","",'Arcas HD'!BL17)
A7: =IF('Arcas HD'!$AY18="","",'Arcas HD'!AY18) -> Arcas HD | B7: =IF('Arcas HD'!$AY18="","",'Arcas HD'!AZ18) -> 0 | C7: =IF('Arcas HD'!$AY18="","",'Arcas HD'!BA18) -> 0 | D7: =IF('Arcas HD'!$AY18="","",'Arcas HD'!BB18) -> 0 | E7: =IF('Arcas HD'!$AY18="","",'Arcas HD'!BC18) -> 0 | F7: =IF('Arcas HD'!$AY18="","",'Arcas HD'!BD18) -> 0 | G7: =IF('Arcas HD'!$AY18="","",'Arcas HD'!BE18) -> 0 | H7: =IF('Arcas HD'!$AY18="","",'Arcas HD'!BF18) -> 0 | ... N7: =IF('Arcas HD'!$AY18="","",'Arcas HD'!BL18)
A8: =IF('Arcas HD'!$AY19="","",'Arcas HD'!AY19) -> Arcas HD | B8: =IF('Arcas HD'!$AY19="","",'Arcas HD'!AZ19) -> 0 | C8: =IF('Arcas HD'!$AY19="","",'Arcas HD'!BA19) -> 0 | D8: =IF('Arcas HD'!$AY19="","",'Arcas HD'!BB19) -> 0 | E8: =IF('Arcas HD'!$AY19="","",'Arcas HD'!BC19) -> 0 | F8: =IF('Arcas HD'!$AY19="","",'Arcas HD'!BD19) -> 0 | G8: =IF('Arcas HD'!$AY19="","",'Arcas HD'!BE19) -> 0 | H8: =IF('Arcas HD'!$AY19="","",'Arcas HD'!BF19) -> 0 | ... N8: =IF('Arcas HD'!$AY19="","",'Arcas HD'!BL19)
A9: =IF('Arcas HD'!$AY20="","",'Arcas HD'!AY20) -> Arcas HD | B9: =IF('Arcas HD'!$AY20="","",'Arcas HD'!AZ20) -> 0 | C9: =IF('Arcas HD'!$AY20="","",'Arcas HD'!BA20) -> 0 | D9: =IF('Arcas HD'!$AY20="","",'Arcas HD'!BB20) -> 0 | E9: =IF('Arcas HD'!$AY20="","",'Arcas HD'!BC20) -> 0 | F9: =IF('Arcas HD'!$AY20="","",'Arcas HD'!BD20) -> 0 | G9: =IF('Arcas HD'!$AY20="","",'Arcas HD'!BE20) -> 0 | H9: =IF('Arcas HD'!$AY20="","",'Arcas HD'!BF20) -> 0 | ... N9: =IF('Arcas HD'!$AY20="","",'Arcas HD'!BL20)
A10: =IF('Arcas HD'!$AY21="","",'Arcas HD'!AY21) -> Arcas HD | B10: =IF('Arcas HD'!$AY21="","",'Arcas HD'!AZ21) -> 0 | C10: =IF('Arcas HD'!$AY21="","",'Arcas HD'!BA21) -> 0 | D10: =IF('Arcas HD'!$AY21="","",'Arcas HD'!BB21) -> 0 | E10: =IF('Arcas HD'!$AY21="","",'Arcas HD'!BC21) -> 0 | F10: =IF('Arcas HD'!$AY21="","",'Arcas HD'!BD21) -> 0 | G10: =IF('Arcas HD'!$AY21="","",'Arcas HD'!BE21) -> 0 | H10: =IF('Arcas HD'!$AY21="","",'Arcas HD'!BF21) -> 0 | ... N10: =IF('Arcas HD'!$AY21="","",'Arcas HD'!BL21)
A11: =IF('Arcas HD'!$AY22="","",'Arcas HD'!AY22) -> Arcas HD | B11: =IF('Arcas HD'!$AY22="","",'Arcas HD'!AZ22) -> 0 | C11: =IF('Arcas HD'!$AY22="","",'Arcas HD'!BA22) -> 0 | D11: =IF('Arcas HD'!$AY22="","",'Arcas HD'!BB22) -> 0 | E11: =IF('Arcas HD'!$AY22="","",'Arcas HD'!BC22) -> 0 | F11: =IF('Arcas HD'!$AY22="","",'Arcas HD'!BD22) -> 0 | G11: =IF('Arcas HD'!$AY22="","",'Arcas HD'!BE22) -> 0 | H11: =IF('Arcas HD'!$AY22="","",'Arcas HD'!BF22) -> 0 | ... N11: =IF('Arcas HD'!$AY22="","",'Arcas HD'!BL22)
A12: =IF('Arcas HD'!$AY23="","",'Arcas HD'!AY23) -> Arcas HD | B12: =IF('Arcas HD'!$AY23="","",'Arcas HD'!AZ23) -> 0 | C12: =IF('Arcas HD'!$AY23="","",'Arcas HD'!BA23) -> 0 | D12: =IF('Arcas HD'!$AY23="","",'Arcas HD'!BB23) -> 0 | E12: =IF('Arcas HD'!$AY23="","",'Arcas HD'!BC23) -> 0 | F12: =IF('Arcas HD'!$AY23="","",'Arcas HD'!BD23) -> 0 | G12: =IF('Arcas HD'!$AY23="","",'Arcas HD'!BE23) -> 0 | H12: =IF('Arcas HD'!$AY23="","",'Arcas HD'!BF23) -> 0 | ... N12: =IF('Arcas HD'!$AY23="","",'Arcas HD'!BL23)
A13: =IF('Arcas HD'!$AY24="","",'Arcas HD'!AY24) -> Arcas HD | B13: =IF('Arcas HD'!$AY24="","",'Arcas HD'!AZ24) -> 0 | C13: =IF('Arcas HD'!$AY24="","",'Arcas HD'!BA24) -> 0 | D13: =IF('Arcas HD'!$AY24="","",'Arcas HD'!BB24) -> 0 | E13: =IF('Arcas HD'!$AY24="","",'Arcas HD'!BC24) -> 0 | F13: =IF('Arcas HD'!$AY24="","",'Arcas HD'!BD24) -> 0 | G13: =IF('Arcas HD'!$AY24="","",'Arcas HD'!BE24) -> 0 | H13: =IF('Arcas HD'!$AY24="","",'Arcas HD'!BF24) -> 0 | ... N13: =IF('Arcas HD'!$AY24="","",'Arcas HD'!BL24)
... A239: =IF('Arcas HD'!$AY250="","",'Arcas HD'!AY250) -> Arcas HD | B239: =IF('Arcas HD'!$AY250="","",'Arcas HD'!AZ250) -> 0 | C239: =IF('Arcas HD'!$AY250="","",'Arcas HD'!BA250) -> 0 | D239: =IF('Arcas HD'!$AY250="","",'Arcas HD'!BB250) -> 0 | E239: =IF('Arcas HD'!$AY250="","",'Arcas HD'!BC250) -> 0 | F239: =IF('Arcas HD'!$AY250="","",'Arcas HD'!BD250) -> 0 | G239: =IF('Arcas HD'!$AY250="","",'Arcas HD'!BE250) -> 0 | H239: =IF('Arcas HD'!$AY250="","",'Arcas HD'!BF250) -> 0 | ... N239: =IF('Arcas HD'!$AY250="","",'Arcas HD'!BL250)
A240: =IF('MGD PC'!$AY13="","",'MGD PC'!AY13) -> MGD PC | B240: =IF('MGD PC'!$AY13="","",'MGD PC'!AZ13) -> Jan–Mar 2026 | C240: =IF('MGD PC'!$AY13="","",'MGD PC'!BA13) -> Configuration & setup | D240: =IF('MGD PC'!$AY13="","",'MGD PC'!BB13) -> Install positioning and guidance configuration | E240: =IF('MGD PC'!$AY13="","",'MGD PC'!BC13) -> Vendor | F240: =IF('MGD PC'!$AY13="","",'MGD PC'!BD13) -> Done | G240: =IF('MGD PC'!$AY13="","",'MGD PC'!BE13) -> 0 | H240: =IF('MGD PC'!$AY13="","",'MGD PC'!BF13) -> 0 | ... N240: =IF('MGD PC'!$AY13="","",'MGD PC'!BL13) -> 1
A241: =IF('MGD PC'!$AY14="","",'MGD PC'!AY14) -> MGD PC | B241: =IF('MGD PC'!$AY14="","",'MGD PC'!AZ14) -> Jan–Mar 2026 | C241: =IF('MGD PC'!$AY14="","",'MGD PC'!BA14) -> Configuration & setup | D241: =IF('MGD PC'!$AY14="","",'MGD PC'!BB14) -> Validate data logging and field test protocol | E241: =IF('MGD PC'!$AY14="","",'MGD PC'!BC14) -> Data Team | F241: =IF('MGD PC'!$AY14="","",'MGD PC'!BD14) -> Done | G241: =IF('MGD PC'!$AY14="","",'MGD PC'!BE14) -> 0 | H241: =IF('MGD PC'!$AY14="","",'MGD PC'!BF14) -> 0 | ... N241: =IF('MGD PC'!$AY14="","",'MGD PC'!BL14) -> 0.2
A242: =IF('MGD PC'!$AY15="","",'MGD PC'!AY15) -> MGD PC | B242: =IF('MGD PC'!$AY15="","",'MGD PC'!AZ15) -> Jan–Mar 2026 | C242: =IF('MGD PC'!$AY15="","",'MGD PC'!BA15) -> Configuration & setup | D242: =IF('MGD PC'!$AY15="","",'MGD PC'!BB15) -> Train pilot supervisors on assisted workflow | E242: =IF('MGD PC'!$AY15="","",'MGD PC'!BC15) -> Ops | F242: =IF('MGD PC'!$AY15="","",'MGD PC'!BD15) -> Done | G242: =IF('MGD PC'!$AY15="","",'MGD PC'!BE15) -> 0 | H242: =IF('MGD PC'!$AY15="","",'MGD PC'!BF15) -> 0 | ... N242: =IF('MGD PC'!$AY15="","",'MGD PC'!BL15) -> 1
A243: =IF('MGD PC'!$AY16="","",'MGD PC'!AY16) -> MGD PC | B243: =IF('MGD PC'!$AY16="","",'MGD PC'!AZ16) -> Jan–Mar 2026 | C243: =IF('MGD PC'!$AY16="","",'MGD PC'!BA16) -> Pilot proving | D243: =IF('MGD PC'!$AY16="","",'MGD PC'!BB16) -> Improve guidance accuracy at variable work fronts | E243: =IF('MGD PC'!$AY16="","",'MGD PC'!BC16) -> Vendor + Ops | F243: =IF('MGD PC'!$AY16="","",'MGD PC'!BD16) -> Progress | G243: =IF('MGD PC'!$AY16="","",'MGD PC'!BE16) -> 0 | H243: =IF('MGD PC'!$AY16="","",'MGD PC'!BF16) -> 0 | ... N243: =IF('MGD PC'!$AY16="","",'MGD PC'!BL16) -> 0.5
A244: =IF('MGD PC'!$AY17="","",'MGD PC'!AY17) -> MGD PC | B244: =IF('MGD PC'!$AY17="","",'MGD PC'!AZ17) -> Jan–Mar 2026 | C244: =IF('MGD PC'!$AY17="","",'MGD PC'!BA17) -> Pilot proving | D244: =IF('MGD PC'!$AY17="","",'MGD PC'!BB17) -> Monitor user adoption and coaching needs | E244: =IF('MGD PC'!$AY17="","",'MGD PC'!BC17) -> Supervisor | F244: =IF('MGD PC'!$AY17="","",'MGD PC'!BD17) -> Progress | G244: =IF('MGD PC'!$AY17="","",'MGD PC'!BE17) -> 0 | H244: =IF('MGD PC'!$AY17="","",'MGD PC'!BF17) -> 0 | ... N244: =IF('MGD PC'!$AY17="","",'MGD PC'!BL17) -> 0.5
A245: =IF('MGD PC'!$AY18="","",'MGD PC'!AY18) -> MGD PC | B245: =IF('MGD PC'!$AY18="","",'MGD PC'!AZ18) -> Jan–Mar 2026 | C245: =IF('MGD PC'!$AY18="","",'MGD PC'!BA18) -> Pilot proving | D245: =IF('MGD PC'!$AY18="","",'MGD PC'!BB18) -> Review rework reduction evidence by shift | E245: =IF('MGD PC'!$AY18="","",'MGD PC'!BC18) -> Project Analyst | F245: =IF('MGD PC'!$AY18="","",'MGD PC'!BD18) -> Plan | G245: =IF('MGD PC'!$AY18="","",'MGD PC'!BE18) -> 0 | H245: =IF('MGD PC'!$AY18="","",'MGD PC'!BF18) -> 0 | ... N245: =IF('MGD PC'!$AY18="","",'MGD PC'!BL18) -> 0
A246: =IF('MGD PC'!$AY19="","",'MGD PC'!AY19) -> MGD PC | B246: =IF('MGD PC'!$AY19="","",'MGD PC'!AZ19) -> 0 | C246: =IF('MGD PC'!$AY19="","",'MGD PC'!BA19) -> 0 | D246: =IF('MGD PC'!$AY19="","",'MGD PC'!BB19) -> 0 | E246: =IF('MGD PC'!$AY19="","",'MGD PC'!BC19) -> 0 | F246: =IF('MGD PC'!$AY19="","",'MGD PC'!BD19) -> 0 | G246: =IF('MGD PC'!$AY19="","",'MGD PC'!BE19) -> 0 | H246: =IF('MGD PC'!$AY19="","",'MGD PC'!BF19) -> 0 | ... N246: =IF('MGD PC'!$AY19="","",'MGD PC'!BL19)
A247: =IF('MGD PC'!$AY20="","",'MGD PC'!AY20) -> MGD PC | B247: =IF('MGD PC'!$AY20="","",'MGD PC'!AZ20) -> 0 | C247: =IF('MGD PC'!$AY20="","",'MGD PC'!BA20) -> 0 | D247: =IF('MGD PC'!$AY20="","",'MGD PC'!BB20) -> 0 | E247: =IF('MGD PC'!$AY20="","",'MGD PC'!BC20) -> 0 | F247: =IF('MGD PC'!$AY20="","",'MGD PC'!BD20) -> 0 | G247: =IF('MGD PC'!$AY20="","",'MGD PC'!BE20) -> 0 | H247: =IF('MGD PC'!$AY20="","",'MGD PC'!BF20) -> 0 | ... N247: =IF('MGD PC'!$AY20="","",'MGD PC'!BL20)
A248: =IF('MGD PC'!$AY21="","",'MGD PC'!AY21) -> MGD PC | B248: =IF('MGD PC'!$AY21="","",'MGD PC'!AZ21) -> 0 | C248: =IF('MGD PC'!$AY21="","",'MGD PC'!BA21) -> 0 | D248: =IF('MGD PC'!$AY21="","",'MGD PC'!BB21) -> 0 | E248: =IF('MGD PC'!$AY21="","",'MGD PC'!BC21) -> 0 | F248: =IF('MGD PC'!$AY21="","",'MGD PC'!BD21) -> 0 | G248: =IF('MGD PC'!$AY21="","",'MGD PC'!BE21) -> 0 | H248: =IF('MGD PC'!$AY21="","",'MGD PC'!BF21) -> 0 | ... N248: =IF('MGD PC'!$AY21="","",'MGD PC'!BL21)
A249: =IF('MGD PC'!$AY22="","",'MGD PC'!AY22) -> MGD PC | B249: =IF('MGD PC'!$AY22="","",'MGD PC'!AZ22) -> 0 | C249: =IF('MGD PC'!$AY22="","",'MGD PC'!BA22) -> 0 | D249: =IF('MGD PC'!$AY22="","",'MGD PC'!BB22) -> 0 | E249: =IF('MGD PC'!$AY22="","",'MGD PC'!BC22) -> 0 | F249: =IF('MGD PC'!$AY22="","",'MGD PC'!BD22) -> 0 | G249: =IF('MGD PC'!$AY22="","",'MGD PC'!BE22) -> 0 | H249: =IF('MGD PC'!$AY22="","",'MGD PC'!BF22) -> 0 | ... N249: =IF('MGD PC'!$AY22="","",'MGD PC'!BL22)
A250: =IF('MGD PC'!$AY23="","",'MGD PC'!AY23) -> MGD PC | B250: =IF('MGD PC'!$AY23="","",'MGD PC'!AZ23) -> 0 | C250: =IF('MGD PC'!$AY23="","",'MGD PC'!BA23) -> 0 | D250: =IF('MGD PC'!$AY23="","",'MGD PC'!BB23) -> 0 | E250: =IF('MGD PC'!$AY23="","",'MGD PC'!BC23) -> 0 | F250: =IF('MGD PC'!$AY23="","",'MGD PC'!BD23) -> 0 | G250: =IF('MGD PC'!$AY23="","",'MGD PC'!BE23) -> 0 | H250: =IF('MGD PC'!$AY23="","",'MGD PC'!BF23) -> 0 | ... N250: =IF('MGD PC'!$AY23="","",'MGD PC'!BL23)
A251: =IF('MGD PC'!$AY24="","",'MGD PC'!AY24) -> MGD PC | B251: =IF('MGD PC'!$AY24="","",'MGD PC'!AZ24) -> 0 | C251: =IF('MGD PC'!$AY24="","",'MGD PC'!BA24) -> 0 | D251: =IF('MGD PC'!$AY24="","",'MGD PC'!BB24) -> 0 | E251: =IF('MGD PC'!$AY24="","",'MGD PC'!BC24) -> 0 | F251: =IF('MGD PC'!$AY24="","",'MGD PC'!BD24) -> 0 | G251: =IF('MGD PC'!$AY24="","",'MGD PC'!BE24) -> 0 | H251: =IF('MGD PC'!$AY24="","",'MGD PC'!BF24) -> 0 | ... N251: =IF('MGD PC'!$AY24="","",'MGD PC'!BL24)
